Workbook

Sheet Introduction
B2: Workbook Overview: Excel_Demo.xlsx
B4: This workbook contains 12 worksheets covering various business operations, from sales and payroll to inventory and client management. Here's a detailed breakdown:
B6: 📋 Worksheet Summary
B8: # | C8: Sheet Name | D8: Rows × Cols | E8: Key Columns | F8: Purpose
B9: 1 | C9: Formula | D9: 17 × 13 | E9: OrderID, CustomerName, Email, Product, Category, Price, Quantity | F9: Order management with lookup areas (J-M columns) for practicing formulas like VLOOKUP/XLOOKUP
B10: 2 | C10: Email_Data | D10: 41 × 6 | E10: Client_ID, Client_Name, Email, Course, Fee_Status, Enrollment_Date | F10: Client enrollment tracking; useful for generating payment reminders and follow-up emails
B11: 3 | C11: Raw_Messy_Data | D11: 45 × 3 | E11: Name, City, Sales | F11: Data cleaning practice—contains inconsistent spacing, case variations, and duplicates
B12: 4 | C12: Payroll_Data | D12: 41 × 6 | E12: Emp_ID, Employee_Name, Department, Basic_Salary, Bonus, Deductions | F12: Payroll processing and net salary calculations
B13: 5 | C13: Bank_Books | D13: 41 × 3 | E13: Date, Description, Amount | F13: Internal accounting records for bank reconciliation
B14: 6 | C14: Bank_Statement | D14: 41 × 3 | E14: Date, Description, Amount | F14: External bank statement data for reconciliation comparison
B15: 7 | C15: Expenses | D15: 41 × 4 | E15: Date, Category, Description, Amount | F15: Expense tracking by category (Travel, Marketing, Office, Software, Utilities)
B16: 8 | C16: Inventory | D16: 41 × 5 | E16: Item_ID, Item_Name, Stock_Available, Reorder_Level, Supplier | F16: Inventory management and low-stock alerts
B17: 9 | C17: Client_Followup | D17: 41 × 5 | E17: Client_Name, Company, Last_Contact_Date, Status, Next_Followup | F17: CRM/sales pipeline tracking with follow-up scheduling
B18: 10 | C18: Budget_vs_Actual | D18: 7 × 3 | E18: Department, Budget, Actual | F18: Budget variance analysis by department
B19: 11 | C19: Sales_Data | D19: 401 × 4 | E19: Date, Region, Product, Sales_Amount | F19: Large sales dataset for pivot tables, dashboards, and trend analysis
B20: 12 | C20: Prompts | D20: 35 × 3 | E20: Sheet Name, Topic/Demo, Claude Prompt | F20: Reference sheet with sample prompts and use cases
B22: 🎯 Use Cases by Worksheet
B24: Worksheet | C24: What You Can Do
B25: Formula | C25: Practice lookup formulas (VLOOKUP, XLOOKUP, INDEX-MATCH)
B26: Email_Data | C26: Generate personalized reminder emails for pending payments
B27: Raw_Messy_Data | C27: Clean data: trim spaces, standardize text, remove duplicates
B28: Payroll_Data | C28: Calculate net salaries, create department summaries
B29: Bank_Books + Bank_Statement | C29: Perform bank reconciliation, identify unmatched transactions
B30: Expenses | C30: Analyze spending by category, create monthly expense reports
B31: Inventory | C31: Identify low-stock items, generate reorder alerts
B32: Client_Followup | C32: Track sales pipeline, identify upcoming follow-ups
B33: Budget_vs_Actual | C33: Variance analysis, identify over/under-budget departments
B34: Sales_Data | C34: Create dashboards, pivot tables, regional/product analysis
B36: 💡 Quick Insights
B38: Largest dataset: Sales_Data with 400 transactions across 4 regions and 4 products
B39: Data quality issues: Raw_Messy_Data needs cleaning (spacing, capitalization, duplicates)
B40: Reconciliation pair: Bank_Books and Bank_Statement are designed for comparison exercises
B41: Ready-to-use prompts: The Prompts sheet contains 20+ sample tasks you can try
B43: Would you like me to perform any specific analysis or task on any of these worksheets?

Sheet Index
A1: 📑 Workbook Index - Navigation Guide
A2: # | B2: Worksheet Name | C2: Description | D2: Quick Navigate (Ctrl+G)
A3: 1 | B3: Formula | C3: Order management & lookup practice | D3: =HYPERLINK("#Formula!A1","Formula") -> Formula | F3: =_xlfn.FORMULATEXT(D3) -> =HYPERLINK("#Formula!A1","Formula")
A4: 2 | B4: Email_Data | C4: Client enrollment & payment tracking | D4: =HYPERLINK("#Email_Data!A1","Email_Data") -> Email_Data | F4: =_xlfn.FORMULATEXT(D4) -> =HYPERLINK("#Email_Data!A1","Email_Data")
A5: 3 | B5: Raw_Messy_Data | C5: Data cleaning practice | D5: =HYPERLINK("#Raw_Messy_Data!A1","Raw_Messy_Data") -> Raw_Messy_Data | F5: =_xlfn.FORMULATEXT(D5) -> =HYPERLINK("#Raw_Messy_Data!A1","Raw_Messy_Data")
A6: 4 | B6: Payroll_Data | C6: Employee salary calculations | D6: =HYPERLINK("#Payroll_Data!A1","Payroll_Data") -> Payroll_Data | F6: =_xlfn.FORMULATEXT(D6) -> =HYPERLINK("#Payroll_Data!A1","Payroll_Data")
A7: 5 | B7: Bank_Books | C7: Internal accounting records | D7: =HYPERLINK("#Bank_Books!A1","Bank_Books") -> Bank_Books | F7: =_xlfn.FORMULATEXT(D7) -> =HYPERLINK("#Bank_Books!A1","Bank_Books")
A8: 6 | B8: Bank_Statement | C8: External bank data | D8: =HYPERLINK("#Bank_Statement!A1","Bank_Statement") -> Bank_Statement | F8: =_xlfn.FORMULATEXT(D8) -> =HYPERLINK("#Bank_Statement!A1","Bank_Statement")
A9: 7 | B9: Expenses | C9: Expense tracking by category | D9: =HYPERLINK("#Expenses!A1","Expenses") -> Expenses | F9: =_xlfn.FORMULATEXT(D9) -> =HYPERLINK("#Expenses!A1","Expenses")
A10: 8 | B10: Inventory | C10: Stock management & alerts | D10: =HYPERLINK("#Inventory!A1","Inventory") -> Inventory | F10: =_xlfn.FORMULATEXT(D10) -> =HYPERLINK("#Inventory!A1","Inventory")
A11: 9 | B11: Client_Followup | C11: CRM & sales pipeline | D11: =HYPERLINK("#Client_Followup!A1","Client_Followup") -> Client_Followup | F11: =_xlfn.FORMULATEXT(D11) -> =HYPERLINK("#Client_Followup!A1","Client_Followup")
A12: 10 | B12: Budget_vs_Actual | C12: Budget variance analysis | D12: =HYPERLINK("#Budget_vs_Actual!A1","Budget_vs_Actual") -> Budget_vs_Actual | F12: =_xlfn.FORMULATEXT(D12) -> =HYPERLINK("#Budget_vs_Actual!A1","Budget_vs_Actual")
A13: 11 | B13: Sales_Data | C13: Large sales dataset for analysis | D13: =HYPERLINK("#Sales_Data!A1","Sales_Data") -> Sales_Data | F13: =_xlfn.FORMULATEXT(D13) -> =HYPERLINK("#Sales_Data!A1","Sales_Data")
A14: 12 | B14: Prompts | C14: Sample prompts & use cases | D14: =HYPERLINK("#Prompts!A1","Prompts") -> Prompts | F14: =_xlfn.FORMULATEXT(D14) -> =HYPERLINK("#Prompts!A1","Prompts")
A16: 📌 How to Navigate:
A17: 1️⃣ Click any sheet tab at the bottom of Excel
A18: 2️⃣ Or press Ctrl+G, paste a value from column D, and press Enter
A19: 3️⃣ Or use keyboard: Ctrl+Page Down / Ctrl+Page Up to move between sheets

Sheet Formula
A1: OrderID | B1: CustomerName | C1: Email | D1: Product | E1: Category | F1: Price | G1: Quantity | J1: OrderID | K1: CustomerName | L1: Quantity | M1: Price
A2: ORD10000 | B2: Pooja Bansal | C2: pooja95@gmail.com | D2: Charger | E2: Tech | F2: 78572.14 | G2: 4 | J2: ORD10000 | K2: =_xlfn.XLOOKUP(J2,$A$2:$A$17,$B$2:$B$17,"Not Found") -> Pooja Bansal | L2: =_xlfn.XLOOKUP(J2,$A$2:$A$17,$G$2:$G$17,"") -> 4 | M2: =_xlfn.XLOOKUP(J2,$A$2:$A$17,$F$2:$F$17,"") -> 78572.14
A3: ORD10001 | B3: Sneha Verma | C3: sneha12@gmail.com | D3: Tablet | E3: Electronics | F3: 43393.19 | G3: 3 | J3: ORD10002 | K3: =_xlfn.XLOOKUP(J3,$A$2:$A$17,$B$2:$B$17,"Not Found") -> Arjun Singh | L3: =_xlfn.XLOOKUP(J3,$A$2:$A$17,$G$2:$G$17,"") -> 2 | M3: =_xlfn.XLOOKUP(J3,$A$2:$A$17,$F$2:$F$17,"") -> 38208.78
A4: ORD10002 | B4: Arjun Singh | C4: arjun5@gmail.com | D4: Headphones | E4: Electronics | F4: 38208.78 | G4: 2 | J4: ORD10004 | K4: =_xlfn.XLOOKUP(J4,$A$2:$A$17,$B$2:$B$17,"Not Found") -> Neha Gupta | L4: =_xlfn.XLOOKUP(J4,$A$2:$A$17,$G$2:$G$17,"") -> 3 | M4: =_xlfn.XLOOKUP(J4,$A$2:$A$17,$F$2:$F$17,"") -> 73256.56
A5: ORD10003 | B5: Neha Singh | C5: neha3@gmail.com | D5: Headphones | E5: Electronics | F5: 44514.23 | G5: 5 | J5: ORD10006 | K5: =_xlfn.XLOOKUP(J5,$A$2:$A$17,$B$2:$B$17,"Not Found") -> Rohit Arora | L5: =_xlfn.XLOOKUP(J5,$A$2:$A$17,$G$2:$G$17,"") -> 1 | M5: =_xlfn.XLOOKUP(J5,$A$2:$A$17,$F$2:$F$17,"") -> 64501.86
A6: ORD10004 | B6: Neha Gupta | C6: neha60@gmail.com | D6: Mouse | E6: Electronics | F6: 73256.56 | G6: 3 | J6: ORD10008 | K6: =_xlfn.XLOOKUP(J6,$A$2:$A$17,$B$2:$B$17,"Not Found") -> Not Found | L6: =_xlfn.XLOOKUP(J6,$A$2:$A$17,$G$2:$G$17,"") | M6: =_xlfn.XLOOKUP(J6,$A$2:$A$17,$F$2:$F$17,"")
A7: ORD10005 | B7: Meena Sharma | C7: meena84@gmail.com | D7: USB Cable | E7: Tech | F7: 67063.78 | G7: 3 | J7: ORD10010 | K7: =_xlfn.XLOOKUP(J7,$A$2:$A$17,$B$2:$B$17,"Not Found") -> Neha Kapoor | L7: =_xlfn.XLOOKUP(J7,$A$2:$A$17,$G$2:$G$17,"") -> 1 | M7: =_xlfn.XLOOKUP(J7,$A$2:$A$17,$F$2:$F$17,"") -> 69761.1
A8: ORD10006 | B8: Rohit Arora | C8: rohit138@gmail.com | D8: Monitor | E8: Electronics | F8: 64501.86 | G8: 1 | J8: ORD10012 | K8: =_xlfn.XLOOKUP(J8,$A$2:$A$17,$B$2:$B$17,"Not Found") -> Arjun Sharma | L8: =_xlfn.XLOOKUP(J8,$A$2:$A$17,$G$2:$G$17,"") -> 5 | M8: =_xlfn.XLOOKUP(J8,$A$2:$A$17,$F$2:$F$17,"") -> 31399.6
A9: ORD10007 | B9: Sneha Verma | C9: sneha180@gmail.com | D9: Monitor | E9: Gadgets | F9: 61418.64 | G9: 1 | J9: ORD10014 | K9: =_xlfn.XLOOKUP(J9,$A$2:$A$17,$B$2:$B$17,"Not Found") -> Anjali Mehta | L9: =_xlfn.XLOOKUP(J9,$A$2:$A$17,$G$2:$G$17,"") -> 2 | M9: =_xlfn.XLOOKUP(J9,$A$2:$A$17,$F$2:$F$17,"") -> 32961.2
A10: ORD10009 | B10: Vikas Gupta | C10: vikas143@gmail.com | D10: Mouse | E10: Gadgets | F10: 5379.97 | G10: 2 | J10: ORD10016 | K10: =_xlfn.XLOOKUP(J10,$A$2:$A$17,$B$2:$B$17,"Not Found") -> Anjali Jain | L10: =_xlfn.XLOOKUP(J10,$A$2:$A$17,$G$2:$G$17,"") -> 4 | M10: =_xlfn.XLOOKUP(J10,$A$2:$A$17,$F$2:$F$17,"") -> 32137.43
A11: ORD10010 | B11: Neha Kapoor | C11: neha49@gmail.com | D11: Charger | E11: Electronics | F11: 69761.1 | G11: 1
A12: ORD10012 | B12: Arjun Sharma | C12: arjun46@gmail.com | D12: USB Cable | E12: Electronics | F12: 31399.6 | G12: 5
A13: ORD10013 | B13: Rohit Jain | C13: rohit42@gmail.com | D13: Tablet | E13: Tech | F13: 18167.94 | G13: 2
A14: ORD10014 | B14: Anjali Mehta | C14: anjali175@gmail.com | D14: Webcam | E14: Electronics | F14: 32961.2 | G14: 2
A15: ORD10015 | B15: Priya Arora | C15: priya199@gmail.com | D15: Webcam | E15: Gadgets | F15: 46556.77 | G15: 4
A16: ORD10016 | B16: Anjali Jain | C16: anjali106@gmail.com | D16: Headphones | E16: Electronics | F16: 32137.43 | G16: 4
A17: ORD10017 | B17: Karan Singh | C17: karan171@gmail.com | D17: Mouse | E17: Electronics | F17: 10041.37 | G17: 1

Sheet Email_Data
A1: Client_ID | B1: Client_Name | C1: Email | D1: Course | E1: Fee_Status | F1: Enrollment_Date | G1: Email_Subject | H1: Email_Body | I1: Followup_Email
A2: 101 | B2: Nikhil Gupta | C2: user1@email.com | D2: Power BI | E2: Pending | F2: 46024 | G2: =IF(E2="Pending","Payment Reminder - "&D2&" Course Fee Due",IF(E2="Paid","Payment Confirmation - "&D2&" Course Fee Received","")) -> Payment Reminder - Power BI Course Fee Due | H2: =IF(E2="Pending","Dear "&B2&","&CHAR(10)&CHAR(10)&"This is a friendly reminder that your fee for the "&D2&" course enrolled on "&TEXT(F2,"YYYY-MM-DD")&" is still pending."&CHAR(10)&CHAR(10)&"Please complete your payment at your earliest convenience to continue uninterrupted access to course materials."&CHAR(10)&CHAR(10)&"If you have already made the payment, please disregard this message."&CHAR(10)&CHAR(10)&"Best regards,"&CHAR(10)&"Training Team",IF(E2="Paid","Dear "&B2&","&CHAR(10)&CHAR(10)&"Thank you for your payment! We are pleased to confirm that your fee for the "&D2&" course enrolled on "&TEXT(F2,"YYYY-MM-DD")&" has been successfully received."&CHAR(10)&CHAR(10)&"You now have full access to all course materials and resources."&CHAR(10)&CHAR(10)&"We wish you the best in your learning journey!"&CHAR(10)&CHAR(10)&"Best regards,"&CHAR(10)&"Training Team","")) -> Dear Nikhil Gupta, This is a friendly reminder that your fee for the Power BI course enrolled on 2026-01-02 is still pending. Please complete your payment at your earliest convenience to continue uninterrupted access to course materials. If you have already made the payment, please disregard this message. Best regards, Training Team | I2: =IF(D2="Advanced Excel","Dear "&B2&", We hope you're enjoying your Advanced Excel course that you enrolled in on "&TEXT(F2,"YYYY-MM-DD")&_xlfn._LONGTEXT(". We wanted to check in on your progress and see if you have any questions about the course material. Our team is here to support your learning journey! Here are some resources you might find helpful: • Access our Excel formula library • Join our weekly"," live Q&A sessions • Download practice worksheets Feel free to reach out if you need any assistance. Best regards, Training Team"),"")
A3: 102 | B3: Arjun Sharma | C3: user2@email.com | D3: GST Mastery | E3: Pending | F3: 46025 | G3: =IF(E3="Pending","Payment Reminder - "&D3&" Course Fee Due",IF(E3="Paid","Payment Confirmation - "&D3&" Course Fee Received","")) -> Payment Reminder - GST Mastery Course Fee Due | H3: =IF(E3="Pending","Dear "&B3&","&CHAR(10)&CHAR(10)&"This is a friendly reminder that your fee for the "&D3&" course enrolled on "&TEXT(F3,"YYYY-MM-DD")&" is still pending."&CHAR(10)&CHAR(10)&"Please complete your payment at your earliest convenience to continue uninterrupted access to course materials."&CHAR(10)&CHAR(10)&"If you have already made the payment, please disregard this message."&CHAR(10)&CHAR(10)&"Best regards,"&CHAR(10)&"Training Team",IF(E3="Paid","Dear "&B3&","&CHAR(10)&CHAR(10)&"Thank you for your payment! We are pleased to confirm that your fee for the "&D3&" course enrolled on "&TEXT(F3,"YYYY-MM-DD")&" has been successfully received."&CHAR(10)&CHAR(10)&"You now have full access to all course materials and resources."&CHAR(10)&CHAR(10)&"We wish you the best in your learning journey!"&CHAR(10)&CHAR(10)&"Best regards,"&CHAR(10)&"Training Team","")) -> Dear Arjun Sharma, This is a friendly reminder that your fee for the GST Mastery course enrolled on 2026-01-03 is still pending. Please complete your payment at your earliest convenience to continue uninterrupted access to course materials. If you have already made the payment, please disregard this message. Best regards, Training Team | I3: =IF(D3="Advanced Excel","Dear "&B3&", We hope you're enjoying your Advanced Excel course that you enrolled in on "&TEXT(F3,"YYYY-MM-DD")&_xlfn._LONGTEXT(". We wanted to check in on your progress and see if you have any questions about the course material. Our team is here to support your learning journey! Here are some resources you might find helpful: • Access our Excel formula library • Join our weekly"," live Q&A sessions • Download practice worksheets Feel free to reach out if you need any assistance. Best regards, Training Team"),"")
A4: 103 | B4: Deepak Verma | C4: user3@email.com | D4: Tally Prime | E4: Pending | F4: 46026 | G4: =IF(E4="Pending","Payment Reminder - "&D4&" Course Fee Due",IF(E4="Paid","Payment Confirmation - "&D4&" Course Fee Received","")) -> Payment Reminder - Tally Prime Course Fee Due | H4: =IF(E4="Pending","Dear "&B4&","&CHAR(10)&CHAR(10)&"This is a friendly reminder that your fee for the "&D4&" course enrolled on "&TEXT(F4,"YYYY-MM-DD")&" is still pending."&CHAR(10)&CHAR(10)&"Please complete your payment at your earliest convenience to continue uninterrupted access to course materials."&CHAR(10)&CHAR(10)&"If you have already made the payment, please disregard this message."&CHAR(10)&CHAR(10)&"Best regards,"&CHAR(10)&"Training Team",IF(E4="Paid","Dear "&B4&","&CHAR(10)&CHAR(10)&"Thank you for your payment! We are pleased to confirm that your fee for the "&D4&" course enrolled on "&TEXT(F4,"YYYY-MM-DD")&" has been successfully received."&CHAR(10)&CHAR(10)&"You now have full access to all course materials and resources."&CHAR(10)&CHAR(10)&"We wish you the best in your learning journey!"&CHAR(10)&CHAR(10)&"Best regards,"&CHAR(10)&"Training Team","")) -> Dear Deepak Verma, This is a friendly reminder that your fee for the Tally Prime course enrolled on 2026-01-04 is still pending. Please complete your payment at your earliest convenience to continue uninterrupted access to course materials. If you have already made the payment, please disregard this message. Best regards, Training Team | I4: =IF(D4="Advanced Excel","Dear "&B4&", We hope you're enjoying your Advanced Excel course that you enrolled in on "&TEXT(F4,"YYYY-MM-DD")&_xlfn._LONGTEXT(". We wanted to check in on your progress and see if you have any questions about the course material. Our team is here to support your learning journey! Here are some resources you might find helpful: • Access our Excel formula library • Join our weekly"," live Q&A sessions • Download practice worksheets Feel free to reach out if you need any assistance. Best regards, Training Team"),"")
A5: 104 | B5: Rahul Gupta | C5: user4@email.com | D5: Power BI | E5: Pending | F5: 46027 | G5: =IF(E5="Pending","Payment Reminder - "&D5&" Course Fee Due",IF(E5="Paid","Payment Confirmation - "&D5&" Course Fee Received","")) -> Payment Reminder - Power BI Course Fee Due | H5: =IF(E5="Pending","Dear "&B5&","&CHAR(10)&CHAR(10)&"This is a friendly reminder that your fee for the "&D5&" course enrolled on "&TEXT(F5,"YYYY-MM-DD")&" is still pending."&CHAR(10)&CHAR(10)&"Please complete your payment at your earliest convenience to continue uninterrupted access to course materials."&CHAR(10)&CHAR(10)&"If you have already made the payment, please disregard this message."&CHAR(10)&CHAR(10)&"Best regards,"&CHAR(10)&"Training Team",IF(E5="Paid","Dear "&B5&","&CHAR(10)&CHAR(10)&"Thank you for your payment! We are pleased to confirm that your fee for the "&D5&" course enrolled on "&TEXT(F5,"YYYY-MM-DD")&" has been successfully received."&CHAR(10)&CHAR(10)&"You now have full access to all course materials and resources."&CHAR(10)&CHAR(10)&"We wish you the best in your learning journey!"&CHAR(10)&CHAR(10)&"Best regards,"&CHAR(10)&"Training Team","")) -> Dear Rahul Gupta, This is a friendly reminder that your fee for the Power BI course enrolled on 2026-01-05 is still pending. Please complete your payment at your earliest convenience to continue uninterrupted access to course materials. If you have already made the payment, please disregard this message. Best regards, Training Team | I5: =IF(D5="Advanced Excel","Dear "&B5&", We hope you're enjoying your Advanced Excel course that you enrolled in on "&TEXT(F5,"YYYY-MM-DD")&_xlfn._LONGTEXT(". We wanted to check in on your progress and see if you have any questions about the course material. Our team is here to support your learning journey! Here are some resources you might find helpful: • Access our Excel formula library • Join our weekly"," live Q&A sessions • Download practice worksheets Feel free to reach out if you need any assistance. Best regards, Training Team"),"")
A6: 105 | B6: Neha Singh | C6: user5@email.com | D6: Advanced Excel | E6: Pending | F6: 46028 | G6: =IF(E6="Pending","Payment Reminder - "&D6&" Course Fee Due",IF(E6="Paid","Payment Confirmation - "&D6&" Course Fee Received","")) -> Payment Reminder - Advanced Excel Course Fee Due | H6: =IF(E6="Pending","Dear "&B6&","&CHAR(10)&CHAR(10)&"This is a friendly reminder that your fee for the "&D6&" course enrolled on "&TEXT(F6,"YYYY-MM-DD")&" is still pending."&CHAR(10)&CHAR(10)&"Please complete your payment at your earliest convenience to continue uninterrupted access to course materials."&CHAR(10)&CHAR(10)&"If you have already made the payment, please disregard this message."&CHAR(10)&CHAR(10)&"Best regards,"&CHAR(10)&"Training Team",IF(E6="Paid","Dear "&B6&","&CHAR(10)&CHAR(10)&"Thank you for your payment! We are pleased to confirm that your fee for the "&D6&" course enrolled on "&TEXT(F6,"YYYY-MM-DD")&" has been successfully received."&CHAR(10)&CHAR(10)&"You now have full access to all course materials and resources."&CHAR(10)&CHAR(10)&"We wish you the best in your learning journey!"&CHAR(10)&CHAR(10)&"Best regards,"&CHAR(10)&"Training Team","")) -> Dear Neha Singh, This is a friendly reminder that your fee for the Advanced Excel course enrolled on 2026-01-06 is still pending. Please complete your payment at your earliest convenience to continue uninterrupted access to course materials. If you have already made the payment, please disregard this message. Best regards, Training Team | I6: =IF(D6="Advanced Excel","Dear "&B6&", We hope you're enjoying your Advanced Excel course that you enrolled in on "&TEXT(F6,"YYYY-MM-DD")&_xlfn._LONGTEXT(". We wanted to check in on your progress and see if you have any questions about the course material. Our team is here to support your learning journey! Here are some resources you might find helpful: • Access our Excel formula library • Join our weekly"," live Q&A sessions • Download practice worksheets Feel free to reach out if you need any assistance. Best regards, Training Team"),"") -> Dear Neha Singh, We hope you're enjoying your Advanced Excel course that you enrolled in on 2026-01-06. We wanted to check in on your progress and see if you have any questions about the course material. Our team is here to support your learning journey! Here are some resources you might find helpful: • Access our Excel formula library • Join our weekly live Q&A sessions • Download practice worksheets Feel free to reach out if you need any assistance. Best regards, Training Team
A7: 106 | B7: Deepak Gupta | C7: user6@email.com | D7: Tally Prime | E7: Paid | F7: 46029 | G7: =IF(E7="Pending","Payment Reminder - "&D7&" Course Fee Due",IF(E7="Paid","Payment Confirmation - "&D7&" Course Fee Received","")) -> Payment Confirmation - Tally Prime Course Fee Received | H7: =IF(E7="Pending","Dear "&B7&","&CHAR(10)&CHAR(10)&"This is a friendly reminder that your fee for the "&D7&" course enrolled on "&TEXT(F7,"YYYY-MM-DD")&" is still pending."&CHAR(10)&CHAR(10)&"Please complete your payment at your earliest convenience to continue uninterrupted access to course materials."&CHAR(10)&CHAR(10)&"If you have already made the payment, please disregard this message."&CHAR(10)&CHAR(10)&"Best regards,"&CHAR(10)&"Training Team",IF(E7="Paid","Dear "&B7&","&CHAR(10)&CHAR(10)&"Thank you for your payment! We are pleased to confirm that your fee for the "&D7&" course enrolled on "&TEXT(F7,"YYYY-MM-DD")&" has been successfully received."&CHAR(10)&CHAR(10)&"You now have full access to all course materials and resources."&CHAR(10)&CHAR(10)&"We wish you the best in your learning journey!"&CHAR(10)&CHAR(10)&"Best regards,"&CHAR(10)&"Training Team","")) -> Dear Deepak Gupta, Thank you for your payment! We are pleased to confirm that your fee for the Tally Prime course enrolled on 2026-01-07 has been successfully received. You now have full access to all course materials and resources. We wish you the best in your learning journey! Best regards, Training Team | I7: =IF(D7="Advanced Excel","Dear "&B7&", We hope you're enjoying your Advanced Excel course that you enrolled in on "&TEXT(F7,"YYYY-MM-DD")&_xlfn._LONGTEXT(". We wanted to check in on your progress and see if you have any questions about the course material. Our team is here to support your learning journey! Here are some resources you might find helpful: • Access our Excel formula library • Join our weekly"," live Q&A sessions • Download practice worksheets Feel free to reach out if you need any assistance. Best regards, Training Team"),"")
A8: 107 | B8: Vikas Singh | C8: user7@email.com | D8: Power BI | E8: Paid | F8: 46030 | G8: =IF(E8="Pending","Payment Reminder - "&D8&" Course Fee Due",IF(E8="Paid","Payment Confirmation - "&D8&" Course Fee Received","")) -> Payment Confirmation - Power BI Course Fee Received | H8: =IF(E8="Pending","Dear "&B8&","&CHAR(10)&CHAR(10)&"This is a friendly reminder that your fee for the "&D8&" course enrolled on "&TEXT(F8,"YYYY-MM-DD")&" is still pending."&CHAR(10)&CHAR(10)&"Please complete your payment at your earliest convenience to continue uninterrupted access to course materials."&CHAR(10)&CHAR(10)&"If you have already made the payment, please disregard this message."&CHAR(10)&CHAR(10)&"Best regards,"&CHAR(10)&"Training Team",IF(E8="Paid","Dear "&B8&","&CHAR(10)&CHAR(10)&"Thank you for your payment! We are pleased to confirm that your fee for the "&D8&" course enrolled on "&TEXT(F8,"YYYY-MM-DD")&" has been successfully received."&CHAR(10)&CHAR(10)&"You now have full access to all course materials and resources."&CHAR(10)&CHAR(10)&"We wish you the best in your learning journey!"&CHAR(10)&CHAR(10)&"Best regards,"&CHAR(10)&"Training Team","")) -> Dear Vikas Singh, Thank you for your payment! We are pleased to confirm that your fee for the Power BI course enrolled on 2026-01-08 has been successfully received. You now have full access to all course materials and resources. We wish you the best in your learning journey! Best regards, Training Team | I8: =IF(D8="Advanced Excel","Dear "&B8&", We hope you're enjoying your Advanced Excel course that you enrolled in on "&TEXT(F8,"YYYY-MM-DD")&_xlfn._LONGTEXT(". We wanted to check in on your progress and see if you have any questions about the course material. Our team is here to support your learning journey! Here are some resources you might find helpful: • Access our Excel formula library • Join our weekly"," live Q&A sessions • Download practice worksheets Feel free to reach out if you need any assistance. Best regards, Training Team"),"")
A9: 108 | B9: Aman Gupta | C9: user8@email.com | D9: Tally Prime | E9: Pending | F9: 46031 | G9: =IF(E9="Pending","Payment Reminder - "&D9&" Course Fee Due",IF(E9="Paid","Payment Confirmation - "&D9&" Course Fee Received","")) -> Payment Reminder - Tally Prime Course Fee Due | H9: =IF(E9="Pending","Dear "&B9&","&CHAR(10)&CHAR(10)&"This is a friendly reminder that your fee for the "&D9&" course enrolled on "&TEXT(F9,"YYYY-MM-DD")&" is still pending."&CHAR(10)&CHAR(10)&"Please complete your payment at your earliest convenience to continue uninterrupted access to course materials."&CHAR(10)&CHAR(10)&"If you have already made the payment, please disregard this message."&CHAR(10)&CHAR(10)&"Best regards,"&CHAR(10)&"Training Team",IF(E9="Paid","Dear "&B9&","&CHAR(10)&CHAR(10)&"Thank you for your payment! We are pleased to confirm that your fee for the "&D9&" course enrolled on "&TEXT(F9,"YYYY-MM-DD")&" has been successfully received."&CHAR(10)&CHAR(10)&"You now have full access to all course materials and resources."&CHAR(10)&CHAR(10)&"We wish you the best in your learning journey!"&CHAR(10)&CHAR(10)&"Best regards,"&CHAR(10)&"Training Team","")) -> Dear Aman Gupta, This is a friendly reminder that your fee for the Tally Prime course enrolled on 2026-01-09 is still pending. Please complete your payment at your earliest convenience to continue uninterrupted access to course materials. If you have already made the payment, please disregard this message. Best regards, Training Team | I9: =IF(D9="Advanced Excel","Dear "&B9&", We hope you're enjoying your Advanced Excel course that you enrolled in on "&TEXT(F9,"YYYY-MM-DD")&_xlfn._LONGTEXT(". We wanted to check in on your progress and see if you have any questions about the course material. Our team is here to support your learning journey! Here are some resources you might find helpful: • Access our Excel formula library • Join our weekly"," live Q&A sessions • Download practice worksheets Feel free to reach out if you need any assistance. Best regards, Training Team"),"")
A10: 109 | B10: Karan Gupta | C10: user9@email.com | D10: GST Mastery | E10: Pending | F10: 46032 | G10: =IF(E10="Pending","Payment Reminder - "&D10&" Course Fee Due",IF(E10="Paid","Payment Confirmation - "&D10&" Course Fee Received","")) -> Payment Reminder - GST Mastery Course Fee Due | H10: =IF(E10="Pending","Dear "&B10&","&CHAR(10)&CHAR(10)&"This is a friendly reminder that your fee for the "&D10&" course enrolled on "&TEXT(F10,"YYYY-MM-DD")&" is still pending."&CHAR(10)&CHAR(10)&"Please complete your payment at your earliest convenience to continue uninterrupted access to course materials."&CHAR(10)&CHAR(10)&"If you have already made the payment, please disregard this message."&CHAR(10)&CHAR(10)&"Best regards,"&CHAR(10)&"Training Team",IF(E10="Paid","Dear "&B10&","&CHAR(10)&CHAR(10)&"Thank you for your payment! We are pleased to confirm that your fee for the "&D10&" course enrolled on "&TEXT(F10,"YYYY-MM-DD")&" has been successfully received."&CHAR(10)&CHAR(10)&"You now have full access to all course materials and resources."&CHAR(10)&CHAR(10)&"We wish you the best in your learning journey!"&CHAR(10)&CHAR(10)&"Best regards,"&CHAR(10)&"Training Team","")) -> Dear Karan Gupta, This is a friendly reminder that your fee for the GST Mastery course enrolled on 2026-01-10 is still pending. Please complete your payment at your earliest convenience to continue uninterrupted access to course materials. If you have already made the payment, please disregard this message. Best regards, Training Team | I10: =IF(D10="Advanced Excel","Dear "&B10&", We hope you're enjoying your Advanced Excel course that you enrolled in on "&TEXT(F10,"YYYY-MM-DD")&_xlfn._LONGTEXT(". We wanted to check in on your progress and see if you have any questions about the course material. Our team is here to support your learning journey! Here are some resources you might find helpful: • Access our Excel formula library • Join our weekly"," live Q&A sessions • Download practice worksheets Feel free to reach out if you need any assistance. Best regards, Training Team"),"")
A11: 110 | B11: Karan Verma | C11: user10@email.com | D11: Advanced Excel | E11: Pending | F11: 46033 | G11: =IF(E11="Pending","Payment Reminder - "&D11&" Course Fee Due",IF(E11="Paid","Payment Confirmation - "&D11&" Course Fee Received","")) -> Payment Reminder - Advanced Excel Course Fee Due | H11: =IF(E11="Pending","Dear "&B11&","&CHAR(10)&CHAR(10)&"This is a friendly reminder that your fee for the "&D11&" course enrolled on "&TEXT(F11,"YYYY-MM-DD")&" is still pending."&CHAR(10)&CHAR(10)&"Please complete your payment at your earliest convenience to continue uninterrupted access to course materials."&CHAR(10)&CHAR(10)&"If you have already made the payment, please disregard this message."&CHAR(10)&CHAR(10)&"Best regards,"&CHAR(10)&"Training Team",IF(E11="Paid","Dear "&B11&","&CHAR(10)&CHAR(10)&"Thank you for your payment! We are pleased to confirm that your fee for the "&D11&" course enrolled on "&TEXT(F11,"YYYY-MM-DD")&" has been successfully received."&CHAR(10)&CHAR(10)&"You now have full access to all course materials and resources."&CHAR(10)&CHAR(10)&"We wish you the best in your learning journey!"&CHAR(10)&CHAR(10)&"Best regards,"&CHAR(10)&"Training Team","")) -> Dear Karan Verma, This is a friendly reminder that your fee for the Advanced Excel course enrolled on 2026-01-11 is still pending. Please complete your payment at your earliest convenience to continue uninterrupted access to course materials. If you have already made the payment, please disregard this message. Best regards, Training Team | I11: =IF(D11="Advanced Excel","Dear "&B11&", We hope you're enjoying your Advanced Excel course that you enrolled in on "&TEXT(F11,"YYYY-MM-DD")&_xlfn._LONGTEXT(". We wanted to check in on your progress and see if you have any questions about the course material. Our team is here to support your learning journey! Here are some resources you might find helpful: • Access our Excel formula library • Join our weekly"," live Q&A sessions • Download practice worksheets Feel free to reach out if you need any assistance. Best regards, Training Team"),"") -> Dear Karan Verma, We hope you're enjoying your Advanced Excel course that you enrolled in on 2026-01-11. We wanted to check in on your progress and see if you have any questions about the course material. Our team is here to support your learning journey! Here are some resources you might find helpful: • Access our Excel formula library • Join our weekly live Q&A sessions • Download practice worksheets Feel free to reach out if you need any assistance. Best regards, Training Team
A12: 111 | B12: Priya Gupta | C12: user11@email.com | D12: Power BI | E12: Paid | F12: 46034 | G12: =IF(E12="Pending","Payment Reminder - "&D12&" Course Fee Due",IF(E12="Paid","Payment Confirmation - "&D12&" Course Fee Received","")) -> Payment Confirmation - Power BI Course Fee Received | H12: =IF(E12="Pending","Dear "&B12&","&CHAR(10)&CHAR(10)&"This is a friendly reminder that your fee for the "&D12&" course enrolled on "&TEXT(F12,"YYYY-MM-DD")&" is still pending."&CHAR(10)&CHAR(10)&"Please complete your payment at your earliest convenience to continue uninterrupted access to course materials."&CHAR(10)&CHAR(10)&"If you have already made the payment, please disregard this message."&CHAR(10)&CHAR(10)&"Best regards,"&CHAR(10)&"Training Team",IF(E12="Paid","Dear "&B12&","&CHAR(10)&CHAR(10)&"Thank you for your payment! We are pleased to confirm that your fee for the "&D12&" course enrolled on "&TEXT(F12,"YYYY-MM-DD")&" has been successfully received."&CHAR(10)&CHAR(10)&"You now have full access to all course materials and resources."&CHAR(10)&CHAR(10)&"We wish you the best in your learning journey!"&CHAR(10)&CHAR(10)&"Best regards,"&CHAR(10)&"Training Team","")) -> Dear Priya Gupta, Thank you for your payment! We are pleased to confirm that your fee for the Power BI course enrolled on 2026-01-12 has been successfully received. You now have full access to all course materials and resources. We wish you the best in your learning journey! Best regards, Training Team | I12: =IF(D12="Advanced Excel","Dear "&B12&", We hope you're enjoying your Advanced Excel course that you enrolled in on "&TEXT(F12,"YYYY-MM-DD")&_xlfn._LONGTEXT(". We wanted to check in on your progress and see if you have any questions about the course material. Our team is here to support your learning journey! Here are some resources you might find helpful: • Access our Excel formula library • Join our weekly"," live Q&A sessions • Download practice worksheets Feel free to reach out if you need any assistance. Best regards, Training Team"),"")
A13: 112 | B13: Aman Singh | C13: user12@email.com | D13: GST Mastery | E13: Paid | F13: 46035 | G13: =IF(E13="Pending","Payment Reminder - "&D13&" Course Fee Due",IF(E13="Paid","Payment Confirmation - "&D13&" Course Fee Received","")) -> Payment Confirmation - GST Mastery Course Fee Received | H13: =IF(E13="Pending","Dear "&B13&","&CHAR(10)&CHAR(10)&"This is a friendly reminder that your fee for the "&D13&" course enrolled on "&TEXT(F13,"YYYY-MM-DD")&" is still pending."&CHAR(10)&CHAR(10)&"Please complete your payment at your earliest convenience to continue uninterrupted access to course materials."&CHAR(10)&CHAR(10)&"If you have already made the payment, please disregard this message."&CHAR(10)&CHAR(10)&"Best regards,"&CHAR(10)&"Training Team",IF(E13="Paid","Dear "&B13&","&CHAR(10)&CHAR(10)&"Thank you for your payment! We are pleased to confirm that your fee for the "&D13&" course enrolled on "&TEXT(F13,"YYYY-MM-DD")&" has been successfully received."&CHAR(10)&CHAR(10)&"You now have full access to all course materials and resources."&CHAR(10)&CHAR(10)&"We wish you the best in your learning journey!"&CHAR(10)&CHAR(10)&"Best regards,"&CHAR(10)&"Training Team","")) -> Dear Aman Singh, Thank you for your payment! We are pleased to confirm that your fee for the GST Mastery course enrolled on 2026-01-13 has been successfully received. You now have full access to all course materials and resources. We wish you the best in your learning journey! Best regards, Training Team | I13: =IF(D13="Advanced Excel","Dear "&B13&", We hope you're enjoying your Advanced Excel course that you enrolled in on "&TEXT(F13,"YYYY-MM-DD")&_xlfn._LONGTEXT(". We wanted to check in on your progress and see if you have any questions about the course material. Our team is here to support your learning journey! Here are some resources you might find helpful: • Access our Excel formula library • Join our weekly"," live Q&A sessions • Download practice worksheets Feel free to reach out if you need any assistance. Best regards, Training Team"),"")
... A41: 140 | B41: Simran Singh | C41: user40@email.com | D41: Advanced Excel | E41: Paid | F41: 46063 | G41: =IF(E41="Pending","Payment Reminder - "&D41&" Course Fee Due",IF(E41="Paid","Payment Confirmation - "&D41&" Course Fee Received","")) -> Payment Confirmation - Advanced Excel Course Fee Received | H41: =IF(E41="Pending","Dear "&B41&","&CHAR(10)&CHAR(10)&"This is a friendly reminder that your fee for the "&D41&" course enrolled on "&TEXT(F41,"YYYY-MM-DD")&" is still pending."&CHAR(10)&CHAR(10)&"Please complete your payment at your earliest convenience to continue uninterrupted access to course materials."&CHAR(10)&CHAR(10)&"If you have already made the payment, please disregard this message."&CHAR(10)&CHAR(10)&"Best regards,"&CHAR(10)&"Training Team",IF(E41="Paid","Dear "&B41&","&CHAR(10)&CHAR(10)&"Thank you for your payment! We are pleased to confirm that your fee for the "&D41&" course enrolled on "&TEXT(F41,"YYYY-MM-DD")&" has been successfully received."&CHAR(10)&CHAR(10)&"You now have full access to all course materials and resources."&CHAR(10)&CHAR(10)&"We wish you the best in your learning journey!"&CHAR(10)&CHAR(10)&"Best regards,"&CHAR(10)&"Training Team","")) -> Dear Simran Singh, Thank you for your payment! We are pleased to confirm that your fee for the Advanced Excel course enrolled on 2026-02-10 has been successfully received. You now have full access to all course materials and resources. We wish you the best in your learning journey! Best regards, Training Team | I41: =IF(D41="Advanced Excel","Dear "&B41&", We hope you're enjoying your Advanced Excel course that you enrolled in on "&TEXT(F41,"YYYY-MM-DD")&_xlfn._LONGTEXT(". We wanted to check in on your progress and see if you have any questions about the course material. Our team is here to support your learning journey! Here are some resources you might find helpful: • Access our Excel formula library • Join our weekly"," live Q&A sessions • Download practice worksheets Feel free to reach out if you need any assistance. Best regards, Training Team"),"") -> Dear Simran Singh, We hope you're enjoying your Advanced Excel course that you enrolled in on 2026-02-10. We wanted to check in on your progress and see if you have any questions about the course material. Our team is here to support your learning journey! Here are some resources you might find helpful: • Access our Excel formula library • Join our weekly live Q&A sessions • Download practice worksheets Feel free to reach out if you need any assistance. Best regards, Training Team

Sheet Raw_Messy_Data
A1: Name | B1: City | C1: Sales
A2: Priya | B2: Mumbai | C2: 7801
A3: Rohit | B3: Delhi | C3: 19278
A4: Neha | B4: Bangalore | C4: 11295
A5: Aman | B5: Mumbai | C5: 19200
A6: Rohit | B6: Delhi | C6: 8411
A7: Priya | B7: Mumbai | C7: 13574
A8: Neha | B8: Pune | C8: 7700
A9: Rohit | B9: Mumbai | C9: 12815
A10: Priya | B10: Delhi | C10: 5871
A11: Rohit | B11: Mumbai | C11: 7169
A12: Rohit | B12: Delhi | C12: 5626
A13: Rohit | B13: Pune | C13: 12058
... A41: Rohit | B41: Pune | C41: 11859
A43: 📊 Data Cleaning Summary
A44: Original Records: | B44: 44
A45: Cleaned Records: | B45: 40
A46: Duplicates Removed: | B46: 4
A47: Unique Names: | B47: 4
A48: Unique Cities: | B48: 4
A50: Standardized Cities:
A51: Bangalore, Delhi, Mumbai, Pune

Sheet Payroll_Data
A1: Emp_ID | B1: Employee_Name | C1: Department | D1: Basic_Salary | E1: Bonus | F1: Deductions | G1: Net_Salary
A2: 201 | B2: Anita Singh | C2: IT | D2: 45902 | E2: 5986 | F2: 2200 | G2: =D2+E2-F2 -> 49688
A3: 202 | B3: Rahul Singh | C3: Sales | D3: 53315 | E3: 2868 | F3: 1636 | G3: =D3+E3-F3 -> 54547
A4: 203 | B4: Rohit Singh | C4: Accounts | D4: 40336 | E4: 5556 | F4: 2065 | G4: =D4+E4-F4 -> 43827
A5: 204 | B5: Arjun Verma | C5: HR | D5: 48066 | E5: 2538 | F5: 2166 | G5: =D5+E5-F5 -> 48438
A6: 205 | B6: Priya Singh | C6: Accounts | D6: 57772 | E6: 2192 | F6: 768 | G6: =D6+E6-F6 -> 59196
A7: 206 | B7: Anita Verma | C7: IT | D7: 47690 | E7: 6945 | F7: 1912 | G7: =D7+E7-F7 -> 52723
A8: 207 | B8: Priya Verma | C8: Admin | D8: 44668 | E8: 7649 | F8: 2734 | G8: =D8+E8-F8 -> 49583
A9: 208 | B9: Arjun Kumar | C9: HR | D9: 41888 | E9: 4455 | F9: 1771 | G9: =D9+E9-F9 -> 44572
A10: 209 | B10: Karan Singh | C10: Accounts | D10: 43908 | E10: 6913 | F10: 2077 | G10: =D10+E10-F10 -> 48744
A11: 210 | B11: Nikhil Verma | C11: HR | D11: 36734 | E11: 4610 | F11: 2769 | G11: =D11+E11-F11 -> 38575
A12: 211 | B12: Nikhil Singh | C12: IT | D12: 38287 | E12: 3133 | F12: 2437 | G12: =D12+E12-F12 -> 38983
A13: 212 | B13: Neha Singh | C13: Accounts | D13: 39777 | E13: 7294 | F13: 2153 | G13: =D13+E13-F13 -> 44918
... A41: 240 | B41: Arjun Singh | C41: Admin | D41: 47808 | E41: 4561 | F41: 2892 | G41: =D41+E41-F41 -> 49477

Sheet Payroll_Summary
A1: 📊 Department-Wise Payroll Summary
A3: Department | B3: Employee_Count | C3: Total_Basic_Salary | D3: Total_Bonus | E3: Total_Deductions | F3: Total_Net_Salary | G3: Avg_Net_Salary
A4: Accounts | B4: =COUNTIF(Payroll_Data!C:C,"Accounts") -> 5 | C4: =SUMIF(Payroll_Data!C:C,"Accounts",Payroll_Data!D:D) -> 224259 | D4: =SUMIF(Payroll_Data!C:C,"Accounts",Payroll_Data!E:E) -> 27697 | E4: =SUMIF(Payroll_Data!C:C,"Accounts",Payroll_Data!F:F) -> 7571 | F4: =SUMIF(Payroll_Data!C:C,"Accounts",Payroll_Data!G:G) -> 244385 | G4: =AVERAGEIF(Payroll_Data!C:C,"Accounts",Payroll_Data!G:G) -> 48877
A5: Admin | B5: =COUNTIF(Payroll_Data!C:C,"Admin") -> 6 | C5: =SUMIF(Payroll_Data!C:C,"Admin",Payroll_Data!D:D) -> 275278 | D5: =SUMIF(Payroll_Data!C:C,"Admin",Payroll_Data!E:E) -> 28200 | E5: =SUMIF(Payroll_Data!C:C,"Admin",Payroll_Data!F:F) -> 10706 | F5: =SUMIF(Payroll_Data!C:C,"Admin",Payroll_Data!G:G) -> 292772 | G5: =AVERAGEIF(Payroll_Data!C:C,"Admin",Payroll_Data!G:G) -> 48795.333
A6: HR | B6: =COUNTIF(Payroll_Data!C:C,"HR") -> 8 | C6: =SUMIF(Payroll_Data!C:C,"HR",Payroll_Data!D:D) -> 380929 | D6: =SUMIF(Payroll_Data!C:C,"HR",Payroll_Data!E:E) -> 35706 | E6: =SUMIF(Payroll_Data!C:C,"HR",Payroll_Data!F:F) -> 14754 | F6: =SUMIF(Payroll_Data!C:C,"HR",Payroll_Data!G:G) -> 401881 | G6: =AVERAGEIF(Payroll_Data!C:C,"HR",Payroll_Data!G:G) -> 50235.125
A7: IT | B7: =COUNTIF(Payroll_Data!C:C,"IT") -> 4 | C7: =SUMIF(Payroll_Data!C:C,"IT",Payroll_Data!D:D) -> 165885 | D7: =SUMIF(Payroll_Data!C:C,"IT",Payroll_Data!E:E) -> 19403 | E7: =SUMIF(Payroll_Data!C:C,"IT",Payroll_Data!F:F) -> 7524 | F7: =SUMIF(Payroll_Data!C:C,"IT",Payroll_Data!G:G) -> 177764 | G7: =AVERAGEIF(Payroll_Data!C:C,"IT",Payroll_Data!G:G) -> 44441
A8: Marketing | B8: =COUNTIF(Payroll_Data!C:C,"Marketing") -> 7 | C8: =SUMIF(Payroll_Data!C:C,"Marketing",Payroll_Data!D:D) -> 324483 | D8: =SUMIF(Payroll_Data!C:C,"Marketing",Payroll_Data!E:E) -> 32658 | E8: =SUMIF(Payroll_Data!C:C,"Marketing",Payroll_Data!F:F) -> 11507 | F8: =SUMIF(Payroll_Data!C:C,"Marketing",Payroll_Data!G:G) -> 345634 | G8: =AVERAGEIF(Payroll_Data!C:C,"Marketing",Payroll_Data!G:G) -> 49376.286
A9: Sales | B9: =COUNTIF(Payroll_Data!C:C,"Sales") -> 10 | C9: =SUMIF(Payroll_Data!C:C,"Sales",Payroll_Data!D:D) -> 493427 | D9: =SUMIF(Payroll_Data!C:C,"Sales",Payroll_Data!E:E) -> 43734 | E9: =SUMIF(Payroll_Data!C:C,"Sales",Payroll_Data!F:F) -> 16571 | F9: =SUMIF(Payroll_Data!C:C,"Sales",Payroll_Data!G:G) -> 520590 | G9: =AVERAGEIF(Payroll_Data!C:C,"Sales",Payroll_Data!G:G) -> 52059
A10: GRAND TOTAL | B10: =SUM(B4:B9) -> 40 | C10: =SUM(C4:C9) -> 1864261 | D10: =SUM(D4:D9) -> 187398 | E10: =SUM(E4:E9) -> 68633 | F10: =SUM(F4:F9) -> 1983026 | G10: =AVERAGE(G4:G9) -> 48963.957
A12: 📌 Conditional Formatting Applied:
A13: • Employee Count: Blue data bars show relative department size
A14: • Total Net Salary: Color scale (Red=Low, Yellow=Mid, Green=High)
A15: • Avg Net Salary: Arrow icons (↑ High, → Mid, ↓ Low)

Sheet Bank_Books
A1: Date | B1: Description | C1: Amount
A2: 46023 | B2: Consulting Fee | C2: 21673
A3: 46024 | B3: Consulting Fee | C3: -13047
A4: 46025 | B4: Consulting Fee | C4: 19375
A5: 46026 | B5: Utility Bill | C5: 12429
A6: 46027 | B6: Office Rent | C6: 9070
A7: 46028 | B7: Software Purchase | C7: 15876
A8: 46029 | B8: Client Payment | C8: -7221
A9: 46030 | B9: Client Payment | C9: -2163
A10: 46031 | B10: Utility Bill | C10: -9499
A11: 46032 | B11: Utility Bill | C11: -14246
A12: 46033 | B12: Utility Bill | C12: 8049
A13: 46034 | B13: Office Rent | C13: 12737
... A41: 46062 | B41: Utility Bill | C41: 23021

Sheet Bank_Statement
A1: Date | B1: Description | C1: Amount
A2: 46023 | B2: Client Payment | C2: 10997
A3: 46024 | B3: Office Rent | C3: 19376
A4: 46025 | B4: Office Rent | C4: 18559
A5: 46026 | B5: Client Payment | C5: -7646
A6: 46027 | B6: Office Rent | C6: 2360
A7: 46028 | B7: Client Payment | C7: 17153
A8: 46029 | B8: Utility Bill | C8: -4586
A9: 46030 | B9: Office Rent | C9: -3633
A10: 46031 | B10: Bank Charges | C10: 12001
A11: 46032 | B11: Client Payment | C11: -8247
A12: 46033 | B12: Utility Bill | C12: -11811
A13: 46034 | B13: Client Payment | C13: 18674
... A41: 46062 | B41: Client Payment | C41: 3328

Sheet Bank_Reconciliation
A1: 🏦 Bank Reconciliation Report
A2: Comparison of Bank_Books vs Bank_Statement
A4: 📘 Bank Books (Internal Records) | G4: 📗 Bank Statement (External Records)
A5: Date | B5: Description | C5: Amount | D5: Match_Key | E5: Match_Status | F5: Date_Match | G5: Date | H5: Description | I5: Amount | J5: Match_Key | K5: Match_Status | L5: Date_Match
A6: =Bank_Books!A2 -> 46023 | B6: =Bank_Books!B2 -> Consulting Fee | C6: =Bank_Books!C2 -> 21673 | D6: =TEXT(A6,"YYYY-MM-DD")&"|"&B6&"|"&C6 -> 2026-01-01|Consulting Fee|21673 | E6: =IF(COUNTIF($J$6:$J$45,D6)>0,"✓ Matched","✗ Unmatched") -> ✗ Unmatched | F6: =IF(COUNTIF($G$6:$G$45,A6)>0,"Date exists in Statement","Date not found") -> Date exists in Statement | G6: =Bank_Statement!A2 -> 46023 | H6: =Bank_Statement!B2 -> Client Payment | I6: =Bank_Statement!C2 -> 10997 | J6: =TEXT(G6,"YYYY-MM-DD")&"|"&H6&"|"&I6 -> 2026-01-01|Client Payment|10997 | K6: =IF(COUNTIF($D$6:$D$45,J6)>0,"✓ Matched","✗ Unmatched") -> ✗ Unmatched | L6: =IF(COUNTIF($A$6:$A$45,G6)>0,"Date exists in Books","Date not found") -> Date exists in Books
A7: =Bank_Books!A3 -> 46024 | B7: =Bank_Books!B3 -> Consulting Fee | C7: =Bank_Books!C3 -> -13047 | D7: =TEXT(A7,"YYYY-MM-DD")&"|"&B7&"|"&C7 -> 2026-01-02|Consulting Fee|-13047 | E7: =IF(COUNTIF($J$6:$J$45,D7)>0,"✓ Matched","✗ Unmatched") -> ✗ Unmatched | F7: =IF(COUNTIF($G$6:$G$45,A7)>0,"Date exists in Statement","Date not found") -> Date exists in Statement | G7: =Bank_Statement!A3 -> 46024 | H7: =Bank_Statement!B3 -> Office Rent | I7: =Bank_Statement!C3 -> 19376 | J7: =TEXT(G7,"YYYY-MM-DD")&"|"&H7&"|"&I7 -> 2026-01-02|Office Rent|19376 | K7: =IF(COUNTIF($D$6:$D$45,J7)>0,"✓ Matched","✗ Unmatched") -> ✗ Unmatched | L7: =IF(COUNTIF($A$6:$A$45,G7)>0,"Date exists in Books","Date not found") -> Date exists in Books
A8: =Bank_Books!A4 -> 46025 | B8: =Bank_Books!B4 -> Consulting Fee | C8: =Bank_Books!C4 -> 19375 | D8: =TEXT(A8,"YYYY-MM-DD")&"|"&B8&"|"&C8 -> 2026-01-03|Consulting Fee|19375 | E8: =IF(COUNTIF($J$6:$J$45,D8)>0,"✓ Matched","✗ Unmatched") -> ✗ Unmatched | F8: =IF(COUNTIF($G$6:$G$45,A8)>0,"Date exists in Statement","Date not found") -> Date exists in Statement | G8: =Bank_Statement!A4 -> 46025 | H8: =Bank_Statement!B4 -> Office Rent | I8: =Bank_Statement!C4 -> 18559 | J8: =TEXT(G8,"YYYY-MM-DD")&"|"&H8&"|"&I8 -> 2026-01-03|Office Rent|18559 | K8: =IF(COUNTIF($D$6:$D$45,J8)>0,"✓ Matched","✗ Unmatched") -> ✗ Unmatched | L8: =IF(COUNTIF($A$6:$A$45,G8)>0,"Date exists in Books","Date not found") -> Date exists in Books
A9: =Bank_Books!A5 -> 46026 | B9: =Bank_Books!B5 -> Utility Bill | C9: =Bank_Books!C5 -> 12429 | D9: =TEXT(A9,"YYYY-MM-DD")&"|"&B9&"|"&C9 -> 2026-01-04|Utility Bill|12429 | E9: =IF(COUNTIF($J$6:$J$45,D9)>0,"✓ Matched","✗ Unmatched") -> ✗ Unmatched | F9: =IF(COUNTIF($G$6:$G$45,A9)>0,"Date exists in Statement","Date not found") -> Date exists in Statement | G9: =Bank_Statement!A5 -> 46026 | H9: =Bank_Statement!B5 -> Client Payment | I9: =Bank_Statement!C5 -> -7646 | J9: =TEXT(G9,"YYYY-MM-DD")&"|"&H9&"|"&I9 -> 2026-01-04|Client Payment|-7646 | K9: =IF(COUNTIF($D$6:$D$45,J9)>0,"✓ Matched","✗ Unmatched") -> ✗ Unmatched | L9: =IF(COUNTIF($A$6:$A$45,G9)>0,"Date exists in Books","Date not found") -> Date exists in Books
A10: =Bank_Books!A6 -> 46027 | B10: =Bank_Books!B6 -> Office Rent | C10: =Bank_Books!C6 -> 9070 | D10: =TEXT(A10,"YYYY-MM-DD")&"|"&B10&"|"&C10 -> 2026-01-05|Office Rent|9070 | E10: =IF(COUNTIF($J$6:$J$45,D10)>0,"✓ Matched","✗ Unmatched") -> ✗ Unmatched | F10: =IF(COUNTIF($G$6:$G$45,A10)>0,"Date exists in Statement","Date not found") -> Date exists in Statement | G10: =Bank_Statement!A6 -> 46027 | H10: =Bank_Statement!B6 -> Office Rent | I10: =Bank_Statement!C6 -> 2360 | J10: =TEXT(G10,"YYYY-MM-DD")&"|"&H10&"|"&I10 -> 2026-01-05|Office Rent|2360 | K10: =IF(COUNTIF($D$6:$D$45,J10)>0,"✓ Matched","✗ Unmatched") -> ✗ Unmatched | L10: =IF(COUNTIF($A$6:$A$45,G10)>0,"Date exists in Books","Date not found") -> Date exists in Books
A11: =Bank_Books!A7 -> 46028 | B11: =Bank_Books!B7 -> Software Purchase | C11: =Bank_Books!C7 -> 15876 | D11: =TEXT(A11,"YYYY-MM-DD")&"|"&B11&"|"&C11 -> 2026-01-06|Software Purchase|15876 | E11: =IF(COUNTIF($J$6:$J$45,D11)>0,"✓ Matched","✗ Unmatched") -> ✗ Unmatched | F11: =IF(COUNTIF($G$6:$G$45,A11)>0,"Date exists in Statement","Date not found") -> Date exists in Statement | G11: =Bank_Statement!A7 -> 46028 | H11: =Bank_Statement!B7 -> Client Payment | I11: =Bank_Statement!C7 -> 17153 | J11: =TEXT(G11,"YYYY-MM-DD")&"|"&H11&"|"&I11 -> 2026-01-06|Client Payment|17153 | K11: =IF(COUNTIF($D$6:$D$45,J11)>0,"✓ Matched","✗ Unmatched") -> ✗ Unmatched | L11: =IF(COUNTIF($A$6:$A$45,G11)>0,"Date exists in Books","Date not found") -> Date exists in Books
A12: =Bank_Books!A8 -> 46029 | B12: =Bank_Books!B8 -> Client Payment | C12: =Bank_Books!C8 -> -7221 | D12: =TEXT(A12,"YYYY-MM-DD")&"|"&B12&"|"&C12 -> 2026-01-07|Client Payment|-7221 | E12: =IF(COUNTIF($J$6:$J$45,D12)>0,"✓ Matched","✗ Unmatched") -> ✗ Unmatched | F12: =IF(COUNTIF($G$6:$G$45,A12)>0,"Date exists in Statement","Date not found") -> Date exists in Statement | G12: =Bank_Statement!A8 -> 46029 | H12: =Bank_Statement!B8 -> Utility Bill | I12: =Bank_Statement!C8 -> -4586 | J12: =TEXT(G12,"YYYY-MM-DD")&"|"&H12&"|"&I12 -> 2026-01-07|Utility Bill|-4586 | K12: =IF(COUNTIF($D$6:$D$45,J12)>0,"✓ Matched","✗ Unmatched") -> ✗ Unmatched | L12: =IF(COUNTIF($A$6:$A$45,G12)>0,"Date exists in Books","Date not found") -> Date exists in Books
A13: =Bank_Books!A9 -> 46030 | B13: =Bank_Books!B9 -> Client Payment | C13: =Bank_Books!C9 -> -2163 | D13: =TEXT(A13,"YYYY-MM-DD")&"|"&B13&"|"&C13 -> 2026-01-08|Client Payment|-2163 | E13: =IF(COUNTIF($J$6:$J$45,D13)>0,"✓ Matched","✗ Unmatched") -> ✗ Unmatched | F13: =IF(COUNTIF($G$6:$G$45,A13)>0,"Date exists in Statement","Date not found") -> Date exists in Statement | G13: =Bank_Statement!A9 -> 46030 | H13: =Bank_Statement!B9 -> Office Rent | I13: =Bank_Statement!C9 -> -3633 | J13: =TEXT(G13,"YYYY-MM-DD")&"|"&H13&"|"&I13 -> 2026-01-08|Office Rent|-3633 | K13: =IF(COUNTIF($D$6:$D$45,J13)>0,"✓ Matched","✗ Unmatched") -> ✗ Unmatched | L13: =IF(COUNTIF($A$6:$A$45,G13)>0,"Date exists in Books","Date not found") -> Date exists in Books
A14: =Bank_Books!A10 -> 46031 | B14: =Bank_Books!B10 -> Utility Bill | C14: =Bank_Books!C10 -> -9499 | D14: =TEXT(A14,"YYYY-MM-DD")&"|"&B14&"|"&C14 -> 2026-01-09|Utility Bill|-9499 | E14: =IF(COUNTIF($J$6:$J$45,D14)>0,"✓ Matched","✗ Unmatched") -> ✗ Unmatched | F14: =IF(COUNTIF($G$6:$G$45,A14)>0,"Date exists in Statement","Date not found") -> Date exists in Statement | G14: =Bank_Statement!A10 -> 46031 | H14: =Bank_Statement!B10 -> Bank Charges | I14: =Bank_Statement!C10 -> 12001 | J14: =TEXT(G14,"YYYY-MM-DD")&"|"&H14&"|"&I14 -> 2026-01-09|Bank Charges|12001 | K14: =IF(COUNTIF($D$6:$D$45,J14)>0,"✓ Matched","✗ Unmatched") -> ✗ Unmatched | L14: =IF(COUNTIF($A$6:$A$45,G14)>0,"Date exists in Books","Date not found") -> Date exists in Books
A15: =Bank_Books!A11 -> 46032 | B15: =Bank_Books!B11 -> Utility Bill | C15: =Bank_Books!C11 -> -14246 | D15: =TEXT(A15,"YYYY-MM-DD")&"|"&B15&"|"&C15 -> 2026-01-10|Utility Bill|-14246 | E15: =IF(COUNTIF($J$6:$J$45,D15)>0,"✓ Matched","✗ Unmatched") -> ✗ Unmatched | F15: =IF(COUNTIF($G$6:$G$45,A15)>0,"Date exists in Statement","Date not found") -> Date exists in Statement | G15: =Bank_Statement!A11 -> 46032 | H15: =Bank_Statement!B11 -> Client Payment | I15: =Bank_Statement!C11 -> -8247 | J15: =TEXT(G15,"YYYY-MM-DD")&"|"&H15&"|"&I15 -> 2026-01-10|Client Payment|-8247 | K15: =IF(COUNTIF($D$6:$D$45,J15)>0,"✓ Matched","✗ Unmatched") -> ✗ Unmatched | L15: =IF(COUNTIF($A$6:$A$45,G15)>0,"Date exists in Books","Date not found") -> Date exists in Books
A16: =Bank_Books!A12 -> 46033 | B16: =Bank_Books!B12 -> Utility Bill | C16: =Bank_Books!C12 -> 8049 | D16: =TEXT(A16,"YYYY-MM-DD")&"|"&B16&"|"&C16 -> 2026-01-11|Utility Bill|8049 | E16: =IF(COUNTIF($J$6:$J$45,D16)>0,"✓ Matched","✗ Unmatched") -> ✗ Unmatched | F16: =IF(COUNTIF($G$6:$G$45,A16)>0,"Date exists in Statement","Date not found") -> Date exists in Statement | G16: =Bank_Statement!A12 -> 46033 | H16: =Bank_Statement!B12 -> Utility Bill | I16: =Bank_Statement!C12 -> -11811 | J16: =TEXT(G16,"YYYY-MM-DD")&"|"&H16&"|"&I16 -> 2026-01-11|Utility Bill|-11811 | K16: =IF(COUNTIF($D$6:$D$45,J16)>0,"✓ Matched","✗ Unmatched") -> ✗ Unmatched | L16: =IF(COUNTIF($A$6:$A$45,G16)>0,"Date exists in Books","Date not found") -> Date exists in Books
A17: =Bank_Books!A13 -> 46034 | B17: =Bank_Books!B13 -> Office Rent | C17: =Bank_Books!C13 -> 12737 | D17: =TEXT(A17,"YYYY-MM-DD")&"|"&B17&"|"&C17 -> 2026-01-12|Office Rent|12737 | E17: =IF(COUNTIF($J$6:$J$45,D17)>0,"✓ Matched","✗ Unmatched") -> ✗ Unmatched | F17: =IF(COUNTIF($G$6:$G$45,A17)>0,"Date exists in Statement","Date not found") -> Date exists in Statement | G17: =Bank_Statement!A13 -> 46034 | H17: =Bank_Statement!B13 -> Client Payment | I17: =Bank_Statement!C13 -> 18674 | J17: =TEXT(G17,"YYYY-MM-DD")&"|"&H17&"|"&I17 -> 2026-01-12|Client Payment|18674 | K17: =IF(COUNTIF($D$6:$D$45,J17)>0,"✓ Matched","✗ Unmatched") -> ✗ Unmatched | L17: =IF(COUNTIF($A$6:$A$45,G17)>0,"Date exists in Books","Date not found") -> Date exists in Books
... A45: =Bank_Books!A41 -> 46062 | B45: =Bank_Books!B41 -> Utility Bill | C45: =Bank_Books!C41 -> 23021 | D45: =TEXT(A45,"YYYY-MM-DD")&"|"&B45&"|"&C45 -> 2026-02-09|Utility Bill|23021 | E45: =IF(COUNTIF($J$6:$J$45,D45)>0,"✓ Matched","✗ Unmatched") -> ✗ Unmatched | F45: =IF(COUNTIF($G$6:$G$45,A45)>0,"Date exists in Statement","Date not found") -> Date exists in Statement | G45: =Bank_Statement!A41 -> 46062 | H45: =Bank_Statement!B41 -> Client Payment | I45: =Bank_Statement!C41 -> 3328 | J45: =TEXT(G45,"YYYY-MM-DD")&"|"&H45&"|"&I45 -> 2026-02-09|Client Payment|3328 | K45: =IF(COUNTIF($D$6:$D$45,J45)>0,"✓ Matched","✗ Unmatched") -> ✗ Unmatched | L45: =IF(COUNTIF($A$6:$A$45,G45)>0,"Date exists in Books","Date not found") -> Date exists in Books
A48: 📊 Reconciliation Summary
A50: Metric | B50: Value | D50: 📋 Reconciliation Analysis
A51: Total Bank Books Entries | B51: =COUNTA(A6:A45) -> 40
A52: Total Bank Statement Entries | B52: =COUNTA(G6:G45) -> 40 | D52: The Bank Books and Bank Statement contain:
A53: Matched in Bank Books | B53: =COUNTIF(E6:E45,"✓ Matched") -> 0 | D53: • Same date range (Jan 1 - Feb 9, 2026)
A54: Unmatched in Bank Books | B54: =COUNTIF(E6:E45,"✗ Unmatched") -> 40 | D54: • Different transaction descriptions
A55: Matched in Bank Statement | B55: =COUNTIF(K6:K45,"✓ Matched") -> 0 | D55: • Different transaction amounts
A56: Unmatched in Bank Statement | B56: =COUNTIF(K6:K45,"✗ Unmatched") -> 40 | D56: • This indicates two independent record sources
A57: Bank Books Total Amount | B57: =SUM(C6:C45) -> 184616 | D57: • Full reconciliation requires manual review
A58: Bank Statement Total Amount | B58: =SUM(I6:I45) -> 209914
A59: Variance (Books - Statement) | B59: =B57-B58 -> -25298
A60: ⚠️ Unmatched Transactions Details
A62: Note: Transactions are matched based on Date + Description + Amount combination. Unmatched entries may indicate:
A63: • Transactions recorded in one book but not the other
A64: • Timing differences between internal records and bank processing
A65: • Data entry errors or discrepancies in amounts
A66: • Bank charges or fees not recorded in internal books
A69: 📅 Date-wise Amount Comparison
A71: Date | B71: Books Amount | C71: Statement Amount | D71: Difference
A72: =A6 -> 46023 | B72: =C6 -> 21673 | C72: =SUMIF($G$6:$G$45,A72,$I$6:$I$45) -> 10997 | D72: =B72-C72 -> 10676
A73: =A7 -> 46024 | B73: =C7 -> -13047 | C73: =SUMIF($G$6:$G$45,A73,$I$6:$I$45) -> 19376 | D73: =B73-C73 -> -32423
A74: =A8 -> 46025 | B74: =C8 -> 19375 | C74: =SUMIF($G$6:$G$45,A74,$I$6:$I$45) -> 18559 | D74: =B74-C74 -> 816
A75: =A9 -> 46026 | B75: =C9 -> 12429 | C75: =SUMIF($G$6:$G$45,A75,$I$6:$I$45) -> -7646 | D75: =B75-C75 -> 20075
A76: =A10 -> 46027 | B76: =C10 -> 9070 | C76: =SUMIF($G$6:$G$45,A76,$I$6:$I$45) -> 2360 | D76: =B76-C76 -> 6710
A77: =A11 -> 46028 | B77: =C11 -> 15876 | C77: =SUMIF($G$6:$G$45,A77,$I$6:$I$45) -> 17153 | D77: =B77-C77 -> -1277
A78: =A12 -> 46029 | B78: =C12 -> -7221 | C78: =SUMIF($G$6:$G$45,A78,$I$6:$I$45) -> -4586 | D78: =B78-C78 -> -2635
A79: =A13 -> 46030 | B79: =C13 -> -2163 | C79: =SUMIF($G$6:$G$45,A79,$I$6:$I$45) -> -3633 | D79: =B79-C79 -> 1470
A80: =A14 -> 46031 | B80: =C14 -> -9499 | C80: =SUMIF($G$6:$G$45,A80,$I$6:$I$45) -> 12001 | D80: =B80-C80 -> -21500
A81: =A15 -> 46032 | B81: =C15 -> -14246 | C81: =SUMIF($G$6:$G$45,A81,$I$6:$I$45) -> -8247 | D81: =B81-C81 -> -5999
A82: =A16 -> 46033 | B82: =C16 -> 8049 | C82: =SUMIF($G$6:$G$45,A82,$I$6:$I$45) -> -11811 | D82: =B82-C82 -> 19860
A83: =A17 -> 46034 | B83: =C17 -> 12737 | C83: =SUMIF($G$6:$G$45,A83,$I$6:$I$45) -> 18674 | D83: =B83-C83 -> -5937
... A111: =A45 -> 46062 | B111: =C45 -> 23021 | C111: =SUMIF($G$6:$G$45,A111,$I$6:$I$45) -> 3328 | D111: =B111-C111 -> 19693

Sheet Missing_Entries_Report
A1: 📋 Bank Reconciliation - Missing Entries Report
A2: Generated: 29/3/2026
A4: 📘 Missing from Bank Statement (Recorded in Books but NOT in Statement) | G4: 📗 Missing from Bank Books (Recorded in Statement but NOT in Books)
A5: Date | B5: Description | C5: Amount | D5: Match_Key | E5: Status | G5: Date | H5: Description | I5: Amount | J5: Match_Key | K5: Status
A6: 46023 | B6: Consulting Fee | C6: 21673 | D6: =TEXT(A6,"YYYY-MM-DD")&"|"&B6&"|"&C6 -> 2026-01-01|Consulting Fee|21673 | E6: =IF(COUNTIFS(Bank_Statement!A:A,A6,Bank_Statement!B:B,B6,Bank_Statement!C:C,C6)>0,"✓ Found","✗ Missing") -> ✗ Missing | G6: 46023 | H6: Client Payment | I6: 10997 | J6: =TEXT(G6,"YYYY-MM-DD")&"|"&H6&"|"&I6 -> 2026-01-01|Client Payment|10997 | K6: =IF(COUNTIFS(Bank_Books!A:A,G6,Bank_Books!B:B,H6,Bank_Books!C:C,I6)>0,"✓ Found","✗ Missing") -> ✗ Missing
A7: 46024 | B7: Consulting Fee | C7: -13047 | D7: =TEXT(A7,"YYYY-MM-DD")&"|"&B7&"|"&C7 -> 2026-01-02|Consulting Fee|-13047 | E7: =IF(COUNTIFS(Bank_Statement!A:A,A7,Bank_Statement!B:B,B7,Bank_Statement!C:C,C7)>0,"✓ Found","✗ Missing") -> ✗ Missing | G7: 46024 | H7: Office Rent | I7: 19376 | J7: =TEXT(G7,"YYYY-MM-DD")&"|"&H7&"|"&I7 -> 2026-01-02|Office Rent|19376 | K7: =IF(COUNTIFS(Bank_Books!A:A,G7,Bank_Books!B:B,H7,Bank_Books!C:C,I7)>0,"✓ Found","✗ Missing") -> ✗ Missing
A8: 46025 | B8: Consulting Fee | C8: 19375 | D8: =TEXT(A8,"YYYY-MM-DD")&"|"&B8&"|"&C8 -> 2026-01-03|Consulting Fee|19375 | E8: =IF(COUNTIFS(Bank_Statement!A:A,A8,Bank_Statement!B:B,B8,Bank_Statement!C:C,C8)>0,"✓ Found","✗ Missing") -> ✗ Missing | G8: 46025 | H8: Office Rent | I8: 18559 | J8: =TEXT(G8,"YYYY-MM-DD")&"|"&H8&"|"&I8 -> 2026-01-03|Office Rent|18559 | K8: =IF(COUNTIFS(Bank_Books!A:A,G8,Bank_Books!B:B,H8,Bank_Books!C:C,I8)>0,"✓ Found","✗ Missing") -> ✗ Missing
A9: 46026 | B9: Utility Bill | C9: 12429 | D9: =TEXT(A9,"YYYY-MM-DD")&"|"&B9&"|"&C9 -> 2026-01-04|Utility Bill|12429 | E9: =IF(COUNTIFS(Bank_Statement!A:A,A9,Bank_Statement!B:B,B9,Bank_Statement!C:C,C9)>0,"✓ Found","✗ Missing") -> ✗ Missing | G9: 46026 | H9: Client Payment | I9: -7646 | J9: =TEXT(G9,"YYYY-MM-DD")&"|"&H9&"|"&I9 -> 2026-01-04|Client Payment|-7646 | K9: =IF(COUNTIFS(Bank_Books!A:A,G9,Bank_Books!B:B,H9,Bank_Books!C:C,I9)>0,"✓ Found","✗ Missing") -> ✗ Missing
A10: 46027 | B10: Office Rent | C10: 9070 | D10: =TEXT(A10,"YYYY-MM-DD")&"|"&B10&"|"&C10 -> 2026-01-05|Office Rent|9070 | E10: =IF(COUNTIFS(Bank_Statement!A:A,A10,Bank_Statement!B:B,B10,Bank_Statement!C:C,C10)>0,"✓ Found","✗ Missing") -> ✗ Missing | G10: 46027 | H10: Office Rent | I10: 2360 | J10: =TEXT(G10,"YYYY-MM-DD")&"|"&H10&"|"&I10 -> 2026-01-05|Office Rent|2360 | K10: =IF(COUNTIFS(Bank_Books!A:A,G10,Bank_Books!B:B,H10,Bank_Books!C:C,I10)>0,"✓ Found","✗ Missing") -> ✗ Missing
A11: 46028 | B11: Software Purchase | C11: 15876 | D11: =TEXT(A11,"YYYY-MM-DD")&"|"&B11&"|"&C11 -> 2026-01-06|Software Purchase|15876 | E11: =IF(COUNTIFS(Bank_Statement!A:A,A11,Bank_Statement!B:B,B11,Bank_Statement!C:C,C11)>0,"✓ Found","✗ Missing") -> ✗ Missing | G11: 46028 | H11: Client Payment | I11: 17153 | J11: =TEXT(G11,"YYYY-MM-DD")&"|"&H11&"|"&I11 -> 2026-01-06|Client Payment|17153 | K11: =IF(COUNTIFS(Bank_Books!A:A,G11,Bank_Books!B:B,H11,Bank_Books!C:C,I11)>0,"✓ Found","✗ Missing") -> ✗ Missing
A12: 46029 | B12: Client Payment | C12: -7221 | D12: =TEXT(A12,"YYYY-MM-DD")&"|"&B12&"|"&C12 -> 2026-01-07|Client Payment|-7221 | E12: =IF(COUNTIFS(Bank_Statement!A:A,A12,Bank_Statement!B:B,B12,Bank_Statement!C:C,C12)>0,"✓ Found","✗ Missing") -> ✗ Missing | G12: 46029 | H12: Utility Bill | I12: -4586 | J12: =TEXT(G12,"YYYY-MM-DD")&"|"&H12&"|"&I12 -> 2026-01-07|Utility Bill|-4586 | K12: =IF(COUNTIFS(Bank_Books!A:A,G12,Bank_Books!B:B,H12,Bank_Books!C:C,I12)>0,"✓ Found","✗ Missing") -> ✗ Missing
A13: 46030 | B13: Client Payment | C13: -2163 | D13: =TEXT(A13,"YYYY-MM-DD")&"|"&B13&"|"&C13 -> 2026-01-08|Client Payment|-2163 | E13: =IF(COUNTIFS(Bank_Statement!A:A,A13,Bank_Statement!B:B,B13,Bank_Statement!C:C,C13)>0,"✓ Found","✗ Missing") -> ✗ Missing | G13: 46030 | H13: Office Rent | I13: -3633 | J13: =TEXT(G13,"YYYY-MM-DD")&"|"&H13&"|"&I13 -> 2026-01-08|Office Rent|-3633 | K13: =IF(COUNTIFS(Bank_Books!A:A,G13,Bank_Books!B:B,H13,Bank_Books!C:C,I13)>0,"✓ Found","✗ Missing") -> ✗ Missing
A14: 46031 | B14: Utility Bill | C14: -9499 | D14: =TEXT(A14,"YYYY-MM-DD")&"|"&B14&"|"&C14 -> 2026-01-09|Utility Bill|-9499 | E14: =IF(COUNTIFS(Bank_Statement!A:A,A14,Bank_Statement!B:B,B14,Bank_Statement!C:C,C14)>0,"✓ Found","✗ Missing") -> ✗ Missing | G14: 46031 | H14: Bank Charges | I14: 12001 | J14: =TEXT(G14,"YYYY-MM-DD")&"|"&H14&"|"&I14 -> 2026-01-09|Bank Charges|12001 | K14: =IF(COUNTIFS(Bank_Books!A:A,G14,Bank_Books!B:B,H14,Bank_Books!C:C,I14)>0,"✓ Found","✗ Missing") -> ✗ Missing
A15: 46032 | B15: Utility Bill | C15: -14246 | D15: =TEXT(A15,"YYYY-MM-DD")&"|"&B15&"|"&C15 -> 2026-01-10|Utility Bill|-14246 | E15: =IF(COUNTIFS(Bank_Statement!A:A,A15,Bank_Statement!B:B,B15,Bank_Statement!C:C,C15)>0,"✓ Found","✗ Missing") -> ✗ Missing | G15: 46032 | H15: Client Payment | I15: -8247 | J15: =TEXT(G15,"YYYY-MM-DD")&"|"&H15&"|"&I15 -> 2026-01-10|Client Payment|-8247 | K15: =IF(COUNTIFS(Bank_Books!A:A,G15,Bank_Books!B:B,H15,Bank_Books!C:C,I15)>0,"✓ Found","✗ Missing") -> ✗ Missing
A16: 46033 | B16: Utility Bill | C16: 8049 | D16: =TEXT(A16,"YYYY-MM-DD")&"|"&B16&"|"&C16 -> 2026-01-11|Utility Bill|8049 | E16: =IF(COUNTIFS(Bank_Statement!A:A,A16,Bank_Statement!B:B,B16,Bank_Statement!C:C,C16)>0,"✓ Found","✗ Missing") -> ✗ Missing | G16: 46033 | H16: Utility Bill | I16: -11811 | J16: =TEXT(G16,"YYYY-MM-DD")&"|"&H16&"|"&I16 -> 2026-01-11|Utility Bill|-11811 | K16: =IF(COUNTIFS(Bank_Books!A:A,G16,Bank_Books!B:B,H16,Bank_Books!C:C,I16)>0,"✓ Found","✗ Missing") -> ✗ Missing
A17: 46034 | B17: Office Rent | C17: 12737 | D17: =TEXT(A17,"YYYY-MM-DD")&"|"&B17&"|"&C17 -> 2026-01-12|Office Rent|12737 | E17: =IF(COUNTIFS(Bank_Statement!A:A,A17,Bank_Statement!B:B,B17,Bank_Statement!C:C,C17)>0,"✓ Found","✗ Missing") -> ✗ Missing | G17: 46034 | H17: Client Payment | I17: 18674 | J17: =TEXT(G17,"YYYY-MM-DD")&"|"&H17&"|"&I17 -> 2026-01-12|Client Payment|18674 | K17: =IF(COUNTIFS(Bank_Books!A:A,G17,Bank_Books!B:B,H17,Bank_Books!C:C,I17)>0,"✓ Found","✗ Missing") -> ✗ Missing
... A45: 46062 | B45: Utility Bill | C45: 23021 | D45: =TEXT(A45,"YYYY-MM-DD")&"|"&B45&"|"&C45 -> 2026-02-09|Utility Bill|23021 | E45: =IF(COUNTIFS(Bank_Statement!A:A,A45,Bank_Statement!B:B,B45,Bank_Statement!C:C,C45)>0,"✓ Found","✗ Missing") -> ✗ Missing | G45: 46062 | H45: Client Payment | I45: 3328 | J45: =TEXT(G45,"YYYY-MM-DD")&"|"&H45&"|"&I45 -> 2026-02-09|Client Payment|3328 | K45: =IF(COUNTIFS(Bank_Books!A:A,G45,Bank_Books!B:B,H45,Bank_Books!C:C,I45)>0,"✓ Found","✗ Missing") -> ✗ Missing
A48: 📊 Reconciliation Summary
A49: Metric | B49: Value
A50: Total Bank Books Entries | B50: =COUNTA(A6:A45) -> 40
A51: Total Bank Statement Entries | B51: =COUNTA(G6:G45) -> 40
A52: Missing from Statement (in Books only) | B52: =COUNTIF(E6:E45,"✗ Missing") -> 40
A53: Missing from Books (in Statement only) | B53: =COUNTIF(K6:K45,"✗ Missing") -> 40
A54: Matched Entries | B54: =COUNTIF(E6:E45,"✓ Found") -> 0
A55: Bank Books Total Amount | B55: =SUM(C6:C45) -> 184616
A56: Bank Statement Total Amount | B56: =SUM(I6:I45) -> 209914
A57: Variance (Books - Statement) | B57: =B55-B56 -> -25298

Sheet Expenses
A1: Date | B1: Category | C1: Description | D1: Amount
A2: 46023 | B2: Travel | C2: Expense Item 1 | D2: 4882
A3: 46024 | B3: Travel | C3: Expense Item 2 | D3: 9758
A4: 46025 | B4: Utilities | C4: Expense Item 3 | D4: 2417
A5: 46026 | B5: Marketing | C5: Expense Item 4 | D5: 6640
A6: 46027 | B6: Marketing | C6: Expense Item 5 | D6: 5900
A7: 46028 | B7: Marketing | C7: Expense Item 6 | D7: 1818
A8: 46029 | B8: Marketing | C8: Expense Item 7 | D8: 6877
A9: 46030 | B9: Travel | C9: Expense Item 8 | D9: 1313
A10: 46031 | B10: Travel | C10: Expense Item 9 | D10: 2293
A11: 46032 | B11: Office | C11: Expense Item 10 | D11: 4390
A12: 46033 | B12: Marketing | C12: Expense Item 11 | D12: 4148
A13: 46034 | B13: Utilities | C13: Expense Item 12 | D13: 9112
... A41: 46062 | B41: Software | C41: Expense Item 40 | D41: 2477

Sheet Expense_Summary
A1: 📊 Category-Wise Expense Summary
A2: Generated: 29/3/2026
A4: Category | B4: Transaction_Count | C4: Total_Amount | D4: Avg_Amount | E4: % of Total
A5: Marketing | B5: =COUNTIF(Expenses!B:B,"Marketing") -> 10 | C5: =SUMIF(Expenses!B:B,"Marketing",Expenses!D:D) -> 47046 | D5: =AVERAGEIF(Expenses!B:B,"Marketing",Expenses!D:D) -> 4704.6 | E5: =C5/C$10 -> 0.23376197
A6: Office | B6: =COUNTIF(Expenses!B:B,"Office") -> 6 | C6: =SUMIF(Expenses!B:B,"Office",Expenses!D:D) -> 27138 | D6: =AVERAGEIF(Expenses!B:B,"Office",Expenses!D:D) -> 4523 | E6: =C6/C$10 -> 0.13484318
A7: Software | B7: =COUNTIF(Expenses!B:B,"Software") -> 6 | C7: =SUMIF(Expenses!B:B,"Software",Expenses!D:D) -> 29632 | D7: =AVERAGEIF(Expenses!B:B,"Software",Expenses!D:D) -> 4938.6667 | E7: =C7/C$10 -> 0.14723536
A8: Travel | B8: =COUNTIF(Expenses!B:B,"Travel") -> 13 | C8: =SUMIF(Expenses!B:B,"Travel",Expenses!D:D) -> 74686 | D8: =AVERAGEIF(Expenses!B:B,"Travel",Expenses!D:D) -> 5745.0769 | E8: =C8/C$10 -> 0.3710995
A9: Utilities | B9: =COUNTIF(Expenses!B:B,"Utilities") -> 5 | C9: =SUMIF(Expenses!B:B,"Utilities",Expenses!D:D) -> 22754 | D9: =AVERAGEIF(Expenses!B:B,"Utilities",Expenses!D:D) -> 4550.8 | E9: =C9/C$10 -> 0.11305998
A10: GRAND TOTAL | B10: =SUM(B5:B9) -> 40 | C10: =SUM(C5:C9) -> 201256 | D10: =AVERAGE(Expenses!D:D) -> 5031.4 | E10: =SUM(E5:E9) -> 1
A12: 🏆 Highest Expense Category Analysis
A14: Highest Expense Category: | B14: =INDEX(A5:A9,MATCH(MAX(C5:C9),C5:C9,0)) -> Travel
A15: Total Amount: | B15: =MAX(C5:C9) -> 74686
A16: % of Total Expenses: | B16: =MAX(C5:C9)/C10 -> 0.3710995
A18: 📌 Conditional Formatting Applied:
A19: • Total Amount: Color scale (Red=Low, Yellow=Mid, Green=High)
A20: • Transaction Count: Blue data bars showing relative counts
A21: • % of Total: Arrow icons (↑ High, → Mid, ↓ Low)
A22: • Highest Expense Category: Highlighted in yellow

Sheet Monthly_Expense_Report
A1: 📊 Monthly Expense Report
A2: Generated: 29/3/2026
A4: 📅 Monthly Expense Summary
A6: Month | B6: Transaction_Count | C6: Total_Amount | D6: Avg_Amount | E6: Min_Amount | F6: Max_Amount
A7: 46023 | B7: {=SUMPRODUCT((MONTH(Expenses!A2:A41)=1)*(YEAR(Expenses!A2:A41)=2026)*1)} -> 31 | C7: {=SUMPRODUCT((MONTH(Expenses!A2:A41)=1)*(YEAR(Expenses!A2:A41)=2026)*Expenses!D2:D41)} -> 156226 | D7: =IF(B7>0,C7/B7,0) -> 5039.5484 | E7: =_xlfn.MINIFS(Expenses!D2:D41,Expenses!A2:A41,">="&DATE(2026,1,1),Expenses!A2:A41,"<"&DATE(2026,2,1)) -> 509 | F7: =_xlfn.MAXIFS(Expenses!D2:D41,Expenses!A2:A41,">="&DATE(2026,1,1),Expenses!A2:A41,"<"&DATE(2026,2,1)) -> 9847
A8: 46054 | B8: {=SUMPRODUCT((MONTH(Expenses!A2:A41)=2)*(YEAR(Expenses!A2:A41)=2026)*1)} -> 9 | C8: {=SUMPRODUCT((MONTH(Expenses!A2:A41)=2)*(YEAR(Expenses!A2:A41)=2026)*Expenses!D2:D41)} -> 45030 | D8: =IF(B8>0,C8/B8,0) -> 5003.3333 | E8: =_xlfn.MINIFS(Expenses!D2:D41,Expenses!A2:A41,">="&DATE(2026,2,1),Expenses!A2:A41,"<"&DATE(2026,3,1)) -> 1180 | F8: =_xlfn.MAXIFS(Expenses!D2:D41,Expenses!A2:A41,">="&DATE(2026,2,1),Expenses!A2:A41,"<"&DATE(2026,3,1)) -> 9605
A9: GRAND TOTAL | B9: =SUM(B7:B8) -> 40 | C9: =SUM(C7:C8) -> 201256 | D9: =IF(B9>0,C9/B9,0) -> 5031.4 | E9: =MIN(Expenses!D2:D41) -> 509 | F9: =MAX(Expenses!D2:D41) -> 9847
A11: 📁 Category-Wise Expense Summary
A13: Category | B13: Transaction_Count | C13: Total_Amount | D13: Avg_Amount | E13: % of Total
A14: Marketing | B14: =COUNTIF(Expenses!B:B,"Marketing") -> 10 | C14: =SUMIF(Expenses!B:B,"Marketing",Expenses!D:D) -> 47046 | D14: =AVERAGEIF(Expenses!B:B,"Marketing",Expenses!D:D) -> 4704.6 | E14: =C14/C$19 -> 0.23376197
A15: Office | B15: =COUNTIF(Expenses!B:B,"Office") -> 6 | C15: =SUMIF(Expenses!B:B,"Office",Expenses!D:D) -> 27138 | D15: =AVERAGEIF(Expenses!B:B,"Office",Expenses!D:D) -> 4523 | E15: =C15/C$19 -> 0.13484318
A16: Software | B16: =COUNTIF(Expenses!B:B,"Software") -> 6 | C16: =SUMIF(Expenses!B:B,"Software",Expenses!D:D) -> 29632 | D16: =AVERAGEIF(Expenses!B:B,"Software",Expenses!D:D) -> 4938.6667 | E16: =C16/C$19 -> 0.14723536
A17: Travel | B17: =COUNTIF(Expenses!B:B,"Travel") -> 13 | C17: =SUMIF(Expenses!B:B,"Travel",Expenses!D:D) -> 74686 | D17: =AVERAGEIF(Expenses!B:B,"Travel",Expenses!D:D) -> 5745.0769 | E17: =C17/C$19 -> 0.3710995
A18: Utilities | B18: =COUNTIF(Expenses!B:B,"Utilities") -> 5 | C18: =SUMIF(Expenses!B:B,"Utilities",Expenses!D:D) -> 22754 | D18: =AVERAGEIF(Expenses!B:B,"Utilities",Expenses!D:D) -> 4550.8 | E18: =C18/C$19 -> 0.11305998
A19: GRAND TOTAL | B19: =SUM(B14:B18) -> 40 | C19: =SUM(C14:C18) -> 201256 | D19: =IF(B19>0,C19/B19,0) -> 5031.4 | E19: 1
A21: 🏆 Highest Expense Category Analysis
A23: Highest Expense Category: | B23: =INDEX(A14:A18,MATCH(MAX(C14:C18),C14:C18,0)) -> Travel
A24: Total Amount: | B24: =MAX(C14:C18) -> 74686
A25: Transaction Count: | B25: =INDEX(B14:B18,MATCH(MAX(C14:C18),C14:C18,0)) -> 13
A26: % of Total Expenses: | B26: =MAX(C14:C18)/C19 -> 0.3710995
A27: Average per Transaction: | B27: =INDEX(D14:D18,MATCH(MAX(C14:C18),C14:C18,0)) -> 5745.0769
A29: 📊 Monthly Category Breakdown
A31: Category | B31: Jan Count | C31: Jan Amount | D31: Feb Count | E31: Feb Amount | F31: Total
A32: Marketing | B32: {=SUMPRODUCT((Expenses!B2:B41="Marketing")*(MONTH(Expenses!A2:A41)=1)*(YEAR(Expenses!A2:A41)=2026)*1)} -> 7 | C32: {=SUMPRODUCT((Expenses!B2:B41="Marketing")*(MONTH(Expenses!A2:A41)=1)*(YEAR(Expenses!A2:A41)=2026)*Expenses!D2:D41)} -> 34492 | D32: {=SUMPRODUCT((Expenses!B2:B41="Marketing")*(MONTH(Expenses!A2:A41)=2)*(YEAR(Expenses!A2:A41)=2026)*1)} -> 3 | E32: {=SUMPRODUCT((Expenses!B2:B41="Marketing")*(MONTH(Expenses!A2:A41)=2)*(YEAR(Expenses!A2:A41)=2026)*Expenses!D2:D41)} -> 12554 | F32: =C32+E32 -> 47046
A33: Office | B33: {=SUMPRODUCT((Expenses!B2:B41="Office")*(MONTH(Expenses!A2:A41)=1)*(YEAR(Expenses!A2:A41)=2026)*1)} -> 5 | C33: {=SUMPRODUCT((Expenses!B2:B41="Office")*(MONTH(Expenses!A2:A41)=1)*(YEAR(Expenses!A2:A41)=2026)*Expenses!D2:D41)} -> 25286 | D33: {=SUMPRODUCT((Expenses!B2:B41="Office")*(MONTH(Expenses!A2:A41)=2)*(YEAR(Expenses!A2:A41)=2026)*1)} -> 1 | E33: {=SUMPRODUCT((Expenses!B2:B41="Office")*(MONTH(Expenses!A2:A41)=2)*(YEAR(Expenses!A2:A41)=2026)*Expenses!D2:D41)} -> 1852 | F33: =C33+E33 -> 27138
A34: Software | B34: {=SUMPRODUCT((Expenses!B2:B41="Software")*(MONTH(Expenses!A2:A41)=1)*(YEAR(Expenses!A2:A41)=2026)*1)} -> 5 | C34: {=SUMPRODUCT((Expenses!B2:B41="Software")*(MONTH(Expenses!A2:A41)=1)*(YEAR(Expenses!A2:A41)=2026)*Expenses!D2:D41)} -> 27155 | D34: {=SUMPRODUCT((Expenses!B2:B41="Software")*(MONTH(Expenses!A2:A41)=2)*(YEAR(Expenses!A2:A41)=2026)*1)} -> 1 | E34: {=SUMPRODUCT((Expenses!B2:B41="Software")*(MONTH(Expenses!A2:A41)=2)*(YEAR(Expenses!A2:A41)=2026)*Expenses!D2:D41)} -> 2477 | F34: =C34+E34 -> 29632
A35: Travel | B35: {=SUMPRODUCT((Expenses!B2:B41="Travel")*(MONTH(Expenses!A2:A41)=1)*(YEAR(Expenses!A2:A41)=2026)*1)} -> 9 | C35: {=SUMPRODUCT((Expenses!B2:B41="Travel")*(MONTH(Expenses!A2:A41)=1)*(YEAR(Expenses!A2:A41)=2026)*Expenses!D2:D41)} -> 46539 | D35: {=SUMPRODUCT((Expenses!B2:B41="Travel")*(MONTH(Expenses!A2:A41)=2)*(YEAR(Expenses!A2:A41)=2026)*1)} -> 4 | E35: {=SUMPRODUCT((Expenses!B2:B41="Travel")*(MONTH(Expenses!A2:A41)=2)*(YEAR(Expenses!A2:A41)=2026)*Expenses!D2:D41)} -> 28147 | F35: =C35+E35 -> 74686
A36: Utilities | B36: {=SUMPRODUCT((Expenses!B2:B41="Utilities")*(MONTH(Expenses!A2:A41)=1)*(YEAR(Expenses!A2:A41)=2026)*1)} -> 5 | C36: {=SUMPRODUCT((Expenses!B2:B41="Utilities")*(MONTH(Expenses!A2:A41)=1)*(YEAR(Expenses!A2:A41)=2026)*Expenses!D2:D41)} -> 22754 | D36: {=SUMPRODUCT((Expenses!B2:B41="Utilities")*(MONTH(Expenses!A2:A41)=2)*(YEAR(Expenses!A2:A41)=2026)*1)} -> 0 | E36: {=SUMPRODUCT((Expenses!B2:B41="Utilities")*(MONTH(Expenses!A2:A41)=2)*(YEAR(Expenses!A2:A41)=2026)*Expenses!D2:D41)} -> 0 | F36: =C36+E36 -> 22754
A37: TOTAL | B37: =SUM(B32:B36) -> 31 | C37: =SUM(C32:C36) -> 156226 | D37: =SUM(D32:D36) -> 9 | E37: =SUM(E32:E36) -> 45030 | F37: =SUM(F32:F36) -> 201256
A39: 📌 Conditional Formatting Applied:
A40: • Total Amount (Category): Color scale (Red=Low → Yellow=Mid → Green=High)
A41: • Transaction Count: Blue data bars showing relative counts
A42: • % of Total: Arrow icons (↑ High, → Mid, ↓ Low)
A43: • Highest Category Row: Yellow highlight with bold text
A44: • Monthly Amounts: Orange scale for Jan, Blue scale for Feb

Sheet Inventory
A1: Item_ID | B1: Item_Name | C1: Stock_Available | D1: Reorder_Level | E1: Supplier | F1: Stock_Status
A2: 300 | B2: Item_1 | C2: 35 | D2: 9 | E2: Lenovo | F2: =IF(C2<D2,"⚠️ Low Stock","✓ OK") -> ✓ OK
A3: 301 | B3: Item_2 | C3: 39 | D3: 10 | E3: Epson | F3: =IF(C3<D3,"⚠️ Low Stock","✓ OK") -> ✓ OK
A4: 302 | B4: Item_3 | C4: 22 | D4: 9 | E4: HP | F4: =IF(C4<D4,"⚠️ Low Stock","✓ OK") -> ✓ OK
A5: 303 | B5: Item_4 | C5: 9 | D5: 14 | E5: Samsung | F5: =IF(C5<D5,"⚠️ Low Stock","✓ OK") -> ⚠️ Low Stock
A6: 304 | B6: Item_5 | C6: 5 | D6: 7 | E6: Logitech | F6: =IF(C6<D6,"⚠️ Low Stock","✓ OK") -> ⚠️ Low Stock
A7: 305 | B7: Item_6 | C7: 2 | D7: 14 | E7: Lenovo | F7: =IF(C7<D7,"⚠️ Low Stock","✓ OK") -> ⚠️ Low Stock
A8: 306 | B8: Item_7 | C8: 33 | D8: 7 | E8: Samsung | F8: =IF(C8<D8,"⚠️ Low Stock","✓ OK") -> ✓ OK
A9: 307 | B9: Item_8 | C9: 13 | D9: 7 | E9: Samsung | F9: =IF(C9<D9,"⚠️ Low Stock","✓ OK") -> ✓ OK
A10: 308 | B10: Item_9 | C10: 39 | D10: 10 | E10: Epson | F10: =IF(C10<D10,"⚠️ Low Stock","✓ OK") -> ✓ OK
A11: 309 | B11: Item_10 | C11: 28 | D11: 6 | E11: Logitech | F11: =IF(C11<D11,"⚠️ Low Stock","✓ OK") -> ✓ OK
A12: 310 | B12: Item_11 | C12: 7 | D12: 12 | E12: Epson | F12: =IF(C12<D12,"⚠️ Low Stock","✓ OK") -> ⚠️ Low Stock
A13: 311 | B13: Item_12 | C13: 40 | D13: 11 | E13: HP | F13: =IF(C13<D13,"⚠️ Low Stock","✓ OK") -> ✓ OK
... A41: 339 | B41: Item_40 | C41: 50 | D41: 9 | E41: Samsung | F41: =IF(C41<D41,"⚠️ Low Stock","✓ OK") -> ✓ OK

Sheet Inventory_Summary
A1: 📦 Inventory Summary Report
A2: Generated: 29/3/2026
A4: 📊 Overall Inventory Summary
A6: Metric | B6: Value
A7: Total Items | B7: =COUNTA(Inventory!A2:A41) -> 40
A8: Total Stock Available | B8: =SUM(Inventory!C2:C41) -> 866
A9: Average Stock per Item | B9: =AVERAGE(Inventory!C2:C41) -> 21.65
A10: Low Stock Items (⚠️) | B10: =COUNTIF(Inventory!F2:F41,"⚠️ Low Stock") -> 11
A11: OK Items (✓) | B11: =COUNTIF(Inventory!F2:F41,"✓ OK") -> 29
A12: Low Stock % | B12: =B10/B7 -> 0.275
A13: Min Stock Level | B13: =MIN(Inventory!C2:C41) -> 1
A14: Max Stock Level | B14: =MAX(Inventory!C2:C41) -> 50
A16: 📋 Supplier-wise Inventory Summary
A18: Supplier | B18: Total Items | C18: Total Stock | D18: Low Stock Items | E18: % Low Stock
A19: Dell | B19: =COUNTIF(Inventory!E:E,"Dell") -> 3 | C19: =SUMIF(Inventory!E:E,"Dell",Inventory!C:C) -> 90 | D19: =COUNTIFS(Inventory!E:E,"Dell",Inventory!F:F,"⚠️ Low Stock") -> 0 | E19: =IF(B19>0,D19/B19,0) -> 0
A20: Epson | B20: =COUNTIF(Inventory!E:E,"Epson") -> 11 | C20: =SUMIF(Inventory!E:E,"Epson",Inventory!C:C) -> 258 | D20: =COUNTIFS(Inventory!E:E,"Epson",Inventory!F:F,"⚠️ Low Stock") -> 3 | E20: =IF(B20>0,D20/B20,0) -> 0.27272727
A21: HP | B21: =COUNTIF(Inventory!E:E,"HP") -> 8 | C21: =SUMIF(Inventory!E:E,"HP",Inventory!C:C) -> 138 | D21: =COUNTIFS(Inventory!E:E,"HP",Inventory!F:F,"⚠️ Low Stock") -> 3 | E21: =IF(B21>0,D21/B21,0) -> 0.375
A22: Lenovo | B22: =COUNTIF(Inventory!E:E,"Lenovo") -> 4 | C22: =SUMIF(Inventory!E:E,"Lenovo",Inventory!C:C) -> 59 | D22: =COUNTIFS(Inventory!E:E,"Lenovo",Inventory!F:F,"⚠️ Low Stock") -> 2 | E22: =IF(B22>0,D22/B22,0) -> 0.5
A23: Logitech | B23: =COUNTIF(Inventory!E:E,"Logitech") -> 5 | C23: =SUMIF(Inventory!E:E,"Logitech",Inventory!C:C) -> 84 | D23: =COUNTIFS(Inventory!E:E,"Logitech",Inventory!F:F,"⚠️ Low Stock") -> 2 | E23: =IF(B23>0,D23/B23,0) -> 0.4
A24: Samsung | B24: =COUNTIF(Inventory!E:E,"Samsung") -> 9 | C24: =SUMIF(Inventory!E:E,"Samsung",Inventory!C:C) -> 237 | D24: =COUNTIFS(Inventory!E:E,"Samsung",Inventory!F:F,"⚠️ Low Stock") -> 1 | E24: =IF(B24>0,D24/B24,0) -> 0.11111111
A25: TOTAL | B25: =SUM(B19:B24) -> 40 | C25: =SUM(C19:C24) -> 866 | D25: =SUM(D19:D24) -> 11 | E25: =IF(B25>0,D25/B25,0) -> 0.275
A27: ⚠️ Low Stock Items - Reorder Required
A29: Item_ID | B29: Item_Name | C29: Stock_Available | D29: Reorder_Level | E29: Shortage | F29: Supplier
A30: =Inventory!A5 -> 303 | B30: =Inventory!B5 -> Item_4 | C30: =Inventory!C5 -> 9 | D30: =Inventory!D5 -> 14 | E30: =Inventory!C5-Inventory!D5 -> -5 | F30: =Inventory!E5 -> Samsung
A31: =Inventory!A6 -> 304 | B31: =Inventory!B6 -> Item_5 | C31: =Inventory!C6 -> 5 | D31: =Inventory!D6 -> 7 | E31: =Inventory!C6-Inventory!D6 -> -2 | F31: =Inventory!E6 -> Logitech
A32: =Inventory!A7 -> 305 | B32: =Inventory!B7 -> Item_6 | C32: =Inventory!C7 -> 2 | D32: =Inventory!D7 -> 14 | E32: =Inventory!C7-Inventory!D7 -> -12 | F32: =Inventory!E7 -> Lenovo
A33: =Inventory!A12 -> 310 | B33: =Inventory!B12 -> Item_11 | C33: =Inventory!C12 -> 7 | D33: =Inventory!D12 -> 12 | E33: =Inventory!C12-Inventory!D12 -> -5 | F33: =Inventory!E12 -> Epson
A34: =Inventory!A15 -> 313 | B34: =Inventory!B15 -> Item_14 | C34: =Inventory!C15 -> 8 | D34: =Inventory!D15 -> 14 | E34: =Inventory!C15-Inventory!D15 -> -6 | F34: =Inventory!E15 -> Epson
A35: =Inventory!A16 -> 314 | B35: =Inventory!B16 -> Item_15 | C35: =Inventory!C16 -> 2 | D35: =Inventory!D16 -> 14 | E35: =Inventory!C16-Inventory!D16 -> -12 | F35: =Inventory!E16 -> HP
A36: =Inventory!A19 -> 317 | B36: =Inventory!B19 -> Item_18 | C36: =Inventory!C19 -> 3 | D36: =Inventory!D19 -> 13 | E36: =Inventory!C19-Inventory!D19 -> -10 | F36: =Inventory!E19 -> Logitech
A37: =Inventory!A26 -> 324 | B37: =Inventory!B26 -> Item_25 | C37: =Inventory!C26 -> 7 | D37: =Inventory!D26 -> 8 | E37: =Inventory!C26-Inventory!D26 -> -1 | F37: =Inventory!E26 -> Lenovo
A38: =Inventory!A31 -> 329 | B38: =Inventory!B31 -> Item_30 | C38: =Inventory!C31 -> 10 | D38: =Inventory!D31 -> 15 | E38: =Inventory!C31-Inventory!D31 -> -5 | F38: =Inventory!E31 -> HP
A39: =Inventory!A33 -> 331 | B39: =Inventory!B33 -> Item_32 | C39: =Inventory!C33 -> 4 | D39: =Inventory!D33 -> 6 | E39: =Inventory!C33-Inventory!D33 -> -2 | F39: =Inventory!E33 -> HP
A40: =Inventory!A35 -> 333 | B40: =Inventory!B35 -> Item_34 | C40: =Inventory!C35 -> 1 | D40: =Inventory!D35 -> 7 | E40: =Inventory!C35-Inventory!D35 -> -6 | F40: =Inventory!E35 -> Epson
A42: 📌 Conditional Formatting Applied:
A43: • Low Stock Items Count: Red data bars showing relative counts
A44: • % Low Stock: Color scale (Green=Low → Yellow=Mid → Red=High)
A45: • Shortage Column: Red highlight for negative values
A46: • Stock Available: Color scale showing stock levels

Sheet Client_Followup
A1: Client_Name | B1: Company | C1: Last_Contact_Date | D1: Status | E1: Next_Followup | F1: Followup_Status | G1: Days_Overdue | H1: Priority
A2: Neha Sharma | B2: Company_1 | C2: 46023 | D2: Follow-up | E2: 46030 | F2: =IF(E2="","",IF(E2<DATE(2026,3,29),"⏰ Overdue ("&DATE(2026,3,29)-E2&" days)",IF(E2<=DATE(2026,3,29)+7,"⚠️ Due in "&E2-DATE(2026,3,29)&" days","📅 Scheduled"))) -> ⏰ Overdue (80 days) | G2: =IF(E2<DATE(2026,3,29),DATE(2026,3,29)-E2,0) -> 80 | H2: =IF(D2="Closed","—",IF(G2>=60,"🔴 Critical",IF(G2>=30,"🟠 High",IF(G2>=7,"🟡 Medium","🟢 Low")))) -> 🔴 Critical
A3: Suresh Sharma | B3: Company_2 | C3: 46024 | D3: Interested | E3: 46031 | F3: =IF(E3="","",IF(E3<DATE(2026,3,29),"⏰ Overdue ("&DATE(2026,3,29)-E3&" days)",IF(E3<=DATE(2026,3,29)+7,"⚠️ Due in "&E3-DATE(2026,3,29)&" days","📅 Scheduled"))) -> ⏰ Overdue (79 days) | G3: =IF(E3<DATE(2026,3,29),DATE(2026,3,29)-E3,0) -> 79 | H3: =IF(D3="Closed","—",IF(G3>=60,"🔴 Critical",IF(G3>=30,"🟠 High",IF(G3>=7,"🟡 Medium","🟢 Low")))) -> 🔴 Critical
A4: Deepak Sharma | B4: Company_3 | C4: 46025 | D4: Follow-up | E4: 46032 | F4: =IF(E4="","",IF(E4<DATE(2026,3,29),"⏰ Overdue ("&DATE(2026,3,29)-E4&" days)",IF(E4<=DATE(2026,3,29)+7,"⚠️ Due in "&E4-DATE(2026,3,29)&" days","📅 Scheduled"))) -> ⏰ Overdue (78 days) | G4: =IF(E4<DATE(2026,3,29),DATE(2026,3,29)-E4,0) -> 78 | H4: =IF(D4="Closed","—",IF(G4>=60,"🔴 Critical",IF(G4>=30,"🟠 High",IF(G4>=7,"🟡 Medium","🟢 Low")))) -> 🔴 Critical
A5: Suresh Sharma | B5: Company_4 | C5: 46026 | D5: Follow-up | E5: 46033 | F5: =IF(E5="","",IF(E5<DATE(2026,3,29),"⏰ Overdue ("&DATE(2026,3,29)-E5&" days)",IF(E5<=DATE(2026,3,29)+7,"⚠️ Due in "&E5-DATE(2026,3,29)&" days","📅 Scheduled"))) -> ⏰ Overdue (77 days) | G5: =IF(E5<DATE(2026,3,29),DATE(2026,3,29)-E5,0) -> 77 | H5: =IF(D5="Closed","—",IF(G5>=60,"🔴 Critical",IF(G5>=30,"🟠 High",IF(G5>=7,"🟡 Medium","🟢 Low")))) -> 🔴 Critical
A6: Arjun Verma | B6: Company_5 | C6: 46027 | D6: Closed | E6: 46034 | F6: =IF(E6="","",IF(E6<DATE(2026,3,29),"⏰ Overdue ("&DATE(2026,3,29)-E6&" days)",IF(E6<=DATE(2026,3,29)+7,"⚠️ Due in "&E6-DATE(2026,3,29)&" days","📅 Scheduled"))) -> ⏰ Overdue (76 days) | G6: =IF(E6<DATE(2026,3,29),DATE(2026,3,29)-E6,0) -> 76 | H6: =IF(D6="Closed","—",IF(G6>=60,"🔴 Critical",IF(G6>=30,"🟠 High",IF(G6>=7,"🟡 Medium","🟢 Low")))) -> —
A7: Neha Verma | B7: Company_6 | C7: 46028 | D7: Negotiation | E7: 46035 | F7: =IF(E7="","",IF(E7<DATE(2026,3,29),"⏰ Overdue ("&DATE(2026,3,29)-E7&" days)",IF(E7<=DATE(2026,3,29)+7,"⚠️ Due in "&E7-DATE(2026,3,29)&" days","📅 Scheduled"))) -> ⏰ Overdue (75 days) | G7: =IF(E7<DATE(2026,3,29),DATE(2026,3,29)-E7,0) -> 75 | H7: =IF(D7="Closed","—",IF(G7>=60,"🔴 Critical",IF(G7>=30,"🟠 High",IF(G7>=7,"🟡 Medium","🟢 Low")))) -> 🔴 Critical
A8: Deepak Sharma | B8: Company_7 | C8: 46029 | D8: Closed | E8: 46036 | F8: =IF(E8="","",IF(E8<DATE(2026,3,29),"⏰ Overdue ("&DATE(2026,3,29)-E8&" days)",IF(E8<=DATE(2026,3,29)+7,"⚠️ Due in "&E8-DATE(2026,3,29)&" days","📅 Scheduled"))) -> ⏰ Overdue (74 days) | G8: =IF(E8<DATE(2026,3,29),DATE(2026,3,29)-E8,0) -> 74 | H8: =IF(D8="Closed","—",IF(G8>=60,"🔴 Critical",IF(G8>=30,"🟠 High",IF(G8>=7,"🟡 Medium","🟢 Low")))) -> —
A9: Neha Gupta | B9: Company_8 | C9: 46030 | D9: Closed | E9: 46037 | F9: =IF(E9="","",IF(E9<DATE(2026,3,29),"⏰ Overdue ("&DATE(2026,3,29)-E9&" days)",IF(E9<=DATE(2026,3,29)+7,"⚠️ Due in "&E9-DATE(2026,3,29)&" days","📅 Scheduled"))) -> ⏰ Overdue (73 days) | G9: =IF(E9<DATE(2026,3,29),DATE(2026,3,29)-E9,0) -> 73 | H9: =IF(D9="Closed","—",IF(G9>=60,"🔴 Critical",IF(G9>=30,"🟠 High",IF(G9>=7,"🟡 Medium","🟢 Low")))) -> —
A10: Suresh Verma | B10: Company_9 | C10: 46031 | D10: Follow-up | E10: 46038 | F10: =IF(E10="","",IF(E10<DATE(2026,3,29),"⏰ Overdue ("&DATE(2026,3,29)-E10&" days)",IF(E10<=DATE(2026,3,29)+7,"⚠️ Due in "&E10-DATE(2026,3,29)&" days","📅 Scheduled"))) -> ⏰ Overdue (72 days) | G10: =IF(E10<DATE(2026,3,29),DATE(2026,3,29)-E10,0) -> 72 | H10: =IF(D10="Closed","—",IF(G10>=60,"🔴 Critical",IF(G10>=30,"🟠 High",IF(G10>=7,"🟡 Medium","🟢 Low")))) -> 🔴 Critical
A11: Karan Sharma | B11: Company_10 | C11: 46032 | D11: Closed | E11: 46039 | F11: =IF(E11="","",IF(E11<DATE(2026,3,29),"⏰ Overdue ("&DATE(2026,3,29)-E11&" days)",IF(E11<=DATE(2026,3,29)+7,"⚠️ Due in "&E11-DATE(2026,3,29)&" days","📅 Scheduled"))) -> ⏰ Overdue (71 days) | G11: =IF(E11<DATE(2026,3,29),DATE(2026,3,29)-E11,0) -> 71 | H11: =IF(D11="Closed","—",IF(G11>=60,"🔴 Critical",IF(G11>=30,"🟠 High",IF(G11>=7,"🟡 Medium","🟢 Low")))) -> —
A12: Priya Sharma | B12: Company_11 | C12: 46033 | D12: Follow-up | E12: 46040 | F12: =IF(E12="","",IF(E12<DATE(2026,3,29),"⏰ Overdue ("&DATE(2026,3,29)-E12&" days)",IF(E12<=DATE(2026,3,29)+7,"⚠️ Due in "&E12-DATE(2026,3,29)&" days","📅 Scheduled"))) -> ⏰ Overdue (70 days) | G12: =IF(E12<DATE(2026,3,29),DATE(2026,3,29)-E12,0) -> 70 | H12: =IF(D12="Closed","—",IF(G12>=60,"🔴 Critical",IF(G12>=30,"🟠 High",IF(G12>=7,"🟡 Medium","🟢 Low")))) -> 🔴 Critical
A13: Pooja Gupta | B13: Company_12 | C13: 46034 | D13: Interested | E13: 46041 | F13: =IF(E13="","",IF(E13<DATE(2026,3,29),"⏰ Overdue ("&DATE(2026,3,29)-E13&" days)",IF(E13<=DATE(2026,3,29)+7,"⚠️ Due in "&E13-DATE(2026,3,29)&" days","📅 Scheduled"))) -> ⏰ Overdue (69 days) | G13: =IF(E13<DATE(2026,3,29),DATE(2026,3,29)-E13,0) -> 69 | H13: =IF(D13="Closed","—",IF(G13>=60,"🔴 Critical",IF(G13>=30,"🟠 High",IF(G13>=7,"🟡 Medium","🟢 Low")))) -> 🔴 Critical
... A41: Karan Sharma | B41: Company_40 | C41: 46062 | D41: Negotiation | E41: 46069 | F41: =IF(E41="","",IF(E41<DATE(2026,3,29),"⏰ Overdue ("&DATE(2026,3,29)-E41&" days)",IF(E41<=DATE(2026,3,29)+7,"⚠️ Due in "&E41-DATE(2026,3,29)&" days","📅 Scheduled"))) -> ⏰ Overdue (41 days) | G41: =IF(E41<DATE(2026,3,29),DATE(2026,3,29)-E41,0) -> 41 | H41: =IF(D41="Closed","—",IF(G41>=60,"🔴 Critical",IF(G41>=30,"🟠 High",IF(G41>=7,"🟡 Medium","🟢 Low")))) -> 🟠 High

Sheet Client_Status_Summary
A1: 📊 Client Status Summary Report
A2: Generated: 29/3/2026
A4: 📋 Status-wise Client Summary
A6: Status | B6: Client_Count | C6: % of Total | D6: Avg_Days_Overdue | E6: Min_Days_Overdue | F6: Max_Days_Overdue
A7: Closed | B7: =COUNTIF(Client_Followup!D:D,"Closed") -> 11 | C7: =B7/SUM($B$7:$B$11) -> 0.275 | D7: =IFERROR(AVERAGEIF(Client_Followup!D:D,"Closed",Client_Followup!G:G),0) -> 62.909091 | E7: =IFERROR(_xlfn.MINIFS(Client_Followup!G:G,Client_Followup!D:D,"Closed"),0) -> 44 | F7: =IFERROR(_xlfn.MAXIFS(Client_Followup!G:G,Client_Followup!D:D,"Closed"),0) -> 76
A8: Demo Given | B8: =COUNTIF(Client_Followup!D:D,"Demo Given") -> 3 | C8: =B8/SUM($B$7:$B$11) -> 0.075 | D8: =IFERROR(AVERAGEIF(Client_Followup!D:D,"Demo Given",Client_Followup!G:G),0) -> 46.666667 | E8: =IFERROR(_xlfn.MINIFS(Client_Followup!G:G,Client_Followup!D:D,"Demo Given"),0) -> 43 | F8: =IFERROR(_xlfn.MAXIFS(Client_Followup!G:G,Client_Followup!D:D,"Demo Given"),0) -> 52
A9: Follow-up | B9: =COUNTIF(Client_Followup!D:D,"Follow-up") -> 9 | C9: =B9/SUM($B$7:$B$11) -> 0.225 | D9: =IFERROR(AVERAGEIF(Client_Followup!D:D,"Follow-up",Client_Followup!G:G),0) -> 67.333333 | E9: =IFERROR(_xlfn.MINIFS(Client_Followup!G:G,Client_Followup!D:D,"Follow-up"),0) -> 51 | F9: =IFERROR(_xlfn.MAXIFS(Client_Followup!G:G,Client_Followup!D:D,"Follow-up"),0) -> 80
A10: Interested | B10: =COUNTIF(Client_Followup!D:D,"Interested") -> 10 | C10: =B10/SUM($B$7:$B$11) -> 0.25 | D10: =IFERROR(AVERAGEIF(Client_Followup!D:D,"Interested",Client_Followup!G:G),0) -> 57.7 | E10: =IFERROR(_xlfn.MINIFS(Client_Followup!G:G,Client_Followup!D:D,"Interested"),0) -> 42 | F10: =IFERROR(_xlfn.MAXIFS(Client_Followup!G:G,Client_Followup!D:D,"Interested"),0) -> 79
A11: Negotiation | B11: =COUNTIF(Client_Followup!D:D,"Negotiation") -> 7 | C11: =B11/SUM($B$7:$B$11) -> 0.175 | D11: =IFERROR(AVERAGEIF(Client_Followup!D:D,"Negotiation",Client_Followup!G:G),0) -> 57.857143 | E11: =IFERROR(_xlfn.MINIFS(Client_Followup!G:G,Client_Followup!D:D,"Negotiation"),0) -> 41 | F11: =IFERROR(_xlfn.MAXIFS(Client_Followup!G:G,Client_Followup!D:D,"Negotiation"),0) -> 75
A12: TOTAL | B12: =SUM(B7:B11) -> 40 | C12: =SUM(C7:C11) -> 1 | D12: =AVERAGE(D7:D11) -> 58.493247 | E12: =MIN(E7:E11) -> 41 | F12: =MAX(F7:F11) -> 80
A14: 🚨 Priority Breakdown by Status
A16: Status | B16: 🔴 Critical (60+ days) | C16: 🟠 High (30-59 days) | D16: 🟡 Medium (7-29 days) | E16: 🟢 Low (<7 days)
A17: Closed | B17: =COUNTIFS(Client_Followup!D:D,"Closed",Client_Followup!G:G,">=60") -> 6 | C17: =COUNTIFS(Client_Followup!D:D,"Closed",Client_Followup!G:G,">=30",Client_Followup!G:G,"<60") -> 5 | D17: =COUNTIFS(Client_Followup!D:D,"Closed",Client_Followup!G:G,">=7",Client_Followup!G:G,"<30") -> 0 | E17: =COUNTIFS(Client_Followup!D:D,"Closed",Client_Followup!G:G,"<7") -> 0
A18: Demo Given | B18: =COUNTIFS(Client_Followup!D:D,"Demo Given",Client_Followup!G:G,">=60") -> 0 | C18: =COUNTIFS(Client_Followup!D:D,"Demo Given",Client_Followup!G:G,">=30",Client_Followup!G:G,"<60") -> 3 | D18: =COUNTIFS(Client_Followup!D:D,"Demo Given",Client_Followup!G:G,">=7",Client_Followup!G:G,"<30") -> 0 | E18: =COUNTIFS(Client_Followup!D:D,"Demo Given",Client_Followup!G:G,"<7") -> 0
A19: Follow-up | B19: =COUNTIFS(Client_Followup!D:D,"Follow-up",Client_Followup!G:G,">=60") -> 7 | C19: =COUNTIFS(Client_Followup!D:D,"Follow-up",Client_Followup!G:G,">=30",Client_Followup!G:G,"<60") -> 2 | D19: =COUNTIFS(Client_Followup!D:D,"Follow-up",Client_Followup!G:G,">=7",Client_Followup!G:G,"<30") -> 0 | E19: =COUNTIFS(Client_Followup!D:D,"Follow-up",Client_Followup!G:G,"<7") -> 0
A20: Interested | B20: =COUNTIFS(Client_Followup!D:D,"Interested",Client_Followup!G:G,">=60") -> 4 | C20: =COUNTIFS(Client_Followup!D:D,"Interested",Client_Followup!G:G,">=30",Client_Followup!G:G,"<60") -> 6 | D20: =COUNTIFS(Client_Followup!D:D,"Interested",Client_Followup!G:G,">=7",Client_Followup!G:G,"<30") -> 0 | E20: =COUNTIFS(Client_Followup!D:D,"Interested",Client_Followup!G:G,"<7") -> 0
A21: Negotiation | B21: =COUNTIFS(Client_Followup!D:D,"Negotiation",Client_Followup!G:G,">=60") -> 4 | C21: =COUNTIFS(Client_Followup!D:D,"Negotiation",Client_Followup!G:G,">=30",Client_Followup!G:G,"<60") -> 3 | D21: =COUNTIFS(Client_Followup!D:D,"Negotiation",Client_Followup!G:G,">=7",Client_Followup!G:G,"<30") -> 0 | E21: =COUNTIFS(Client_Followup!D:D,"Negotiation",Client_Followup!G:G,"<7") -> 0
A22: TOTAL | B22: =SUM(B17:B21) -> 21 | C22: =SUM(C17:C21) -> 19 | D22: =SUM(D17:D21) -> 0 | E22: =SUM(E17:E21) -> 0
A24: 💡 Key Insights
A26: Most Common Status: | B26: =INDEX(A7:A11,MATCH(MAX(B7:B11),B7:B11,0)) -> Closed
A27: Active Clients (Non-Closed): | B27: =B12-COUNTIF(Client_Followup!D:D,"Closed") -> 29
A28: Closed Deals: | B28: =COUNTIF(Client_Followup!D:D,"Closed") -> 11
A29: Total Critical Priority: | B29: =COUNTIF(Client_Followup!H:H,"🔴 Critical") -> 15
A30: Total High Priority: | B30: =COUNTIF(Client_Followup!H:H,"🟠 High") -> 14
A32: 📌 Conditional Formatting Applied:
A33: • Client Count: Blue data bars showing relative counts
A34: • Critical Priority: Red highlight for values > 0
A35: • High Priority: Orange highlight for values > 0
A36: • Status Rows: Color-coded by status type

Sheet Budget_vs_Actual
A1: Department | B1: Budget | C1: Actual | D1: Variance | E1: Variance % | F1: Status
A2: Sales | B2: 59375 | C2: 40955 | D2: =C2-B2 -> -18420 | E2: =D2/B2 -> -0.31023158 | F2: =IF(D2>0,"⚠️ Over Budget","✓ Under Budget") -> ✓ Under Budget
A3: Marketing | B3: 71817 | C3: 60111 | D3: =C3-B3 -> -11706 | E3: =D3/B3 -> -0.16299762 | F3: =IF(D3>0,"⚠️ Over Budget","✓ Under Budget") -> ✓ Under Budget
A4: Accounts | B4: 61800 | C4: 27760 | D4: =C4-B4 -> -34040 | E4: =D4/B4 -> -0.55080906 | F4: =IF(D4>0,"⚠️ Over Budget","✓ Under Budget") -> ✓ Under Budget
A5: HR | B5: 69924 | C5: 47780 | D5: =C5-B5 -> -22144 | E5: =D5/B5 -> -0.31668669 | F5: =IF(D5>0,"⚠️ Over Budget","✓ Under Budget") -> ✓ Under Budget
A6: IT | B6: 63020 | C6: 70302 | D6: =C6-B6 -> 7282 | E6: =D6/B6 -> 0.11555062 | F6: =IF(D6>0,"⚠️ Over Budget","✓ Under Budget") -> ⚠️ Over Budget
A7: Admin | B7: 48568 | C7: 63330 | D7: =C7-B7 -> 14762 | E7: =D7/B7 -> 0.30394498 | F7: =IF(D7>0,"⚠️ Over Budget","✓ Under Budget") -> ⚠️ Over Budget

Sheet Budget_Variance_Report
A1: 📊 Budget vs Actual - Variance Report
A2: Generated: 29/3/2026
A4: Department | B4: Budget | C4: Actual | D4: Variance | E4: Variance %
A5: Sales | B5: =Budget_vs_Actual!B2 -> 59375 | C5: =Budget_vs_Actual!C2 -> 40955 | D5: =C5-B5 -> -18420 | E5: =D5/B5 -> -0.31023158
A6: Marketing | B6: =Budget_vs_Actual!B3 -> 71817 | C6: =Budget_vs_Actual!C3 -> 60111 | D6: =C6-B6 -> -11706 | E6: =D6/B6 -> -0.16299762
A7: Accounts | B7: =Budget_vs_Actual!B4 -> 61800 | C7: =Budget_vs_Actual!C4 -> 27760 | D7: =C7-B7 -> -34040 | E7: =D7/B7 -> -0.55080906
A8: HR | B8: =Budget_vs_Actual!B5 -> 69924 | C8: =Budget_vs_Actual!C5 -> 47780 | D8: =C8-B8 -> -22144 | E8: =D8/B8 -> -0.31668669
A9: IT | B9: =Budget_vs_Actual!B6 -> 63020 | C9: =Budget_vs_Actual!C6 -> 70302 | D9: =C9-B9 -> 7282 | E9: =D9/B9 -> 0.11555062
A10: Admin | B10: =Budget_vs_Actual!B7 -> 48568 | C10: =Budget_vs_Actual!C7 -> 63330 | D10: =C10-B10 -> 14762 | E10: =D10/B10 -> 0.30394498
A11: TOTAL | B11: =SUM(B5:B10) -> 374504 | C11: =SUM(C5:C10) -> 310238 | D11: =SUM(D5:D10) -> -64266 | E11: =D11/B11 -> -0.17160297
A13: 💡 Key Insights
A15: Departments Under Budget (Savings): | B15: {=_xlfn.TEXTJOIN(", ", TRUE, IF(D5:D10<0, A5:A10, ""))} -> Sales, Marketing, Accounts, HR
A16: Departments Over Budget: | B16: {=_xlfn.TEXTJOIN(", ", TRUE, IF(D5:D10>0, A5:A10, ""))} -> IT, Admin
A17: Total Variance: | B17: =IF(D11>0, "Over Budget by ₹"&TEXT(D11,"#,##0"), "Under Budget by ₹"&TEXT(ABS(D11),"#,##0")) -> Under Budget by ₹64,266
A18: Largest Over Budget: | B18: =IF(MAX(D5:D10)>0, INDEX(A5:A10, MATCH(MAX(D5:D10), D5:D10, 0))&" (+₹"&TEXT(MAX(D5:D10),"#,##0")&")", "None") -> Admin (+₹14,762)
A19: Largest Under Budget: | B19: =IF(MIN(D5:D10)<0, INDEX(A5:A10, MATCH(MIN(D5:D10), D5:D10, 0))&" (-₹"&TEXT(ABS(MIN(D5:D10)),"#,##0")&")", "None") -> Accounts (-₹34,040)
A21: 📌 Conditional Formatting Legend:
A22: 🟢 Green = Under Budget (Negative Variance - Savings)
A23: 🔴 Red = Over Budget (Positive Variance - Overspending)
A24: 📊 Blue bars = Budget amounts | Green bars = Actual amounts

Sheet Sales_Data
A1: Date | B1: Region | C1: Product | D1: Sales_Amount
A2: 46110 | B2: North | C2: Power BI Course | D2: 51636
A3: 46073 | B3: West | C3: Tally Course | D3: 53095
A4: 46134 | B4: West | C4: GST Course | D4: 56972
A5: 46114 | B5: North | C5: GST Course | D5: 16696
A6: 46058 | B6: North | C6: GST Course | D6: 9196
A7: 46105 | B7: West | C7: Power BI Course | D7: 39625
A8: 46135 | B8: East | C8: Power BI Course | D8: 6702
A9: 46034 | B9: East | C9: Power BI Course | D9: 48570
A10: 46113 | B10: South | C10: Power BI Course | D10: 24902
A11: 46134 | B11: East | C11: Excel Course | D11: 11401
A12: 46093 | B12: West | C12: Tally Course | D12: 44018
A13: 46081 | B13: West | C13: Tally Course | D13: 31000
... A401: 46076 | B401: West | C401: GST Course | D401: 46251

Sheet Prompts
A1: Sheet Name | B1: Topic / Demo | C1: Claude Prompt (Copy-Paste)
A2: Email_Data | B2: Email Generation from Excel Data | C2: “Using the Email_Data sheet, generate personalized payment reminder emails for clients whose fee status is pending.”
A3: Email_Data | B3: Follow-up Email Automation | C3: “From the Email_Data sheet, draft follow-up emails for students who enrolled in Advanced Excel course.”
A4: Index_Sheet | B4: Index Sheet Navigation | C4: “Create an index sheet with hyperlinks for all sheets in this Excel workbook.”
A5: Raw_Messy_Data | B5: Data Cleaning | C5: “Clean the Raw_Messy_Data sheet by removing extra spaces, standardizing city names, and removing duplicate records.”
A6: Raw_Messy_Data | B6: Data Standardization | C6: “Standardize the city names in Raw_Messy_Data so that Delhi, delhi and Delhi are treated as the same value.”
A7: Payroll_Data | B7: Salary Calculation | C7: “Using the Payroll_Data sheet, create a formula to calculate net salary as Basic Salary + Bonus − Deductions.”
A8: Payroll_Data | B8: Payroll Summary | C8: “Generate a department-wise payroll summary from the Payroll_Data sheet.”
A9: Bank_Books + Bank_Statement | B9: Bank Reconciliation | C9: “Compare the Bank_Books and Bank_Statement sheets and identify unmatched transactions.”
A10: Bank_Books + Bank_Statement | B10: Reconciliation Report | C10: “Prepare a reconciliation report showing missing entries between Bank_Books and Bank_Statement.”
A11: Expenses | B11: Expense Analysis | C11: “Create a category-wise expense summary from the Expenses sheet.”
A12: Expenses | B12: Monthly Expense Report | C12: “Generate a monthly expense report and identify the highest expense category.”
... A35: Sales_Data | B35: Full PPT Draft | C35: “Generate a complete PowerPoint structure (10 slides) based on the Sales_Data insights including slide titles and bullet points.”

Sheet Sales_Dashboard
A1: 📊 SALES DASHBOARD
A2: Regional & Product Performance Analysis
A4: 📈 KEY METRICS
A5: Total Sales | B5: Total Transactions | C5: Average Sale | D5: Top Region | E5: Top Product
A6: =SUM(Sales_Data!D:D) -> 11819830 | B6: =COUNTA(Sales_Data!A:A)-1 -> 400 | C6: =AVERAGE(Sales_Data!D:D) -> 29549.575 | D6: =INDEX(A11:A14,MATCH(MAX(B11:B14),B11:B14,0)) -> West | E6: =INDEX(A20:A23,MATCH(MAX(B20:B23),B20:B23,0)) -> Tally Course
A8: 🌍 REGION-WISE SALES SUMMARY
A10: Region | B10: Total Sales | C10: Transactions | D10: Avg Sale | E10: % of Total
A11: East | B11: =SUMIF(Sales_Data!B:B,"East",Sales_Data!D:D) -> 3000144 | C11: =COUNTIF(Sales_Data!B:B,"East") -> 98 | D11: =AVERAGEIF(Sales_Data!B:B,"East",Sales_Data!D:D) -> 30613.714 | E11: =B11/SUM($B$11:$B$14) -> 0.25382294
A12: North | B12: =SUMIF(Sales_Data!B:B,"North",Sales_Data!D:D) -> 2748083 | C12: =COUNTIF(Sales_Data!B:B,"North") -> 105 | D12: =AVERAGEIF(Sales_Data!B:B,"North",Sales_Data!D:D) -> 26172.219 | E12: =B12/SUM($B$11:$B$14) -> 0.23249768
A13: South | B13: =SUMIF(Sales_Data!B:B,"South",Sales_Data!D:D) -> 2464143 | C13: =COUNTIF(Sales_Data!B:B,"South") -> 81 | D13: =AVERAGEIF(Sales_Data!B:B,"South",Sales_Data!D:D) -> 30421.519 | E13: =B13/SUM($B$11:$B$14) -> 0.20847533
A14: West | B14: =SUMIF(Sales_Data!B:B,"West",Sales_Data!D:D) -> 3607460 | C14: =COUNTIF(Sales_Data!B:B,"West") -> 116 | D14: =AVERAGEIF(Sales_Data!B:B,"West",Sales_Data!D:D) -> 31098.793 | E14: =B14/SUM($B$11:$B$14) -> 0.30520405
A15: TOTAL | B15: =SUM(B11:B14) -> 11819830 | C15: =SUM(C11:C14) -> 400 | D15: =AVERAGE(D11:D14) -> 29576.561 | E15: =SUM(E11:E14) -> 1
A17: 📦 PRODUCT-WISE SALES SUMMARY
A19: Product | B19: Total Sales | C19: Transactions | D19: Avg Sale | E19: % of Total
A20: Excel Course | B20: =SUMIF(Sales_Data!C:C,"Excel Course",Sales_Data!D:D) -> 2954852 | C20: =COUNTIF(Sales_Data!C:C,"Excel Course") -> 96 | D20: =AVERAGEIF(Sales_Data!C:C,"Excel Course",Sales_Data!D:D) -> 30779.708 | E20: =B20/SUM($B$20:$B$23) -> 0.24999107
A21: GST Course | B21: =SUMIF(Sales_Data!C:C,"GST Course",Sales_Data!D:D) -> 2919573 | C21: =COUNTIF(Sales_Data!C:C,"GST Course") -> 108 | D21: =AVERAGEIF(Sales_Data!C:C,"GST Course",Sales_Data!D:D) -> 27033.083 | E21: =B21/SUM($B$20:$B$23) -> 0.24700634
A22: Power BI Course | B22: =SUMIF(Sales_Data!C:C,"Power BI Course",Sales_Data!D:D) -> 2667418 | C22: =COUNTIF(Sales_Data!C:C,"Power BI Course") -> 89 | D22: =AVERAGEIF(Sales_Data!C:C,"Power BI Course",Sales_Data!D:D) -> 29970.989 | E22: =B22/SUM($B$20:$B$23) -> 0.22567313
A23: Tally Course | B23: =SUMIF(Sales_Data!C:C,"Tally Course",Sales_Data!D:D) -> 3277987 | C23: =COUNTIF(Sales_Data!C:C,"Tally Course") -> 107 | D23: =AVERAGEIF(Sales_Data!C:C,"Tally Course",Sales_Data!D:D) -> 30635.393 | E23: =B23/SUM($B$20:$B$23) -> 0.27732945
A24: TOTAL | B24: =SUM(B20:B23) -> 11819830 | C24: =SUM(C20:C23) -> 400 | D24: =AVERAGE(D20:D23) -> 29604.793 | E24: =SUM(E20:E23) -> 1
A26: 📅 MONTHLY SALES TREND
A28: Month | B28: Total Sales | C28: Transactions | D28: Avg Sale
A29: 46023 | B29: =SUMIFS(Sales_Data!D:D,Sales_Data!A:A,">="&DATE(2026,1,1),Sales_Data!A:A,"<="&DATE(2026,1,31)) -> 2945349 | C29: =COUNTIFS(Sales_Data!A:A,">="&DATE(2026,1,1),Sales_Data!A:A,"<="&DATE(2026,1,31)) -> 100 | D29: =IF(C29>0,B29/C29,0) -> 29453.49
A30: 46054 | B30: =SUMIFS(Sales_Data!D:D,Sales_Data!A:A,">="&DATE(2026,2,1),Sales_Data!A:A,"<="&DATE(2026,2,28)) -> 2640404 | C30: =COUNTIFS(Sales_Data!A:A,">="&DATE(2026,2,1),Sales_Data!A:A,"<="&DATE(2026,2,28)) -> 94 | D30: =IF(C30>0,B30/C30,0) -> 28089.404
A31: 46082 | B31: =SUMIFS(Sales_Data!D:D,Sales_Data!A:A,">="&DATE(2026,3,1),Sales_Data!A:A,"<="&DATE(2026,3,31)) -> 2731454 | C31: =COUNTIFS(Sales_Data!A:A,">="&DATE(2026,3,1),Sales_Data!A:A,"<="&DATE(2026,3,31)) -> 95 | D31: =IF(C31>0,B31/C31,0) -> 28752.147
A32: 46113 | B32: =SUMIFS(Sales_Data!D:D,Sales_Data!A:A,">="&DATE(2026,4,1),Sales_Data!A:A,"<="&DATE(2026,4,30)) -> 3352394 | C32: =COUNTIFS(Sales_Data!A:A,">="&DATE(2026,4,1),Sales_Data!A:A,"<="&DATE(2026,4,30)) -> 107 | D32: =IF(C32>0,B32/C32,0) -> 31330.785
A33: TOTAL | B33: =SUM(B29:B32) -> 11669601 | C33: =SUM(C29:C32) -> 396 | D33: =IF(C33>0,B33/C33,0) -> 29468.689
A35: 📊 REGION × PRODUCT SALES MATRIX
A37: Region \ Product | B37: Excel Course | C37: GST Course | D37: Power BI Course | E37: Tally Course | F37: TOTAL
A38: East | B38: =SUMIFS(Sales_Data!D:D,Sales_Data!B:B,"East",Sales_Data!C:C,"Excel Course") -> 604036 | C38: =SUMIFS(Sales_Data!D:D,Sales_Data!B:B,"East",Sales_Data!C:C,"GST Course") -> 876421 | D38: =SUMIFS(Sales_Data!D:D,Sales_Data!B:B,"East",Sales_Data!C:C,"Power BI Course") -> 584672 | E38: =SUMIFS(Sales_Data!D:D,Sales_Data!B:B,"East",Sales_Data!C:C,"Tally Course") -> 935015 | F38: =SUM(B38:E38) -> 3000144
A39: North | B39: =SUMIFS(Sales_Data!D:D,Sales_Data!B:B,"North",Sales_Data!C:C,"Excel Course") -> 491115 | C39: =SUMIFS(Sales_Data!D:D,Sales_Data!B:B,"North",Sales_Data!C:C,"GST Course") -> 582698 | D39: =SUMIFS(Sales_Data!D:D,Sales_Data!B:B,"North",Sales_Data!C:C,"Power BI Course") -> 695522 | E39: =SUMIFS(Sales_Data!D:D,Sales_Data!B:B,"North",Sales_Data!C:C,"Tally Course") -> 978748 | F39: =SUM(B39:E39) -> 2748083
A40: South | B40: =SUMIFS(Sales_Data!D:D,Sales_Data!B:B,"South",Sales_Data!C:C,"Excel Course") -> 920120 | C40: =SUMIFS(Sales_Data!D:D,Sales_Data!B:B,"South",Sales_Data!C:C,"GST Course") -> 439632 | D40: =SUMIFS(Sales_Data!D:D,Sales_Data!B:B,"South",Sales_Data!C:C,"Power BI Course") -> 534267 | E40: =SUMIFS(Sales_Data!D:D,Sales_Data!B:B,"South",Sales_Data!C:C,"Tally Course") -> 570124 | F40: =SUM(B40:E40) -> 2464143
A41: West | B41: =SUMIFS(Sales_Data!D:D,Sales_Data!B:B,"West",Sales_Data!C:C,"Excel Course") -> 939581 | C41: =SUMIFS(Sales_Data!D:D,Sales_Data!B:B,"West",Sales_Data!C:C,"GST Course") -> 1020822 | D41: =SUMIFS(Sales_Data!D:D,Sales_Data!B:B,"West",Sales_Data!C:C,"Power BI Course") -> 852957 | E41: =SUMIFS(Sales_Data!D:D,Sales_Data!B:B,"West",Sales_Data!C:C,"Tally Course") -> 794100 | F41: =SUM(B41:E41) -> 3607460
A42: TOTAL | B42: =SUM(B38:B41) -> 2954852 | C42: =SUM(C38:C41) -> 2919573 | D42: =SUM(D38:D41) -> 2667418 | E42: =SUM(E38:E41) -> 3277987 | F42: =SUM(F38:F41) -> 11819830
A44: 📌 DASHBOARD NOTES
A45: • All data is sourced from Sales_Data worksheet with 400 transactions
A46: • Color scales: 🔴 Red = Low | 🟡 Yellow = Medium | 🟢 Green = High
A47: • Dashboard updates automatically when Sales_Data is modified
A48: • Generated: 29 Mar 2026

Sheet Sales_Pivot_Summary
A1: 📊 Sales Pivot Summary - Region × Product Analysis
A2: Generated: 29/3/2026
A4: 📋 Total Sales by Region and Product
A6: Region | B6: Excel Course | C6: GST Course | D6: Power BI Course | E6: Tally Course | F6: Grand Total
A7: East | B7: =SUMIFS(Sales_Data!D:D,Sales_Data!B:B,$A7,Sales_Data!C:C,B$6) -> 604036 | C7: =SUMIFS(Sales_Data!D:D,Sales_Data!B:B,$A7,Sales_Data!C:C,C$6) -> 876421 | D7: =SUMIFS(Sales_Data!D:D,Sales_Data!B:B,$A7,Sales_Data!C:C,D$6) -> 584672 | E7: =SUMIFS(Sales_Data!D:D,Sales_Data!B:B,$A7,Sales_Data!C:C,E$6) -> 935015 | F7: =SUM(B7:E7) -> 3000144
A8: North | B8: =SUMIFS(Sales_Data!D:D,Sales_Data!B:B,$A8,Sales_Data!C:C,B$6) -> 491115 | C8: =SUMIFS(Sales_Data!D:D,Sales_Data!B:B,$A8,Sales_Data!C:C,C$6) -> 582698 | D8: =SUMIFS(Sales_Data!D:D,Sales_Data!B:B,$A8,Sales_Data!C:C,D$6) -> 695522 | E8: =SUMIFS(Sales_Data!D:D,Sales_Data!B:B,$A8,Sales_Data!C:C,E$6) -> 978748 | F8: =SUM(B8:E8) -> 2748083
A9: South | B9: =SUMIFS(Sales_Data!D:D,Sales_Data!B:B,$A9,Sales_Data!C:C,B$6) -> 920120 | C9: =SUMIFS(Sales_Data!D:D,Sales_Data!B:B,$A9,Sales_Data!C:C,C$6) -> 439632 | D9: =SUMIFS(Sales_Data!D:D,Sales_Data!B:B,$A9,Sales_Data!C:C,D$6) -> 534267 | E9: =SUMIFS(Sales_Data!D:D,Sales_Data!B:B,$A9,Sales_Data!C:C,E$6) -> 570124 | F9: =SUM(B9:E9) -> 2464143
A10: West | B10: =SUMIFS(Sales_Data!D:D,Sales_Data!B:B,$A10,Sales_Data!C:C,B$6) -> 939581 | C10: =SUMIFS(Sales_Data!D:D,Sales_Data!B:B,$A10,Sales_Data!C:C,C$6) -> 1020822 | D10: =SUMIFS(Sales_Data!D:D,Sales_Data!B:B,$A10,Sales_Data!C:C,D$6) -> 852957 | E10: =SUMIFS(Sales_Data!D:D,Sales_Data!B:B,$A10,Sales_Data!C:C,E$6) -> 794100 | F10: =SUM(B10:E10) -> 3607460
A11: Grand Total | B11: =SUM(B7:B10) -> 2954852 | C11: =SUM(C7:C10) -> 2919573 | D11: =SUM(D7:D10) -> 2667418 | E11: =SUM(E7:E10) -> 3277987 | F11: =SUM(F7:F10) -> 11819830
A14: 📊 Transaction Count by Region and Product
A16: Region | B16: Excel Course | C16: GST Course | D16: Power BI Course | E16: Tally Course | F16: Grand Total
A17: East | B17: =COUNTIFS(Sales_Data!B:B,$A17,Sales_Data!C:C,B$16) -> 17 | C17: =COUNTIFS(Sales_Data!B:B,$A17,Sales_Data!C:C,C$16) -> 31 | D17: =COUNTIFS(Sales_Data!B:B,$A17,Sales_Data!C:C,D$16) -> 21 | E17: =COUNTIFS(Sales_Data!B:B,$A17,Sales_Data!C:C,E$16) -> 29 | F17: =SUM(B17:E17) -> 98
A18: North | B18: =COUNTIFS(Sales_Data!B:B,$A18,Sales_Data!C:C,B$16) -> 19 | C18: =COUNTIFS(Sales_Data!B:B,$A18,Sales_Data!C:C,C$16) -> 24 | D18: =COUNTIFS(Sales_Data!B:B,$A18,Sales_Data!C:C,D$16) -> 28 | E18: =COUNTIFS(Sales_Data!B:B,$A18,Sales_Data!C:C,E$16) -> 34 | F18: =SUM(B18:E18) -> 105
A19: South | B19: =COUNTIFS(Sales_Data!B:B,$A19,Sales_Data!C:C,B$16) -> 28 | C19: =COUNTIFS(Sales_Data!B:B,$A19,Sales_Data!C:C,C$16) -> 16 | D19: =COUNTIFS(Sales_Data!B:B,$A19,Sales_Data!C:C,D$16) -> 16 | E19: =COUNTIFS(Sales_Data!B:B,$A19,Sales_Data!C:C,E$16) -> 21 | F19: =SUM(B19:E19) -> 81
A20: West | B20: =COUNTIFS(Sales_Data!B:B,$A20,Sales_Data!C:C,B$16) -> 32 | C20: =COUNTIFS(Sales_Data!B:B,$A20,Sales_Data!C:C,C$16) -> 37 | D20: =COUNTIFS(Sales_Data!B:B,$A20,Sales_Data!C:C,D$16) -> 24 | E20: =COUNTIFS(Sales_Data!B:B,$A20,Sales_Data!C:C,E$16) -> 23 | F20: =SUM(B20:E20) -> 116
A21: Grand Total | B21: =SUM(B17:B20) -> 96 | C21: =SUM(C17:C20) -> 108 | D21: =SUM(D17:D20) -> 89 | E21: =SUM(E17:E20) -> 107 | F21: =SUM(F17:F20) -> 400
A24: 📈 Sales Percentage Distribution (% of Grand Total)
A26: Region | B26: Excel Course | C26: GST Course | D26: Power BI Course | E26: Tally Course | F26: Region %
A27: East | B27: =B7/$F$11 -> 0.051103611 | C27: =C7/$F$11 -> 0.074148359 | D27: =D7/$F$11 -> 0.049465348 | E27: =E7/$F$11 -> 0.079105622 | F27: =F7/$F$11 -> 0.25382294
A28: North | B28: =B8/$F$11 -> 0.04155009 | C28: =C8/$F$11 -> 0.04929834 | D28: =D8/$F$11 -> 0.058843655 | E28: =E8/$F$11 -> 0.08280559 | F28: =F8/$F$11 -> 0.23249768
A29: South | B29: =B9/$F$11 -> 0.077845451 | C29: =C9/$F$11 -> 0.037194444 | D29: =D9/$F$11 -> 0.045200904 | E29: =E9/$F$11 -> 0.048234535 | F29: =F9/$F$11 -> 0.20847533
A30: West | B30: =B10/$F$11 -> 0.079491922 | C30: =C10/$F$11 -> 0.086365202 | D30: =D10/$F$11 -> 0.072163221 | E30: =E10/$F$11 -> 0.067183707 | F30: =F10/$F$11 -> 0.30520405
A31: Product % | B31: =B11/$F$11 -> 0.24999107 | C31: =C11/$F$11 -> 0.24700634 | D31: =D11/$F$11 -> 0.22567313 | E31: =E11/$F$11 -> 0.27732945 | F31: =F11/$F$11 -> 1
A34: 💡 Key Insights
A36: Top Performing Region: | B36: =INDEX(A7:A10,MATCH(MAX(F7:F10),F7:F10,0)) -> West
A37: Top Performing Product: | B37: =INDEX(B6:E6,MATCH(MAX(B11:E11),B11:E11,0)) -> Tally Course
A38: Grand Total Sales: | B38: =F11 -> 11819830
A39: Total Transactions: | B39: =F21 -> 400
A40: Average Sale per Transaction: | B40: =F11/F21 -> 29549.575
A41: Highest Region-Product Combo: | B41: =MAX(B7:E10) -> 1020822
A44: 📌 Conditional Formatting Applied:
A45: • Sales Matrix (B7:E10): Color scale (Red=Low → Yellow=Mid → Green=High)
A46: • Transaction Count (B17:E20): Color scale (Red=Low → Yellow=Mid → Green=High)
A47: • Region Totals (F7:F10): Blue data bars
A48: • Product Totals (B11:E11): Green data bars

Sheet Top_Performance_Summary
A1: 🏆 Top Performance Analysis - Sales Data
A2: Identifying Top Performing Product and Region
A4: 🌍 Region-wise Sales Analysis
A6: Region | B6: Total Sales | C6: Transactions | D6: % of Total
A7: East | B7: =SUMIF(Sales_Data!B:B,"East",Sales_Data!D:D) -> 3000144 | C7: =COUNTIF(Sales_Data!B:B,"East") -> 98 | D7: =B7/B$11 -> 0.25382294
A8: North | B8: =SUMIF(Sales_Data!B:B,"North",Sales_Data!D:D) -> 2748083 | C8: =COUNTIF(Sales_Data!B:B,"North") -> 105 | D8: =B8/B$11 -> 0.23249768
A9: South | B9: =SUMIF(Sales_Data!B:B,"South",Sales_Data!D:D) -> 2464143 | C9: =COUNTIF(Sales_Data!B:B,"South") -> 81 | D9: =B9/B$11 -> 0.20847533
A10: West | B10: =SUMIF(Sales_Data!B:B,"West",Sales_Data!D:D) -> 3607460 | C10: =COUNTIF(Sales_Data!B:B,"West") -> 116 | D10: =B10/B$11 -> 0.30520405
A11: TOTAL | B11: =SUM(B7:B10) -> 11819830 | C11: =SUM(C7:C10) -> 400 | D11: =SUM(D7:D10) -> 1
A13: 📦 Product-wise Sales Analysis
A15: Product | B15: Total Sales | C15: Transactions | D15: % of Total
A16: Excel Course | B16: =SUMIF(Sales_Data!C:C,"Excel Course",Sales_Data!D:D) -> 2954852 | C16: =COUNTIF(Sales_Data!C:C,"Excel Course") -> 96 | D16: =B16/B$20 -> 0.24999107
A17: GST Course | B17: =SUMIF(Sales_Data!C:C,"GST Course",Sales_Data!D:D) -> 2919573 | C17: =COUNTIF(Sales_Data!C:C,"GST Course") -> 108 | D17: =B17/B$20 -> 0.24700634
A18: Power BI Course | B18: =SUMIF(Sales_Data!C:C,"Power BI Course",Sales_Data!D:D) -> 2667418 | C18: =COUNTIF(Sales_Data!C:C,"Power BI Course") -> 89 | D18: =B18/B$20 -> 0.22567313
A19: Tally Course | B19: =SUMIF(Sales_Data!C:C,"Tally Course",Sales_Data!D:D) -> 3277987 | C19: =COUNTIF(Sales_Data!C:C,"Tally Course") -> 107 | D19: =B19/B$20 -> 0.27732945
A20: TOTAL | B20: =SUM(B16:B19) -> 11819830 | C20: =SUM(C16:C19) -> 400 | D20: =SUM(D16:D19) -> 1
A22: 🏆 TOP PERFORMERS
A24: 🥇 TOP REGION | D24: 🥇 TOP PRODUCT
A25: =INDEX(A7:A10,MATCH(MAX(B7:B10),B7:B10,0)) -> West | D25: =INDEX(A16:A19,MATCH(MAX(B16:B19),B16:B19,0)) -> Tally Course
A26: Total Sales: | B26: =MAX(B7:B10) -> 3607460 | D26: Total Sales: | E26: =MAX(B16:B19) -> 3277987
A27: Transactions: | B27: =INDEX(C7:C10,MATCH(MAX(B7:B10),B7:B10,0)) -> 116 | D27: Transactions: | E27: =INDEX(C16:C19,MATCH(MAX(B16:B19),B16:B19,0)) -> 107
A28: % of Total: | B28: =INDEX(D7:D10,MATCH(MAX(B7:B10),B7:B10,0)) -> 0.30520405 | D28: % of Total: | E28: =INDEX(D16:D19,MATCH(MAX(B16:B19),B16:B19,0)) -> 0.27732945
A30: 💡 Additional Insights
A32: Grand Total Sales: | B32: =SUM(Sales_Data!D:D) -> 11819830
A33: Total Transactions: | B33: =COUNTA(Sales_Data!D:D)-1 -> 400
A34: Average Sale Amount: | B34: =AVERAGE(Sales_Data!D2:D401) -> 29549.575
A35: Lowest Performing Region: | B35: =INDEX(A7:A10,MATCH(MIN(B7:B10),B7:B10,0)) -> South
A36: Lowest Performing Product: | B36: =INDEX(A16:A19,MATCH(MIN(B16:B19),B16:B19,0)) -> Power BI Course
