Workbook

Sheet Ecommerce_Sales
A1: OrderID | B1: CustomerName | C1: Email | D1: Product | E1: Category | F1: Price | G1: Quantity | H1: OrderDate | I1: City | J1: Country | K1: PaymentMethod | L1: OrderStatus
A2: ORD10000 | B2: Pooja Bansal | C2: pooja95@gmail.com | D2: Charger | E2: Tech | F2: 78572.14 | G2: 4 | H2: 45306 | I2: Delhi | J2: India | K2: Debit Card | L2: Delivered
A3: ORD10001 | B3: Sneha Verma | C3: sneha12@gmail.com | D3: Tablet | E3: Electronics | F3: 43393.19 | G3: 3 | H3: 45271 | I3: Mumbai | J3: India | K3: Net Banking | L3: Returned
A4: ORD10002 | B4: Arjun Singh | C4: arjun5@gmail.com | D4: Headphones | E4: Electronics | F4: 38208.78 | G4: 2 | H4: 45977 | I4: Hyderabad | J4: India | K4: Debit Card | L4: Pending
A5: ORD10003 | B5: Neha Singh | C5: neha3@gmail.com | D5: Headphones | E5: Electronics | F5: 44514.23 | G5: 5 | H5: 45466 | I5: Kolkata | J5: India | K5: Credit Card | L5: Shipped
A6: ORD10004 | B6: Neha Gupta | C6: neha60@gmail.com | D6: Mouse | E6: Electronics | F6: 73256.56 | G6: 3 | H6: 45582 | I6: Delhi | J6: India | K6: Credit Card | L6: Cancelled
A7: ORD10005 | B7: Meena Sharma | C7: meena84@gmail.com | D7: USB Cable | E7: Tech | F7: 67063.78 | G7: 3 | H7: 45543 | I7: Chennai | J7: India | K7: Credit Card | L7: Shipped
A8: ORD10006 | B8: Rohit Arora | C8: rohit138@gmail.com | D8: Monitor | E8: Electronics | F8: 64501.86 | G8: 1 | H8: 45443 | I8: Ahmedabad | J8: India | K8: UPI | L8: Delivered
A9: ORD10007 | B9: Sneha Verma | C9: sneha180@gmail.com | D9: Monitor | E9: Gadgets | F9: 61418.64 | G9: 1 | H9: 45804 | I9: Delhi | J9: India | K9: Debit Card | L9: Delivered
A10: ORD10009 | B10: Vikas Gupta | C10: vikas143@gmail.com | D10: Mouse | E10: Gadgets | F10: 5379.97 | G10: 2 | H10: 45580 | I10: Delhi | J10: India | K10: Credit Card | L10: Delivered
A11: ORD10010 | B11: Neha Kapoor | C11: neha49@gmail.com | D11: Charger | E11: Electronics | F11: 69761.1 | G11: 1 | H11: 45390 | I11: Mumbai | J11: India | K11: Net Banking | L11: Returned
A12: ORD10012 | B12: Arjun Sharma | C12: arjun46@gmail.com | D12: USB Cable | E12: Electronics | F12: 31399.6 | G12: 5 | H12: 45477 | I12: Pune | J12: India | K12: UPI | L12: Returned
A13: ORD10013 | B13: Rohit Jain | C13: rohit42@gmail.com | D13: Tablet | E13: Tech | F13: 18167.94 | G13: 2 | H13: 45357 | I13: Kolkata | J13: India | K13: Credit Card | L13: Delivered
A14: ORD10014 | B14: Anjali Mehta | D14: Webcam | E14: Electronics | F14: 32961.2 | G14: 2 | H14: 45966 | I14: Delhi | J14: India | K14: UPI | L14: Returned
A15: ORD10015 | B15: Priya Arora | C15: priya199@gmail.com | D15: Webcam | E15: Gadgets | F15: 46556.77 | G15: 4 | H15: 45895 | I15: Delhi | J15: India | K15: Credit Card | L15: Returned
A16: ORD10016 | B16: Anjali Jain | C16: anjali106@gmail.com | D16: Headphones | E16: Electronics | F16: 32137.43 | G16: 4 | H16: 45394 | I16: Pune | J16: India | K16: COD | L16: Delivered
A17: ORD10017 | B17: Karan Singh | C17: karan171@gmail.com | D17: Mouse | E17: Electronics | F17: 10041.37 | G17: 1 | H17: 45481 | I17: Delhi | J17: India | K17: COD | L17: Shipped
A18: ORD10018 | B18: Meena Mehta | C18: meena115@gmail.com | D18: USB Cable | E18: Electronics | F18: 26804.67 | G18: 3 | H18: 45509 | I18: Bangalore | J18: India | K18: COD | L18: Returned
A19: ORD10019 | B19: Pooja Kapoor | C19: pooja100@gmail.com | D19: USB Cable | E19: Electronics | F19: 17270.7 | G19: 4 | H19: 45085 | I19: Kolkata | J19: India | K19: COD | L19: Delivered
A20: ORD10020 | B20: Pooja Gupta | C20: pooja182@gmail.com | D20: Laptop | E20: Electronics | F20: 63424.46 | G20: 4 | H20: 45517 | I20: Delhi | J20: India | K20: UPI | L20: Shipped
A21: ORD10022 | B21: Rahul Jain | C21: rahul2@gmail.com | D21: USB Cable | E21: Tech | G21: 2 | H21: 45172 | I21: Ahmedabad | J21: India | K21: Debit Card | L21: Pending
A22: ORD10023 | B22: Vikas Bansal | C22: vikas80@gmail.com | D22: Monitor | E22: Gadgets | F22: 64877.35 | G22: 3 | H22: 45467 | I22: Hyderabad | J22: India | K22: COD | L22: Delivered
A23: ORD10024 | B23: Priya Gupta | C23: priya57@gmail.com | D23: Webcam | E23: Electronics | F23: 57783.79 | G23: 1 | H23: 45933 | I23: Kolkata | J23: India | K23: Debit Card | L23: Delivered
A24: ORD10025 | B24: Rahul Jain | C24: rahul200@gmail.com | D24: Monitor | E24: Electronics | F24: 74788.76 | G24: 2 | H24: 45540 | I24: Kolkata | J24: India | K24: COD | L24: Returned
A25: ORD10026 | B25: Neha Singh | C25: neha45@gmail.com | D25: Headphones | E25: Gadgets | F25: 10792.47 | G25: 2 | H25: 44956 | I25: Pune | J25: India | K25: UPI | L25: Delivered
A26: ORD10028 | B26: Sneha Singh | C26: sneha28@gmail.com | D26: Keyboard | E26: Gadgets | F26: 45547.47 | G26: 2 | H26: 45785 | I26: Bangalore | J26: India | K26: Net Banking | L26: Delivered
A27: ORD10030 | B27: Sneha Agarwal | D27: USB Cable | E27: Gadgets | F27: 73478.02 | G27: 3 | H27: 45111 | I27: Kolkata | J27: India | K27: Credit Card | L27: Cancelled
A28: ORD10031 | B28: Sneha Jain | C28: sneha109@gmail.com | D28: Charger | E28: Electronics | F28: 855.68 | G28: 3 | H28: 44933 | I28: Bangalore | J28: India | K28: Net Banking | L28: Delivered
A29: ORD10032 | B29: Karan Bansal | C29: karan190@gmail.com | D29: Smart Watch | E29: Tech | F29: 68891.61 | G29: 5 | H29: 45789 | I29: Delhi | J29: India | K29: COD | L29: Delivered
A30: ORD10034 | B30: Rohit Mehta | C30: rohit25@gmail.com | D30: Tablet | F30: 69778.83 | G30: 4 | H30: 45993 | I30: Bangalore | J30: India | K30: Debit Card | L30: Cancelled
A31: ORD10035 | B31: Priya Arora | C31: priya81@gmail.com | D31: Keyboard | E31: Tech | F31: 16687.24 | G31: 4 | H31: 45176 | I31: Delhi | J31: India | K31: Debit Card | L31: Returned
A32: ORD10036 | B32: Amit Verma | C32: amit142@gmail.com | D32: Webcam | E32: Electronics | F32: 26604.03 | G32: 1 | H32: 45304 | I32: Chennai | J32: India | K32: COD | L32: Shipped
A33: ORD10037 | B33: Arjun Gupta | C33: arjun189@gmail.com | D33: Smart Watch | E33: Tech | F33: 3614.69 | G33: 5 | H33: 45738 | I33: Delhi | J33: India | K33: UPI | L33: Shipped
A34: ORD10038 | B34: Karan Bansal | C34: karan200@gmail.com | D34: Smart Watch | E34: Electronics | F34: 53870.17 | G34: 1 | H34: 45220 | I34: Ahmedabad | J34: India | K34: UPI | L34: Delivered
A35: ORD10039 | B35: Sneha Bansal | C35: sneha82@gmail.com | D35: Monitor | E35: Electronics | F35: 56457 | G35: 2 | H35: 45573 | I35: Mumbai | J35: India | K35: COD | L35: Returned
A36: ORD10040 | B36: Rahul Arora | C36: rahul168@gmail.com | D36: Monitor | E36: Electronics | F36: 76358.5 | G36: 5 | H36: 45900 | I36: Chennai | J36: India | K36: COD | L36: Returned
A37: ORD10041 | B37: Karan Arora | C37: karan21@gmail.com | D37: Monitor | E37: Gadgets | F37: 62553.22 | G37: 4 | H37: 45590 | I37: Ahmedabad | J37: India | K37: UPI | L37: Returned
A38: ORD10042 | B38: Meena Arora | C38: meena177@gmail.com | D38: Keyboard | E38: Gadgets | F38: 44902.7 | G38: 3 | H38: 45523 | I38: Mumbai | J38: India | K38: COD | L38: Delivered
A39: ORD10043 | B39: Karan Singh | C39: karan173@gmail.com | D39: USB Cable | E39: Gadgets | F39: 65641.99 | G39: 1 | H39: 44938 | I39: Mumbai | J39: India | K39: Debit Card | L39: Delivered
A40: ORD10044 | B40: Vikas Kapoor | C40: vikas115@gmail.com | D40: Webcam | E40: Electronics | F40: 61492.45 | G40: 5 | H40: 45861 | I40: Mumbai | J40: India | K40: Net Banking | L40: Returned
A41: ORD10045 | B41: Sneha Jain | C41: sneha36@gmail.com | D41: Monitor | E41: Electronics | F41: 36716.99 | G41: 4 | H41: 45532 | I41: Mumbai | J41: India | K41: Net Banking | L41: Returned
A42: ORD10046 | B42: Rahul Mehta | C42: rahul12@gmail.com | D42: Mouse | E42: Tech | F42: 8606.63 | G42: 2 | H42: 45148 | I42: Delhi | J42: India | K42: Debit Card | L42: Cancelled
... A50: ORD10056 | B50: Priya Bansal | C50: priya67@gmail.com | D50: Headphones | E50: Electronics | F50: 46796.64 | G50: 1 | H50: 45149 | I50: Hyderabad | J50: India | K50: COD | L50: Pending
A51: ORD10057 | B51: Pooja Singh | C51: pooja63@gmail.com | D51: Charger | E51: Tech | F51: 66710.92 | G51: 2 | H51: 45090 | J51: India | K51: UPI | L51: Shipped
A52: ORD10058 | B52: Pooja Arora | C52: pooja17@gmail.com | D52: Smart Watch | E52: Electronics | F52: 68011.56 | G52: 3 | H52: 45329 | I52: Mumbai | J52: India | K52: Net Banking | L52: Returned
A53: ORD10059 | B53: Meena Agarwal | C53: meena9@gmail.com | D53: Tablet | E53: Gadgets | F53: 29843.45 | G53: 2 | H53: 45748 | I53: Kolkata | J53: India | K53: COD | L53: Pending
A54: ORD10060 | B54: Neha Gupta | C54: neha5@gmail.com | D54: Headphones | E54: Electronics | G54: 3 | H54: 45365 | I54: Delhi | J54: India | K54: Net Banking | L54: Shipped
A55: ORD10061 | B55: Meena Verma | C55: meena156@gmail.com | D55: Keyboard | E55: Tech | F55: 71010.44 | G55: 5 | H55: 45308 | I55: Pune | J55: India | K55: Debit Card | L55: Pending
A56: ORD10062 | B56: Arjun Bansal | C56: arjun23@gmail.com | D56: Monitor | E56: Tech | F56: 25904.25 | G56: 4 | H56: 45287 | I56: Delhi | J56: India | K56: UPI | L56: Shipped
A57: ORD10063 | B57: Sneha Kapoor | C57: sneha173@gmail.com | D57: Smart Watch | E57: Electronics | F57: 51763.15 | G57: 4 | H57: 45390 | I57: Ahmedabad | J57: India | K57: Debit Card | L57: Returned
A58: ORD10064 | B58: Karan Kapoor | C58: karan18@gmail.com | D58: Mouse | E58: Tech | F58: 56908.54 | G58: 4 | H58: 45858 | I58: Ahmedabad | J58: India | K58: Debit Card | L58: Pending
A59: ORD10065 | B59: Meena Gupta | C59: meena48@gmail.com | D59: Charger | E59: Tech | F59: 27597.68 | G59: 3 | H59: 44939 | I59: Delhi | J59: India | K59: Credit Card | L59: Cancelled
A60: ORD10066 | B60: Karan Sharma | C60: karan12@gmail.com | D60: Keyboard | E60: Tech | F60: 3454.97 | G60: 3 | H60: 45735 | I60: Chennai | J60: India | K60: Net Banking | L60: Shipped
A61: ORD10067 | B61: Sneha Kapoor | C61: sneha54@gmail.com | D61: Headphones | E61: Gadgets | F61: 30232.95 | G61: 3 | H61: 45116 | I61: Delhi | J61: India | K61: Net Banking | L61: Delivered
A62: ORD10068 | B62: Arjun Gupta | C62: arjun60@gmail.com | D62: Charger | E62: Gadgets | F62: 19885.46 | G62: 5 | H62: 45948 | I62: Pune | J62: India | K62: COD | L62: Cancelled
A63: ORD10069 | B63: Pooja Gupta | C63: pooja1@gmail.com | D63: Tablet | E63: Electronics | F63: 55236.72 | G63: 2 | H63: 45438 | I63: Delhi | J63: India | K63: COD | L63: Cancelled
A64: ORD10070 | B64: Pooja Bansal | C64: pooja191@gmail.com | D64: Keyboard | E64: Electronics | F64: 64920.07 | G64: 1 | H64: 45867 | I64: Delhi | J64: India | K64: UPI | L64: Delivered
A65: ORD10072 | B65: Anjali Verma | C65: anjali189@gmail.com | D65: Headphones | E65: Electronics | F65: 16304.75 | G65: 4 | H65: 45316 | I65: Delhi | J65: India | K65: Credit Card | L65: Delivered
A66: ORD10075 | B66: Priya Gupta | C66: priya159@gmail.com | D66: Tablet | E66: Electronics | F66: 27303.67 | G66: 1 | H66: 45312 | I66: Bangalore | J66: India | K66: Debit Card | L66: Shipped
... A72: ORD10081 | B72: Amit Agarwal | C72: amit173@gmail.com | D72: Mouse | E72: Tech | F72: 34647.47 | G72: 1 | H72: 45897 | I72: Delhi | J72: India | K72: Net Banking | L72: Cancelled
A73: ORD10082 | B73: Arjun Verma | C73: arjun94@gmail.com | D73: Smart Watch | E73: Tech | F73: 56293.1 | G73: 4 | H73: 45007 | I73: Mumbai | K73: Net Banking | L73: Delivered
A74: ORD10083 | B74: Meena Agarwal | C74: meena71@gmail.com | D74: Smart Watch | E74: Electronics | F74: 38914.91 | G74: 4 | H74: 45823 | I74: Delhi | J74: India | K74: COD | L74: Shipped
A75: ORD10084 | B75: Priya Gupta | C75: priya46@gmail.com | D75: USB Cable | E75: Tech | F75: 23979.69 | G75: 4 | H75: 45252 | I75: Kolkata | J75: India | K75: UPI | L75: Returned
A76: ORD10085 | B76: Rahul Singh | C76: rahul112@gmail.com | D76: Tablet | E76: Electronics | F76: 78748.37 | G76: 2 | H76: 45035 | I76: Delhi | J76: India | K76: Credit Card | L76: Delivered
A77: ORD10086 | B77: Vikas Verma | C77: vikas2@gmail.com | D77: Charger | E77: Gadgets | F77: 33621.4 | G77: 1 | H77: 45359 | I77: Bangalore | J77: India | K77: UPI | L77: Returned
A78: ORD10087 | B78: Meena Jain | C78: meena161@gmail.com | D78: Headphones | E78: Gadgets | G78: 4 | H78: 45645 | I78: Bangalore | J78: India | K78: Net Banking | L78: Delivered
A79: ORD10088 | B79: Anjali Kapoor | C79: anjali170@gmail.com | D79: Laptop | E79: Electronics | F79: 44883.93 | G79: 2 | H79: 45251 | I79: Delhi | J79: India | K79: Net Banking | L79: Shipped
A80: ORD10089 | B80: Amit Arora | C80: amit70@gmail.com | D80: USB Cable | E80: Electronics | F80: 1140.64 | G80: 5 | H80: 45251 | I80: Delhi | J80: India | K80: UPI | L80: Cancelled
A81: ORD10090 | B81: Sneha Kapoor | C81: sneha67@gmail.com | D81: Charger | E81: Electronics | F81: 47358.82 | G81: 3 | H81: 45743 | I81: Mumbai | J81: India | K81: Net Banking | L81: Cancelled
A82: ORD10091 | B82: Sneha Verma | C82: sneha119@gmail.com | D82: Monitor | E82: Electronics | F82: 27875.15 | G82: 2 | H82: 45571 | I82: Ahmedabad | J82: India | K82: Credit Card | L82: Returned
A83: ORD10092 | B83: Anjali Gupta | C83: anjali27@gmail.com | D83: Monitor | E83: Electronics | F83: 44227.6 | G83: 3 | H83: 45925 | I83: Mumbai | J83: India | K83: UPI | L83: Shipped
A84: ORD10093 | B84: Rahul Jain | C84: rahul25@gmail.com | D84: Tablet | E84: Electronics | F84: 66503.95 | G84: 2 | H84: 45663 | I84: Pune | J84: India | K84: UPI | L84: Delivered
A85: ORD10094 | B85: Anjali Verma | C85: anjali156@gmail.com | D85: Laptop | E85: Tech | F85: 21034.14 | G85: 3 | H85: 45137 | I85: Mumbai | J85: India | K85: COD | L85: Cancelled
A86: ORD10095 | B86: Karan Gupta | C86: karan68@gmail.com | D86: Webcam | E86: Electronics | F86: 12974.65 | G86: 3 | H86: 45192 | I86: Delhi | J86: India | K86: UPI | L86: Shipped
A87: ORD10096 | B87: Meena Bansal | C87: meena132@gmail.com | D87: Laptop | E87: Gadgets | F87: 53959.92 | G87: 5 | H87: 45060 | I87: Mumbai | J87: India | K87: Debit Card | L87: Delivered
A88: ORD10097 | B88: Neha Kapoor | C88: neha199@gmail.com | D88: Smart Watch | E88: Electronics | F88: 78355.09 | G88: 5 | H88: 45615 | I88: Kolkata | J88: India | K88: Net Banking | L88: Cancelled
A89: ORD10098 | B89: Vikas Jain | C89: vikas29@gmail.com | D89: Webcam | E89: Gadgets | F89: 74955.82 | G89: 3 | H89: 45175 | I89: Pune | J89: India | K89: Debit Card | L89: Delivered
A90: ORD10099 | B90: Meena Gupta | C90: meena54@gmail.com | D90: Headphones | E90: Electronics | F90: 27902.09 | G90: 5 | H90: 45985 | I90: Delhi | J90: India | K90: Credit Card | L90: Delivered
... A93: ORD10102 | B93: Anjali Arora | C93: anjali157@gmail.com | D93: USB Cable | E93: Tech | F93: 24552.11 | G93: 4 | H93: 45400 | I93: Delhi | J93: India | K93: Debit Card | L93: Delivered
A94: ORD10103 | B94: Neha Sharma | C94: neha4@gmail.com | D94: Keyboard | E94: Tech | F94: 4602.22 | G94: 2 | H94: 45769 | I94: Mumbai | J94: India | L94: Delivered
A95: ORD10104 | B95: Vikas Agarwal | C95: vikas14@gmail.com | D95: Laptop | E95: Gadgets | F95: 58136.13 | G95: 4 | H95: 45097 | I95: Delhi | J95: India | K95: COD | L95: Delivered
A96: ORD10105 | B96: Neha Agarwal | C96: neha38@gmail.com | D96: Keyboard | E96: Electronics | F96: 29858 | G96: 1 | H96: 45596 | I96: Mumbai | J96: India | K96: COD | L96: Cancelled
A97: ORD10106 | B97: Rohit Verma | D97: Webcam | E97: Electronics | F97: 50160.21 | G97: 3 | H97: 45751 | I97: Kolkata | J97: India | K97: Debit Card | L97: Cancelled
A98: ORD10107 | B98: Vikas Singh | C98: vikas70@gmail.com | D98: Tablet | E98: Tech | F98: 14353.4 | G98: 3 | H98: 45695 | I98: Delhi | J98: India | K98: Credit Card | L98: Pending
A99: ORD10108 | B99: Neha Sharma | C99: neha126@gmail.com | D99: USB Cable | E99: Electronics | F99: 58399.52 | G99: 2 | H99: 45410 | I99: Kolkata | J99: India | K99: Credit Card | L99: Delivered
A100: ORD10109 | B100: Rohit Jain | C100: rohit138@gmail.com | D100: Charger | E100: Tech | F100: 61964.46 | G100: 2 | H100: 45915 | I100: Chennai | J100: India | K100: COD | L100: Cancelled
A101: ORD10110 | B101: Priya Mehta | C101: priya181@gmail.com | D101: Mouse | E101: Tech | F101: 8947.67 | G101: 1 | H101: 45068 | I101: Mumbai | J101: India | K101: Credit Card | L101: Pending
A102: ORD10111 | B102: Vikas Arora | C102: vikas24@gmail.com | D102: Tablet | E102: Electronics | F102: 60228.52 | G102: 3 | H102: 45543 | I102: Kolkata | J102: India | K102: COD | L102: Pending
A103: ORD10112 | B103: Sneha Mehta | C103: sneha106@gmail.com | D103: Smart Watch | E103: Electronics | F103: 2553.99 | G103: 1 | H103: 45256 | I103: Mumbai | J103: India | K103: Credit Card | L103: Delivered
A104: ORD10113 | B104: Karan Arora | C104: karan163@gmail.com | D104: Headphones | E104: Gadgets | F104: 48596.43 | G104: 4 | H104: 45832 | I104: Delhi | J104: India | K104: Net Banking | L104: Delivered
A105: ORD10114 | B105: Pooja Arora | C105: pooja1@gmail.com | D105: Tablet | E105: Tech | F105: 12768.13 | G105: 4 | H105: 45091 | I105: Pune | J105: India | K105: Debit Card | L105: Returned
A106: ORD10115 | B106: Anjali Jain | C106: anjali130@gmail.com | D106: Charger | E106: Gadgets | F106: 57172.52 | G106: 4 | H106: 44998 | I106: Bangalore | J106: India | K106: Debit Card | L106: Delivered
A107: ORD10116 | B107: Sneha Singh | C107: sneha186@gmail.com | D107: Mouse | E107: Electronics | F107: 16717.49 | G107: 1 | H107: 45194 | I107: Pune | J107: India | K107: UPI | L107: Cancelled
A108: ORD10117 | B108: Pooja Jain | C108: pooja132@gmail.com | D108: Keyboard | E108: Electronics | F108: 36598.81 | G108: 4 | H108: 45182 | I108: Kolkata | J108: India | K108: Debit Card | L108: Delivered
A109: ORD10118 | B109: Meena Mehta | C109: meena145@gmail.com | D109: Laptop | E109: Electronics | F109: 17508.19 | G109: 1 | H109: 45996 | I109: Bangalore | J109: India | K109: Debit Card | L109: Pending
... A4621: ORD14999 | B4621: Pooja Arora | C4621: pooja29@gmail.com | D4621: Tablet | E4621: Electronics | F4621: 44934.74 | G4621: 2 | H4621: 45628 | I4621: Mumbai | J4621: India | K4621: Debit Card | L4621: Shipped

Sheet Prompt-1 Output
B2: Here's a comprehensive overview of the Ecommerce_Sales_Data.xlsx workbook:
B4: 📋 Workbook Overview
B6: Attribute | C6: Details
B7: Worksheets | C7: 2 sheets: Sheet1 (empty), Ecommerce_Sales (active)
B8: Data Range | C8: A1:L4621
B9: Total Rows | C9: 4,621 (including header)
B10: Data Records | C10: 4,620 orders
B11: Total Columns | C11: 12
B13: 🔑 Key Columns
B15: Column | C15: Field Name | D15: Description | E15: Data Type
B16: A | C16: OrderID | D16: Unique order identifier (e.g., ORD10000) | E16: Text
B17: B | C17: CustomerName | D17: Customer's full name | E17: Text
B18: C | C18: Email | D18: Customer email address | E18: Text
B19: D | C19: Product | D19: Product purchased | E19: Text (10 products)
B20: E | C20: Category | D20: Product category | E20: Text (3 categories)
B21: F | C21: Price | D21: Order price value | E21: Numeric
B22: G | C22: Quantity | D22: Units ordered | E22: Numeric
B23: H | C23: OrderDate | D23: Date of order (serial number format) | E23: Date
B24: I | C24: City | D24: Customer city | E24: Text (8 cities)
B25: J | C25: Country | D25: Customer country | E25: Text
B26: K | C26: PaymentMethod | D26: Payment type used | E26: Text (5 methods)
B27: L | C27: OrderStatus | D27: Current order status | E27: Text (5 statuses)
B29: 📊 Data Characteristics
B31: Products (10)
B33: Charger, Tablet, Headphones, Mouse, USB Cable, Monitor, Webcam, Laptop, Keyboard, Smart Watch
B35: Categories (3)
B37: Tech, Electronics, Gadgets
B39: Cities (8)
B41: Delhi, Mumbai, Hyderabad, Kolkata, Chennai, Ahmedabad, Pune, Bangalore
B43: Payment Methods (5)
B45: Debit Card, Net Banking, Credit Card, UPI, COD
B47: Order Statuses (5)
B49: Delivered, Returned, Pending, Shipped, Cancelled
B53: ⚠️ Data Quality Issues
B55: Issue | C55: Count | D55: Affected Column
B56: Missing Email | C56: 3 | D56: Column C
B57: Missing Price | C57: 3 | D57: Column F
B58: Missing Category | C58: 1 | D58: Column E
B59: Missing City | C59: 1 | D59: Column I
B60: Missing Country | C60: 1 | D60: Column J
B61: Missing Payment Method | C61: 1 | D61: Column K
B63: Total records with issues: ~10 (some may overlap)
B67: 📈 Potential Analysis
B69: Analysis Type | C69: Description
B70: Revenue Analysis | C70: Total sales, average order value, revenue by product/category/city
B71: Sales Trends | C71: Monthly/quarterly order trends, seasonal patterns
B72: Product Performance | C72: Best-selling products, revenue contribution by product
B73: Geographic Analysis | C73: Sales distribution across cities, top-performing regions
B74: Payment Analysis | C74: Preferred payment methods, payment method by city
B75: Order Status Analysis | C75: Delivery rate, return rate, cancellation rate
B76: Customer Analysis | C76: Repeat customers, customer spending patterns
B77: Category Performance | C77: Revenue and quantity by category comparison
B80: Would you like me to perform any specific analysis on this data?

Sheet Prompt-2 Output
A1: OrderID | B1: CustomerName | C1: Email | D1: Product | E1: Category | F1: Price | G1: Quantity | H1: OrderDate | I1: City | J1: Country | K1: PaymentMethod | L1: OrderStatus
A2: ORD10000 | B2: Pooja Bansal | C2: pooja95@gmail.com | D2: Charger | E2: Tech | F2: 78572.14 | G2: 4 | H2: 45306 | I2: Delhi | J2: India | K2: Debit Card | L2: Delivered
A3: ORD10001 | B3: Sneha Verma | C3: sneha12@gmail.com | D3: Tablet | E3: Electronics | F3: 43393.19 | G3: 3 | H3: 45271 | I3: Mumbai | J3: India | K3: Net Banking | L3: Returned
A4: ORD10002 | B4: Arjun Singh | C4: arjun5@gmail.com | D4: Headphones | E4: Electronics | F4: 38208.78 | G4: 2 | H4: 45977 | I4: Hyderabad | J4: India | K4: Debit Card | L4: Pending
A5: ORD10003 | B5: Neha Singh | C5: neha3@gmail.com | D5: Headphones | E5: Electronics | F5: 44514.23 | G5: 5 | H5: 45466 | I5: Kolkata | J5: India | K5: Credit Card | L5: Shipped
A6: ORD10004 | B6: Neha Gupta | C6: neha60@gmail.com | D6: Mouse | E6: Electronics | F6: 73256.56 | G6: 3 | H6: 45582 | I6: Delhi | J6: India | K6: Credit Card | L6: Cancelled
A7: ORD10005 | B7: Meena Sharma | C7: meena84@gmail.com | D7: USB Cable | E7: Tech | F7: 67063.78 | G7: 3 | H7: 45543 | I7: Chennai | J7: India | K7: Credit Card | L7: Shipped
A8: ORD10006 | B8: Rohit Arora | C8: rohit138@gmail.com | D8: Monitor | E8: Electronics | F8: 64501.86 | G8: 1 | H8: 45443 | I8: Ahmedabad | J8: India | K8: UPI | L8: Delivered
A9: ORD10007 | B9: Sneha Verma | C9: sneha180@gmail.com | D9: Monitor | E9: Gadgets | F9: 61418.64 | G9: 1 | H9: 45804 | I9: Delhi | J9: India | K9: Debit Card | L9: Delivered
A10: ORD10009 | B10: Vikas Gupta | C10: vikas143@gmail.com | D10: Mouse | E10: Gadgets | F10: 5379.97 | G10: 2 | H10: 45580 | I10: Delhi | J10: India | K10: Credit Card | L10: Delivered
A11: ORD10010 | B11: Neha Kapoor | C11: neha49@gmail.com | D11: Charger | E11: Electronics | F11: 69761.1 | G11: 1 | H11: 45390 | I11: Mumbai | J11: India | K11: Net Banking | L11: Returned
A12: ORD10012 | B12: Arjun Sharma | C12: arjun46@gmail.com | D12: USB Cable | E12: Electronics | F12: 31399.6 | G12: 5 | H12: 45477 | I12: Pune | J12: India | K12: UPI | L12: Returned
A13: ORD10013 | B13: Rohit Jain | C13: rohit42@gmail.com | D13: Tablet | E13: Tech | F13: 18167.94 | G13: 2 | H13: 45357 | I13: Kolkata | J13: India | K13: Credit Card | L13: Delivered
A14: ORD10014 | B14: Anjali Mehta | D14: Webcam | E14: Electronics | F14: 32961.2 | G14: 2 | H14: 45966 | I14: Delhi | J14: India | K14: UPI | L14: Returned
A15: ORD10015 | B15: Priya Arora | C15: priya199@gmail.com | D15: Webcam | E15: Gadgets | F15: 46556.77 | G15: 4 | H15: 45895 | I15: Delhi | J15: India | K15: Credit Card | L15: Returned
A16: ORD10016 | B16: Anjali Jain | C16: anjali106@gmail.com | D16: Headphones | E16: Electronics | F16: 32137.43 | G16: 4 | H16: 45394 | I16: Pune | J16: India | K16: COD | L16: Delivered
A17: ORD10017 | B17: Karan Singh | C17: karan171@gmail.com | D17: Mouse | E17: Electronics | F17: 10041.37 | G17: 1 | H17: 45481 | I17: Delhi | J17: India | K17: COD | L17: Shipped
A18: ORD10018 | B18: Meena Mehta | C18: meena115@gmail.com | D18: USB Cable | E18: Electronics | F18: 26804.67 | G18: 3 | H18: 45509 | I18: Bangalore | J18: India | K18: COD | L18: Returned
A19: ORD10019 | B19: Pooja Kapoor | C19: pooja100@gmail.com | D19: USB Cable | E19: Electronics | F19: 17270.7 | G19: 4 | H19: 45085 | I19: Kolkata | J19: India | K19: COD | L19: Delivered
A20: ORD10020 | B20: Pooja Gupta | C20: pooja182@gmail.com | D20: Laptop | E20: Electronics | F20: 63424.46 | G20: 4 | H20: 45517 | I20: Delhi | J20: India | K20: UPI | L20: Shipped
A21: ORD10022 | B21: Rahul Jain | C21: rahul2@gmail.com | D21: USB Cable | E21: Tech | G21: 2 | H21: 45172 | I21: Ahmedabad | J21: India | K21: Debit Card | L21: Pending
A22: ORD10023 | B22: Vikas Bansal | C22: vikas80@gmail.com | D22: Monitor | E22: Gadgets | F22: 64877.35 | G22: 3 | H22: 45467 | I22: Hyderabad | J22: India | K22: COD | L22: Delivered
A23: ORD10024 | B23: Priya Gupta | C23: priya57@gmail.com | D23: Webcam | E23: Electronics | F23: 57783.79 | G23: 1 | H23: 45933 | I23: Kolkata | J23: India | K23: Debit Card | L23: Delivered
A24: ORD10025 | B24: Rahul Jain | C24: rahul200@gmail.com | D24: Monitor | E24: Electronics | F24: 74788.76 | G24: 2 | H24: 45540 | I24: Kolkata | J24: India | K24: COD | L24: Returned
A25: ORD10026 | B25: Neha Singh | C25: neha45@gmail.com | D25: Headphones | E25: Gadgets | F25: 10792.47 | G25: 2 | H25: 44956 | I25: Pune | J25: India | K25: UPI | L25: Delivered
A26: ORD10028 | B26: Sneha Singh | C26: sneha28@gmail.com | D26: Keyboard | E26: Gadgets | F26: 45547.47 | G26: 2 | H26: 45785 | I26: Bangalore | J26: India | K26: Net Banking | L26: Delivered
A27: ORD10030 | B27: Sneha Agarwal | D27: USB Cable | E27: Gadgets | F27: 73478.02 | G27: 3 | H27: 45111 | I27: Kolkata | J27: India | K27: Credit Card | L27: Cancelled
A28: ORD10031 | B28: Sneha Jain | C28: sneha109@gmail.com | D28: Charger | E28: Electronics | F28: 855.68 | G28: 3 | H28: 44933 | I28: Bangalore | J28: India | K28: Net Banking | L28: Delivered
A29: ORD10032 | B29: Karan Bansal | C29: karan190@gmail.com | D29: Smart Watch | E29: Tech | F29: 68891.61 | G29: 5 | H29: 45789 | I29: Delhi | J29: India | K29: COD | L29: Delivered
A30: ORD10034 | B30: Rohit Mehta | C30: rohit25@gmail.com | D30: Tablet | F30: 69778.83 | G30: 4 | H30: 45993 | I30: Bangalore | J30: India | K30: Debit Card | L30: Cancelled
A31: ORD10035 | B31: Priya Arora | C31: priya81@gmail.com | D31: Keyboard | E31: Tech | F31: 16687.24 | G31: 4 | H31: 45176 | I31: Delhi | J31: India | K31: Debit Card | L31: Returned
A32: ORD10036 | B32: Amit Verma | C32: amit142@gmail.com | D32: Webcam | E32: Electronics | F32: 26604.03 | G32: 1 | H32: 45304 | I32: Chennai | J32: India | K32: COD | L32: Shipped
A33: ORD10037 | B33: Arjun Gupta | C33: arjun189@gmail.com | D33: Smart Watch | E33: Tech | F33: 3614.69 | G33: 5 | H33: 45738 | I33: Delhi | J33: India | K33: UPI | L33: Shipped
A34: ORD10038 | B34: Karan Bansal | C34: karan200@gmail.com | D34: Smart Watch | E34: Electronics | F34: 53870.17 | G34: 1 | H34: 45220 | I34: Ahmedabad | J34: India | K34: UPI | L34: Delivered
A35: ORD10039 | B35: Sneha Bansal | C35: sneha82@gmail.com | D35: Monitor | E35: Electronics | F35: 56457 | G35: 2 | H35: 45573 | I35: Mumbai | J35: India | K35: COD | L35: Returned
A36: ORD10040 | B36: Rahul Arora | C36: rahul168@gmail.com | D36: Monitor | E36: Electronics | F36: 76358.5 | G36: 5 | H36: 45900 | I36: Chennai | J36: India | K36: COD | L36: Returned
A37: ORD10041 | B37: Karan Arora | C37: karan21@gmail.com | D37: Monitor | E37: Gadgets | F37: 62553.22 | G37: 4 | H37: 45590 | I37: Ahmedabad | J37: India | K37: UPI | L37: Returned
A38: ORD10042 | B38: Meena Arora | C38: meena177@gmail.com | D38: Keyboard | E38: Gadgets | F38: 44902.7 | G38: 3 | H38: 45523 | I38: Mumbai | J38: India | K38: COD | L38: Delivered
A39: ORD10043 | B39: Karan Singh | C39: karan173@gmail.com | D39: USB Cable | E39: Gadgets | F39: 65641.99 | G39: 1 | H39: 44938 | I39: Mumbai | J39: India | K39: Debit Card | L39: Delivered
A40: ORD10044 | B40: Vikas Kapoor | C40: vikas115@gmail.com | D40: Webcam | E40: Electronics | F40: 61492.45 | G40: 5 | H40: 45861 | I40: Mumbai | J40: India | K40: Net Banking | L40: Returned
A41: ORD10045 | B41: Sneha Jain | C41: sneha36@gmail.com | D41: Monitor | E41: Electronics | F41: 36716.99 | G41: 4 | H41: 45532 | I41: Mumbai | J41: India | K41: Net Banking | L41: Returned
A42: ORD10046 | B42: Rahul Mehta | C42: rahul12@gmail.com | D42: Mouse | E42: Tech | F42: 8606.63 | G42: 2 | H42: 45148 | I42: Delhi | J42: India | K42: Debit Card | L42: Cancelled
... A50: ORD10056 | B50: Priya Bansal | C50: priya67@gmail.com | D50: Headphones | E50: Electronics | F50: 46796.64 | G50: 1 | H50: 45149 | I50: Hyderabad | J50: India | K50: COD | L50: Pending
A51: ORD10057 | B51: Pooja Singh | C51: pooja63@gmail.com | D51: Charger | E51: Tech | F51: 66710.92 | G51: 2 | H51: 45090 | J51: India | K51: UPI | L51: Shipped
A52: ORD10058 | B52: Pooja Arora | C52: pooja17@gmail.com | D52: Smart Watch | E52: Electronics | F52: 68011.56 | G52: 3 | H52: 45329 | I52: Mumbai | J52: India | K52: Net Banking | L52: Returned
A53: ORD10059 | B53: Meena Agarwal | C53: meena9@gmail.com | D53: Tablet | E53: Gadgets | F53: 29843.45 | G53: 2 | H53: 45748 | I53: Kolkata | J53: India | K53: COD | L53: Pending
A54: ORD10060 | B54: Neha Gupta | C54: neha5@gmail.com | D54: Headphones | E54: Electronics | G54: 3 | H54: 45365 | I54: Delhi | J54: India | K54: Net Banking | L54: Shipped
A55: ORD10061 | B55: Meena Verma | C55: meena156@gmail.com | D55: Keyboard | E55: Tech | F55: 71010.44 | G55: 5 | H55: 45308 | I55: Pune | J55: India | K55: Debit Card | L55: Pending
A56: ORD10062 | B56: Arjun Bansal | C56: arjun23@gmail.com | D56: Monitor | E56: Tech | F56: 25904.25 | G56: 4 | H56: 45287 | I56: Delhi | J56: India | K56: UPI | L56: Shipped
A57: ORD10063 | B57: Sneha Kapoor | C57: sneha173@gmail.com | D57: Smart Watch | E57: Electronics | F57: 51763.15 | G57: 4 | H57: 45390 | I57: Ahmedabad | J57: India | K57: Debit Card | L57: Returned
A58: ORD10064 | B58: Karan Kapoor | C58: karan18@gmail.com | D58: Mouse | E58: Tech | F58: 56908.54 | G58: 4 | H58: 45858 | I58: Ahmedabad | J58: India | K58: Debit Card | L58: Pending
A59: ORD10065 | B59: Meena Gupta | C59: meena48@gmail.com | D59: Charger | E59: Tech | F59: 27597.68 | G59: 3 | H59: 44939 | I59: Delhi | J59: India | K59: Credit Card | L59: Cancelled
A60: ORD10066 | B60: Karan Sharma | C60: karan12@gmail.com | D60: Keyboard | E60: Tech | F60: 3454.97 | G60: 3 | H60: 45735 | I60: Chennai | J60: India | K60: Net Banking | L60: Shipped
A61: ORD10067 | B61: Sneha Kapoor | C61: sneha54@gmail.com | D61: Headphones | E61: Gadgets | F61: 30232.95 | G61: 3 | H61: 45116 | I61: Delhi | J61: India | K61: Net Banking | L61: Delivered
A62: ORD10068 | B62: Arjun Gupta | C62: arjun60@gmail.com | D62: Charger | E62: Gadgets | F62: 19885.46 | G62: 5 | H62: 45948 | I62: Pune | J62: India | K62: COD | L62: Cancelled
A63: ORD10069 | B63: Pooja Gupta | C63: pooja1@gmail.com | D63: Tablet | E63: Electronics | F63: 55236.72 | G63: 2 | H63: 45438 | I63: Delhi | J63: India | K63: COD | L63: Cancelled
A64: ORD10070 | B64: Pooja Bansal | C64: pooja191@gmail.com | D64: Keyboard | E64: Electronics | F64: 64920.07 | G64: 1 | H64: 45867 | I64: Delhi | J64: India | K64: UPI | L64: Delivered
A65: ORD10072 | B65: Anjali Verma | C65: anjali189@gmail.com | D65: Headphones | E65: Electronics | F65: 16304.75 | G65: 4 | H65: 45316 | I65: Delhi | J65: India | K65: Credit Card | L65: Delivered
A66: ORD10075 | B66: Priya Gupta | C66: priya159@gmail.com | D66: Tablet | E66: Electronics | F66: 27303.67 | G66: 1 | H66: 45312 | I66: Bangalore | J66: India | K66: Debit Card | L66: Shipped
... A72: ORD10081 | B72: Amit Agarwal | C72: amit173@gmail.com | D72: Mouse | E72: Tech | F72: 34647.47 | G72: 1 | H72: 45897 | I72: Delhi | J72: India | K72: Net Banking | L72: Cancelled
A73: ORD10082 | B73: Arjun Verma | C73: arjun94@gmail.com | D73: Smart Watch | E73: Tech | F73: 56293.1 | G73: 4 | H73: 45007 | I73: Mumbai | K73: Net Banking | L73: Delivered
A74: ORD10083 | B74: Meena Agarwal | C74: meena71@gmail.com | D74: Smart Watch | E74: Electronics | F74: 38914.91 | G74: 4 | H74: 45823 | I74: Delhi | J74: India | K74: COD | L74: Shipped
A75: ORD10084 | B75: Priya Gupta | C75: priya46@gmail.com | D75: USB Cable | E75: Tech | F75: 23979.69 | G75: 4 | H75: 45252 | I75: Kolkata | J75: India | K75: UPI | L75: Returned
A76: ORD10085 | B76: Rahul Singh | C76: rahul112@gmail.com | D76: Tablet | E76: Electronics | F76: 78748.37 | G76: 2 | H76: 45035 | I76: Delhi | J76: India | K76: Credit Card | L76: Delivered
A77: ORD10086 | B77: Vikas Verma | C77: vikas2@gmail.com | D77: Charger | E77: Gadgets | F77: 33621.4 | G77: 1 | H77: 45359 | I77: Bangalore | J77: India | K77: UPI | L77: Returned
A78: ORD10087 | B78: Meena Jain | C78: meena161@gmail.com | D78: Headphones | E78: Gadgets | G78: 4 | H78: 45645 | I78: Bangalore | J78: India | K78: Net Banking | L78: Delivered
A79: ORD10088 | B79: Anjali Kapoor | C79: anjali170@gmail.com | D79: Laptop | E79: Electronics | F79: 44883.93 | G79: 2 | H79: 45251 | I79: Delhi | J79: India | K79: Net Banking | L79: Shipped
A80: ORD10089 | B80: Amit Arora | C80: amit70@gmail.com | D80: USB Cable | E80: Electronics | F80: 1140.64 | G80: 5 | H80: 45251 | I80: Delhi | J80: India | K80: UPI | L80: Cancelled
A81: ORD10090 | B81: Sneha Kapoor | C81: sneha67@gmail.com | D81: Charger | E81: Electronics | F81: 47358.82 | G81: 3 | H81: 45743 | I81: Mumbai | J81: India | K81: Net Banking | L81: Cancelled
A82: ORD10091 | B82: Sneha Verma | C82: sneha119@gmail.com | D82: Monitor | E82: Electronics | F82: 27875.15 | G82: 2 | H82: 45571 | I82: Ahmedabad | J82: India | K82: Credit Card | L82: Returned
A83: ORD10092 | B83: Anjali Gupta | C83: anjali27@gmail.com | D83: Monitor | E83: Electronics | F83: 44227.6 | G83: 3 | H83: 45925 | I83: Mumbai | J83: India | K83: UPI | L83: Shipped
A84: ORD10093 | B84: Rahul Jain | C84: rahul25@gmail.com | D84: Tablet | E84: Electronics | F84: 66503.95 | G84: 2 | H84: 45663 | I84: Pune | J84: India | K84: UPI | L84: Delivered
A85: ORD10094 | B85: Anjali Verma | C85: anjali156@gmail.com | D85: Laptop | E85: Tech | F85: 21034.14 | G85: 3 | H85: 45137 | I85: Mumbai | J85: India | K85: COD | L85: Cancelled
A86: ORD10095 | B86: Karan Gupta | C86: karan68@gmail.com | D86: Webcam | E86: Electronics | F86: 12974.65 | G86: 3 | H86: 45192 | I86: Delhi | J86: India | K86: UPI | L86: Shipped
A87: ORD10096 | B87: Meena Bansal | C87: meena132@gmail.com | D87: Laptop | E87: Gadgets | F87: 53959.92 | G87: 5 | H87: 45060 | I87: Mumbai | J87: India | K87: Debit Card | L87: Delivered
A88: ORD10097 | B88: Neha Kapoor | C88: neha199@gmail.com | D88: Smart Watch | E88: Electronics | F88: 78355.09 | G88: 5 | H88: 45615 | I88: Kolkata | J88: India | K88: Net Banking | L88: Cancelled
A89: ORD10098 | B89: Vikas Jain | C89: vikas29@gmail.com | D89: Webcam | E89: Gadgets | F89: 74955.82 | G89: 3 | H89: 45175 | I89: Pune | J89: India | K89: Debit Card | L89: Delivered
A90: ORD10099 | B90: Meena Gupta | C90: meena54@gmail.com | D90: Headphones | E90: Electronics | F90: 27902.09 | G90: 5 | H90: 45985 | I90: Delhi | J90: India | K90: Credit Card | L90: Delivered
... A93: ORD10102 | B93: Anjali Arora | C93: anjali157@gmail.com | D93: USB Cable | E93: Tech | F93: 24552.11 | G93: 4 | H93: 45400 | I93: Delhi | J93: India | K93: Debit Card | L93: Delivered
A94: ORD10103 | B94: Neha Sharma | C94: neha4@gmail.com | D94: Keyboard | E94: Tech | F94: 4602.22 | G94: 2 | H94: 45769 | I94: Mumbai | J94: India | L94: Delivered
A95: ORD10104 | B95: Vikas Agarwal | C95: vikas14@gmail.com | D95: Laptop | E95: Gadgets | F95: 58136.13 | G95: 4 | H95: 45097 | I95: Delhi | J95: India | K95: COD | L95: Delivered
A96: ORD10105 | B96: Neha Agarwal | C96: neha38@gmail.com | D96: Keyboard | E96: Electronics | F96: 29858 | G96: 1 | H96: 45596 | I96: Mumbai | J96: India | K96: COD | L96: Cancelled
A97: ORD10106 | B97: Rohit Verma | D97: Webcam | E97: Electronics | F97: 50160.21 | G97: 3 | H97: 45751 | I97: Kolkata | J97: India | K97: Debit Card | L97: Cancelled
A98: ORD10107 | B98: Vikas Singh | C98: vikas70@gmail.com | D98: Tablet | E98: Tech | F98: 14353.4 | G98: 3 | H98: 45695 | I98: Delhi | J98: India | K98: Credit Card | L98: Pending
A99: ORD10108 | B99: Neha Sharma | C99: neha126@gmail.com | D99: USB Cable | E99: Electronics | F99: 58399.52 | G99: 2 | H99: 45410 | I99: Kolkata | J99: India | K99: Credit Card | L99: Delivered
A100: ORD10109 | B100: Rohit Jain | C100: rohit138@gmail.com | D100: Charger | E100: Tech | F100: 61964.46 | G100: 2 | H100: 45915 | I100: Chennai | J100: India | K100: COD | L100: Cancelled
A101: ORD10110 | B101: Priya Mehta | C101: priya181@gmail.com | D101: Mouse | E101: Tech | F101: 8947.67 | G101: 1 | H101: 45068 | I101: Mumbai | J101: India | K101: Credit Card | L101: Pending
A102: ORD10111 | B102: Vikas Arora | C102: vikas24@gmail.com | D102: Tablet | E102: Electronics | F102: 60228.52 | G102: 3 | H102: 45543 | I102: Kolkata | J102: India | K102: COD | L102: Pending
A103: ORD10112 | B103: Sneha Mehta | C103: sneha106@gmail.com | D103: Smart Watch | E103: Electronics | F103: 2553.99 | G103: 1 | H103: 45256 | I103: Mumbai | J103: India | K103: Credit Card | L103: Delivered
A104: ORD10113 | B104: Karan Arora | C104: karan163@gmail.com | D104: Headphones | E104: Gadgets | F104: 48596.43 | G104: 4 | H104: 45832 | I104: Delhi | J104: India | K104: Net Banking | L104: Delivered
A105: ORD10114 | B105: Pooja Arora | C105: pooja1@gmail.com | D105: Tablet | E105: Tech | F105: 12768.13 | G105: 4 | H105: 45091 | I105: Pune | J105: India | K105: Debit Card | L105: Returned
A106: ORD10115 | B106: Anjali Jain | C106: anjali130@gmail.com | D106: Charger | E106: Gadgets | F106: 57172.52 | G106: 4 | H106: 44998 | I106: Bangalore | J106: India | K106: Debit Card | L106: Delivered
A107: ORD10116 | B107: Sneha Singh | C107: sneha186@gmail.com | D107: Mouse | E107: Electronics | F107: 16717.49 | G107: 1 | H107: 45194 | I107: Pune | J107: India | K107: UPI | L107: Cancelled
A108: ORD10117 | B108: Pooja Jain | C108: pooja132@gmail.com | D108: Keyboard | E108: Electronics | F108: 36598.81 | G108: 4 | H108: 45182 | I108: Kolkata | J108: India | K108: Debit Card | L108: Delivered
A109: ORD10118 | B109: Meena Mehta | C109: meena145@gmail.com | D109: Laptop | E109: Electronics | F109: 17508.19 | G109: 1 | H109: 45996 | I109: Bangalore | J109: India | K109: Debit Card | L109: Pending
... A4621: ORD14999 | B4621: Pooja Arora | C4621: pooja29@gmail.com | D4621: Tablet | E4621: Electronics | F4621: 44934.74 | G4621: 2 | H4621: 45628 | I4621: Mumbai | J4621: India | K4621: Debit Card | L4621: Shipped

Sheet Prompt-3 Output
A1: OrderID | B1: CustomerName | C1: Email | D1: Product | E1: Category | F1: Price | G1: Quantity | H1: OrderDate | I1: City | J1: Country | K1: PaymentMethod | L1: OrderStatus
A2: ORD10000 | B2: Pooja Bansal | C2: pooja95@gmail.com | D2: Charger | E2: Tech | F2: 78572.14 | G2: 4 | H2: 45306 | I2: Delhi | J2: India | K2: Debit Card | L2: Delivered
A3: ORD10001 | B3: Sneha Verma | C3: sneha12@gmail.com | D3: Tablet | E3: Electronics | F3: 43393.19 | G3: 3 | H3: 45271 | I3: Mumbai | J3: India | K3: Net Banking | L3: Returned
A4: ORD10002 | B4: Arjun Singh | C4: arjun5@gmail.com | D4: Headphones | E4: Electronics | F4: 38208.78 | G4: 2 | H4: 45977 | I4: Hyderabad | J4: India | K4: Debit Card | L4: Pending
A5: ORD10003 | B5: Neha Singh | C5: neha3@gmail.com | D5: Headphones | E5: Electronics | F5: 44514.23 | G5: 5 | H5: 45466 | I5: Kolkata | J5: India | K5: Credit Card | L5: Shipped
A6: ORD10004 | B6: Neha Gupta | C6: neha60@gmail.com | D6: Mouse | E6: Electronics | F6: 73256.56 | G6: 3 | H6: 45582 | I6: Delhi | J6: India | K6: Credit Card | L6: Cancelled
A7: ORD10005 | B7: Meena Sharma | C7: meena84@gmail.com | D7: USB Cable | E7: Tech | F7: 67063.78 | G7: 3 | H7: 45543 | I7: Chennai | J7: India | K7: Credit Card | L7: Shipped
A8: ORD10006 | B8: Rohit Arora | C8: rohit138@gmail.com | D8: Monitor | E8: Electronics | F8: 64501.86 | G8: 1 | H8: 45443 | I8: Ahmedabad | J8: India | K8: UPI | L8: Delivered
A9: ORD10007 | B9: Sneha Verma | C9: sneha180@gmail.com | D9: Monitor | E9: Gadgets | F9: 61418.64 | G9: 1 | H9: 45804 | I9: Delhi | J9: India | K9: Debit Card | L9: Delivered
A10: ORD10009 | B10: Vikas Gupta | C10: vikas143@gmail.com | D10: Mouse | E10: Gadgets | F10: 5379.97 | G10: 2 | H10: 45580 | I10: Delhi | J10: India | K10: Credit Card | L10: Delivered
A11: ORD10010 | B11: Neha Kapoor | C11: neha49@gmail.com | D11: Charger | E11: Electronics | F11: 69761.1 | G11: 1 | H11: 45390 | I11: Mumbai | J11: India | K11: Net Banking | L11: Returned
A12: ORD10012 | B12: Arjun Sharma | C12: arjun46@gmail.com | D12: USB Cable | E12: Electronics | F12: 31399.6 | G12: 5 | H12: 45477 | I12: Pune | J12: India | K12: UPI | L12: Returned
A13: ORD10013 | B13: Rohit Jain | C13: rohit42@gmail.com | D13: Tablet | E13: Tech | F13: 18167.94 | G13: 2 | H13: 45357 | I13: Kolkata | J13: India | K13: Credit Card | L13: Delivered
... A4611: ORD14999 | B4611: Pooja Arora | C4611: pooja29@gmail.com | D4611: Tablet | E4611: Electronics | F4611: 44934.74 | G4611: 2 | H4611: 45628 | I4611: Mumbai | J4611: India | K4611: Debit Card | L4611: Shipped

Sheet Prompt-4 Output
B2: 📊 E-COMMERCE SALES DASHBOARD
B3: Comprehensive Sales Analysis by City and Product
B5: 🏙️ CITY-WISE ANALYSIS | F5: 📦 PRODUCT-WISE ANALYSIS | J5: 📈 KEY METRICS
B6: City | C6: Total Sales (₹) | D6: Order Count | J6: Total Revenue
B7: Ahmedabad | C7: =SUMIF('Prompt-3 Output'!I:I,"Ahmedabad",'Prompt-3 Output'!F:F) -> 20090781 | D7: =COUNTIF('Prompt-3 Output'!I:I,"Ahmedabad") -> 506 | F7: Charger | G7: =SUMIF('Prompt-3 Output'!D:D,"Charger",'Prompt-3 Output'!F:F) -> 17942120 | H7: =COUNTIF('Prompt-3 Output'!D:D,"Charger") -> 450 | J7: =C15 -> 1.8399705e+08
B8: Bangalore | C8: =SUMIF('Prompt-3 Output'!I:I,"Bangalore",'Prompt-3 Output'!F:F) -> 19904757 | D8: =COUNTIF('Prompt-3 Output'!I:I,"Bangalore") -> 523 | F8: Headphones | G8: =SUMIF('Prompt-3 Output'!D:D,"Headphones",'Prompt-3 Output'!F:F) -> 19139036 | H8: =COUNTIF('Prompt-3 Output'!D:D,"Headphones") -> 474
B9: Chennai | C9: =SUMIF('Prompt-3 Output'!I:I,"Chennai",'Prompt-3 Output'!F:F) -> 20152947 | D9: =COUNTIF('Prompt-3 Output'!I:I,"Chennai") -> 524 | F9: Keyboard | G9: =SUMIF('Prompt-3 Output'!D:D,"Keyboard",'Prompt-3 Output'!F:F) -> 18478175 | H9: =COUNTIF('Prompt-3 Output'!D:D,"Keyboard") -> 479 | J9: Total Orders
B10: Delhi | C10: =SUMIF('Prompt-3 Output'!I:I,"Delhi",'Prompt-3 Output'!F:F) -> 40287121 | D10: =COUNTIF('Prompt-3 Output'!I:I,"Delhi") -> 1021 | F10: Laptop | G10: =SUMIF('Prompt-3 Output'!D:D,"Laptop",'Prompt-3 Output'!F:F) -> 18616434 | H10: =COUNTIF('Prompt-3 Output'!D:D,"Laptop") -> 462 | J10: =D15 -> 4610
B11: Hyderabad | C11: =SUMIF('Prompt-3 Output'!I:I,"Hyderabad",'Prompt-3 Output'!F:F) -> 21001818 | D11: =COUNTIF('Prompt-3 Output'!I:I,"Hyderabad") -> 514 | F11: Monitor | G11: =SUMIF('Prompt-3 Output'!D:D,"Monitor",'Prompt-3 Output'!F:F) -> 18900594 | H11: =COUNTIF('Prompt-3 Output'!D:D,"Monitor") -> 467
B12: Kolkata | C12: =SUMIF('Prompt-3 Output'!I:I,"Kolkata",'Prompt-3 Output'!F:F) -> 20320735 | D12: =COUNTIF('Prompt-3 Output'!I:I,"Kolkata") -> 472 | F12: Mouse | G12: =SUMIF('Prompt-3 Output'!D:D,"Mouse",'Prompt-3 Output'!F:F) -> 18932174 | H12: =COUNTIF('Prompt-3 Output'!D:D,"Mouse") -> 469 | J12: Avg Order Value
B13: Mumbai | C13: =SUMIF('Prompt-3 Output'!I:I,"Mumbai",'Prompt-3 Output'!F:F) -> 21302650 | D13: =COUNTIF('Prompt-3 Output'!I:I,"Mumbai") -> 538 | F13: Smart Watch | G13: =SUMIF('Prompt-3 Output'!D:D,"Smart Watch",'Prompt-3 Output'!F:F) -> 18829190 | H13: =COUNTIF('Prompt-3 Output'!D:D,"Smart Watch") -> 449 | J13: =C15/D15 -> 39912.592
B14: Pune | C14: =SUMIF('Prompt-3 Output'!I:I,"Pune",'Prompt-3 Output'!F:F) -> 20936242 | D14: =COUNTIF('Prompt-3 Output'!I:I,"Pune") -> 512 | F14: Tablet | G14: =SUMIF('Prompt-3 Output'!D:D,"Tablet",'Prompt-3 Output'!F:F) -> 17877083 | H14: =COUNTIF('Prompt-3 Output'!D:D,"Tablet") -> 443
B15: TOTAL | C15: =SUM(C7:C14) -> 1.8399705e+08 | D15: =SUM(D7:D14) -> 4610 | F15: USB Cable | G15: =SUMIF('Prompt-3 Output'!D:D,"USB Cable",'Prompt-3 Output'!F:F) -> 17600999 | H15: =COUNTIF('Prompt-3 Output'!D:D,"USB Cable") -> 448 | J15: Top City
F16: Webcam | G16: =SUMIF('Prompt-3 Output'!D:D,"Webcam",'Prompt-3 Output'!F:F) -> 17681247 | H16: =COUNTIF('Prompt-3 Output'!D:D,"Webcam") -> 469 | J16: =INDEX(B7:B14,MATCH(MAX(C7:C14),C7:C14,0)) -> Delhi
B18: 📊 Sales by City (Column Chart) | F18: 📊 Sales by Product (Bar Chart) | J18: Top Product
J19: =INDEX(F7:F16,MATCH(MAX(G7:G16),G7:G16,0)) -> Headphones
B36: 🥧 City Sales Distribution | F36: 🍩 Product Sales Distribution
B62: 📋 Data Source: Cleaned E-commerce Sales Data (4,610 orders) | Dashboard created with Excel formulas (SUMIF, COUNTIF, INDEX-MATCH)
B63: Last Updated: 29/3/2026, 1:31:52 pm

Sheet Prompt-5 Output
B2: 📊 E-COMMERCE SALES ANALYTICS DASHBOARD
B3: Comprehensive Business Intelligence Report | Real-time Sales Performance Metrics
B6: 🎯 KEY PERFORMANCE INDICATORS
B8: 💰 TOTAL REVENUE | C8: 📦 TOTAL ORDERS | D8: 📈 AVG ORDER VALUE | F8: 🛍️ UNITS SOLD | G8: 🏆 TOP CITY | H8: ⭐ TOP PRODUCT
B9: =TEXT(SUMIF('Prompt-3 Output'!F:F,">0"),"₹#,##0") -> ₹18,39,97,051 | C9: =TEXT(COUNTA('Prompt-3 Output'!A:A)-1,"#,##0") -> 4,610 | D9: =TEXT(AVERAGEIF('Prompt-3 Output'!F:F,">0"),"₹#,##0") -> ₹39,913 | F9: =TEXT(SUM('Prompt-3 Output'!G:G),"#,##0") -> 13,935 | G9: Delhi | H9: Headphones
B10: All-time sales value | C10: Processed transactions | D10: Per order spending | F10: Total product quantity | G10: Highest revenue city | H10: Best selling product
B13: 🏙️ CITY-WISE SALES ANALYSIS | F13: 📦 PRODUCT-WISE SALES ANALYSIS | J13: 📂 CATEGORY ANALYSIS
B15: City | C15: Total Sales (₹) | D15: Orders | F15: Product | G15: Total Sales (₹) | H15: Orders | J15: Category | K15: Revenue (₹)
B16: Ahmedabad | C16: =SUMIF('Prompt-3 Output'!I:I,"Ahmedabad",'Prompt-3 Output'!F:F) -> 20090781 | D16: =COUNTIF('Prompt-3 Output'!I:I,"Ahmedabad") -> 506 | F16: Charger | G16: =SUMIF('Prompt-3 Output'!D:D,"Charger",'Prompt-3 Output'!F:F) -> 17942120 | H16: =COUNTIF('Prompt-3 Output'!D:D,"Charger") -> 450 | J16: Electronics | K16: =SUMIF('Prompt-3 Output'!E:E,"Electronics",'Prompt-3 Output'!F:F) -> 1.1046355e+08
B17: Bangalore | C17: =SUMIF('Prompt-3 Output'!I:I,"Bangalore",'Prompt-3 Output'!F:F) -> 19904757 | D17: =COUNTIF('Prompt-3 Output'!I:I,"Bangalore") -> 523 | F17: Headphones | G17: =SUMIF('Prompt-3 Output'!D:D,"Headphones",'Prompt-3 Output'!F:F) -> 19139036 | H17: =COUNTIF('Prompt-3 Output'!D:D,"Headphones") -> 474 | J17: Gadgets | K17: =SUMIF('Prompt-3 Output'!E:E,"Gadgets",'Prompt-3 Output'!F:F) -> 36113914
B18: Chennai | C18: =SUMIF('Prompt-3 Output'!I:I,"Chennai",'Prompt-3 Output'!F:F) -> 20152947 | D18: =COUNTIF('Prompt-3 Output'!I:I,"Chennai") -> 524 | F18: Keyboard | G18: =SUMIF('Prompt-3 Output'!D:D,"Keyboard",'Prompt-3 Output'!F:F) -> 18478175 | H18: =COUNTIF('Prompt-3 Output'!D:D,"Keyboard") -> 479 | J18: Tech | K18: =SUMIF('Prompt-3 Output'!E:E,"Tech",'Prompt-3 Output'!F:F) -> 37419585
B19: Delhi | C19: =SUMIF('Prompt-3 Output'!I:I,"Delhi",'Prompt-3 Output'!F:F) -> 40287121 | D19: =COUNTIF('Prompt-3 Output'!I:I,"Delhi") -> 1021 | F19: Laptop | G19: =SUMIF('Prompt-3 Output'!D:D,"Laptop",'Prompt-3 Output'!F:F) -> 18616434 | H19: =COUNTIF('Prompt-3 Output'!D:D,"Laptop") -> 462
B20: Hyderabad | C20: =SUMIF('Prompt-3 Output'!I:I,"Hyderabad",'Prompt-3 Output'!F:F) -> 21001818 | D20: =COUNTIF('Prompt-3 Output'!I:I,"Hyderabad") -> 514 | F20: Monitor | G20: =SUMIF('Prompt-3 Output'!D:D,"Monitor",'Prompt-3 Output'!F:F) -> 18900594 | H20: =COUNTIF('Prompt-3 Output'!D:D,"Monitor") -> 467
B21: Kolkata | C21: =SUMIF('Prompt-3 Output'!I:I,"Kolkata",'Prompt-3 Output'!F:F) -> 20320735 | D21: =COUNTIF('Prompt-3 Output'!I:I,"Kolkata") -> 472 | F21: Mouse | G21: =SUMIF('Prompt-3 Output'!D:D,"Mouse",'Prompt-3 Output'!F:F) -> 18932174 | H21: =COUNTIF('Prompt-3 Output'!D:D,"Mouse") -> 469 | J21: 📊 QUICK STATS
B22: Mumbai | C22: =SUMIF('Prompt-3 Output'!I:I,"Mumbai",'Prompt-3 Output'!F:F) -> 21302650 | D22: =COUNTIF('Prompt-3 Output'!I:I,"Mumbai") -> 538 | F22: Smart Watch | G22: =SUMIF('Prompt-3 Output'!D:D,"Smart Watch",'Prompt-3 Output'!F:F) -> 18829190 | H22: =COUNTIF('Prompt-3 Output'!D:D,"Smart Watch") -> 449
B23: Pune | C23: =SUMIF('Prompt-3 Output'!I:I,"Pune",'Prompt-3 Output'!F:F) -> 20936242 | D23: =COUNTIF('Prompt-3 Output'!I:I,"Pune") -> 512 | F23: Tablet | G23: =SUMIF('Prompt-3 Output'!D:D,"Tablet",'Prompt-3 Output'!F:F) -> 17877083 | H23: =COUNTIF('Prompt-3 Output'!D:D,"Tablet") -> 443 | J23: Highest Order Value: | K23: =MAX('Prompt-3 Output'!F:F) -> 79994.87
B24: TOTAL | C24: =SUM(C16:C23) -> 1.8399705e+08 | D24: =SUM(D16:D23) -> 4610 | F24: USB Cable | G24: =SUMIF('Prompt-3 Output'!D:D,"USB Cable",'Prompt-3 Output'!F:F) -> 17600999 | H24: =COUNTIF('Prompt-3 Output'!D:D,"USB Cable") -> 448 | J24: Lowest Order Value: | K24: =MIN('Prompt-3 Output'!F:F) -> 106.89
F25: Webcam | G25: =SUMIF('Prompt-3 Output'!D:D,"Webcam",'Prompt-3 Output'!F:F) -> 17681247 | H25: =COUNTIF('Prompt-3 Output'!D:D,"Webcam") -> 469 | J25: Avg Quantity/Order: | K25: =AVERAGE('Prompt-3 Output'!G:G) -> 3.0227766
F26: TOTAL | G26: =SUM(G16:G25) -> 1.8399705e+08 | H26: =SUM(H16:H25) -> 4610
B28: 📋 ORDER STATUS BREAKDOWN | F28: 💳 PAYMENT METHOD ANALYSIS
B30: Status | C30: Count | D30: Percentage | F30: Payment Method | G30: Orders | H30: Revenue (₹)
B31: Delivered | C31: =COUNTIF('Prompt-3 Output'!L:L,"Delivered") -> 1519 | D31: =C31/SUM($C$31:$C$35) -> 0.32950108 | F31: COD | G31: =COUNTIF('Prompt-3 Output'!K:K,"COD") -> 928 | H31: =SUMIF('Prompt-3 Output'!K:K,"COD",'Prompt-3 Output'!F:F) -> 34877382
B32: Shipped | C32: =COUNTIF('Prompt-3 Output'!L:L,"Shipped") -> 777 | D32: =C32/SUM($C$31:$C$35) -> 0.16854664 | F32: Credit Card | G32: =COUNTIF('Prompt-3 Output'!K:K,"Credit Card") -> 901 | H32: =SUMIF('Prompt-3 Output'!K:K,"Credit Card",'Prompt-3 Output'!F:F) -> 36003968
B33: Pending | C33: =COUNTIF('Prompt-3 Output'!L:L,"Pending") -> 739 | D33: =C33/SUM($C$31:$C$35) -> 0.16030369 | F33: Debit Card | G33: =COUNTIF('Prompt-3 Output'!K:K,"Debit Card") -> 937 | H33: =SUMIF('Prompt-3 Output'!K:K,"Debit Card",'Prompt-3 Output'!F:F) -> 38001647
B34: Cancelled | C34: =COUNTIF('Prompt-3 Output'!L:L,"Cancelled") -> 781 | D34: =C34/SUM($C$31:$C$35) -> 0.16941432 | F34: Net Banking | G34: =COUNTIF('Prompt-3 Output'!K:K,"Net Banking") -> 933 | H34: =SUMIF('Prompt-3 Output'!K:K,"Net Banking",'Prompt-3 Output'!F:F) -> 37717891
B35: Returned | C35: =COUNTIF('Prompt-3 Output'!L:L,"Returned") -> 794 | D35: =C35/SUM($C$31:$C$35) -> 0.17223427 | F35: UPI | G35: =COUNTIF('Prompt-3 Output'!K:K,"UPI") -> 911 | H35: =SUMIF('Prompt-3 Output'!K:K,"UPI",'Prompt-3 Output'!F:F) -> 37396164
B38: 💡 KEY BUSINESS INSIGHTS
B40: 📍 Geographic Performance
B41: • Delhi leads with highest revenue contribution, accounting for ~22% of total sales
B42: • Top 3 cities (Delhi, Mumbai, Hyderabad) generate over 45% of total revenue
B43: • All 8 cities show healthy sales activity with balanced distribution
B45: 📦 Product Performance
B46: • Headphones is the top-selling product by revenue
B47: • Electronics accessories (Headphones, Mouse, Monitor) dominate sales
B48: • All 10 products show consistent demand across the catalog
B50: 📊 Order Fulfillment
B51: • Track delivery rates and return percentages for operational efficiency
B52: • Monitor pending orders for inventory and logistics planning
... B112: Last Updated: 29-Mar-2026, 1:37 PM IST
